Workbook
Name a_c2_c0: Sheep!$K$245:$M$245
Name arable: General!$J$69:$J$77
Name ave_pad_distance: Mach!$B$5
Name bank_bal_start: Finance!$B$4
Name bas: Labour!$N$72:$P$76
Name BaseLevelInput: Annual!$K$464:$K$473
Name BaseLevelInput: Understory!$K$449:$K$458
Name capital_limit: Finance!$B$2
Name chem: Crop!$G$349:$AU$404
Name chem_by_lmu: Crop!$H$678:$Q$679
Name chem_cost: Crop!$G$286:$AA$341
Name chem_info: Crop!$I$694:$L$698
Name CPDry: Annual!$V$655:$V$664
Name CPDry: Understory!$V$640:$V$649
Name CPGrn: Annual!$X$519:$X$528
Name CPGrn: Understory!$X$504:$X$513
Name daily_harvest_hours: Mach!$B$8
Name daily_hours: Labour!$G$51:$J$55
Name daily_seed_hours: Mach!$B$10
Name Date_Destocking: Annual!$J$149:$S$149
Name Date_Destocking: Understory!$J$145:$S$145
Name Date_ResownGrazing: Annual!$J$155:$S$155
Name Date_ResownGrazing: Understory!$J$151:$S$151
Name Date_Seeding: Annual!$J$151:$S$151
Name Date_Seeding: Understory!$J$147:$S$147
Name DigDryAve: Annual!$J$655:$J$754
Name DigDryAve: Understory!$J$640:$J$739
Name DigDryRange: Annual!$K$655:$K$754
Name DigDryRange: Understory!$K$640:$K$739
Name DigGrn: Annual!$J$519:$R$618
Name DigGrn: Understory!$J$504:$R$603
Name DigPOC: Annual!$I$894:$R$903
Name DigPOC: Understory!$I$879:$R$888
Name DigRednSenesce: Annual!$T$519:$T$618
Name DigRednSenesce: Understory!$T$504:$T$603
Name DigSpread: Annual!$V$519:$V$618
Name DigSpread: Understory!$V$504:$V$603
Name dry_seed_start: Crop!$I$38
Name empty_rate: 'Sup Feed'!$H$77:$J$85
Name end_contract_seeding_gs1_z: Periods!$G$59:$P$59
Name end_wet_seeding_gs1_z: Periods!$G$52:$P$52
Name EndGS: Annual!$J$79:$S$79
Name EndGS: Understory!$J$75:$S$75
Name ErosionLimit: Annual!$K$920:$S$1019
Name ErosionLimit: Understory!$K$905:$S$1004
Name FaG_LMU: Annual!$M$164:$U$164
Name FaG_LMU: Understory!$M$160:$U$160
Name FaG_PropnGrn: Annual!$L$166
Name FaG_PropnGrn: Understory!$L$162
Name feed_freq: 'Sup Feed'!$O$75
Name feed_periods: Sheep!$J$67:$L$168
Name feed_rate: 'Sup Feed'!$N$78:$P$85
Name fert: Crop!$G$413:$AU$468
Name fert_by_lmu: Crop!$H$657:$Q$662
Name fert_info: Crop!$H$601:$K$606
Name fert_passes: Crop!$G$474:$AU$529
Name fert_prep: Labour!$N$100:$P$103
Name fixed_crop_monitoring: Labour!$E$127:$Q$128
Name fixed_rotphases: Crop!$H$162:$M$216
Name FOOatGrazing: Annual!$L$164

Sheet Home

Sheet General
C3: «
E4: Däta | G4: Property ID | I4: note
H6: ID | I6: EWW
C7: 0
G9: =G4 -> Property ID | W9: »
C13: «
G14: Landuses | I14: *These shoud match the landuse arrays in structural.py
P15: phase_can_change_kp7 | U15: phase_can_reduce_kp7
G16: Crop Landuses | H16: Exists | I16: Included | K16: Pasture landuses | L16: Exists | M16: Included | O16: All landuses | P16: =P107 -> Dry seeding | Q16: =Q107 -> Brk | R16: =R107 -> Quality brk | S16: =S107 -> Spring | U16: =P16 -> Dry seeding | V16: =Q16 -> Brk | W16: =R16 -> Quality brk | X16: =S16 -> Spring
G17: b | H17: TRUE | I17: TRUE | K17: a | L17: TRUE | M17: TRUE | O17: a | P17: TRUE | Q17: TRUE | R17: TRUE | S17: FALSE | U17: TRUE | V17: TRUE | W17: FALSE | X17: FALSE
G18: bd | H18: TRUE | I18: TRUE | K18: a2 | L18: TRUE | M18: TRUE | O18: a2 | P18: TRUE | Q18: TRUE | R18: TRUE | S18: FALSE | U18: TRUE | V18: TRUE | W18: TRUE | X18: FALSE
G19: f | H19: FALSE | I19: FALSE | K19: m | L19: TRUE | M19: TRUE | O19: b | P19: TRUE | Q19: TRUE | R19: TRUE | S19: FALSE | U19: TRUE | V19: TRUE | W19: FALSE | X19: FALSE
G20: h | H20: FALSE | I20: FALSE | K20: j | L20: FALSE | M20: FALSE | O20: bd | P20: TRUE | Q20: TRUE | R20: TRUE | S20: FALSE | U20: TRUE | V20: TRUE | W20: FALSE | X20: FALSE
G21: i | H21: FALSE | I21: FALSE | K21: jc | L21: FALSE | M21: FALSE | O21: f | P21: TRUE | Q21: TRUE | R21: TRUE | S21: FALSE | U21: TRUE | V21: TRUE | W21: FALSE | X21: FALSE
G22: k | H22: FALSE | I22: FALSE | K22: s | L22: TRUE | M22: TRUE | O22: h | P22: TRUE | Q22: TRUE | R22: TRUE | S22: FALSE | U22: TRUE | V22: TRUE | W22: FALSE | X22: FALSE
G23: l | H23: TRUE | I23: TRUE | K23: sp | L23: TRUE | M23: FALSE | O23: i | P23: TRUE | Q23: TRUE | R23: TRUE | S23: FALSE | U23: TRUE | V23: TRUE | W23: FALSE | X23: FALSE
G24: lf | H24: TRUE | I24: TRUE | K24: t | L24: FALSE | M24: FALSE | O24: j | P24: TRUE | Q24: TRUE | R24: TRUE | S24: FALSE | U24: TRUE | V24: TRUE | W24: FALSE | X24: FALSE
G25: ms | H25: FALSE | I25: FALSE | K25: tc | L25: FALSE | M25: FALSE | O25: jc | P25: TRUE | Q25: TRUE | R25: TRUE | S25: FALSE | U25: TRUE | V25: TRUE | W25: FALSE | X25: FALSE
G26: o | H26: TRUE | I26: TRUE | K26: u | L26: FALSE | M26: FALSE | O26: k | P26: TRUE | Q26: TRUE | R26: TRUE | S26: FALSE | U26: TRUE | V26: TRUE | W26: FALSE | X26: FALSE
G27: od | H27: TRUE | I27: TRUE | K27: uc | L27: FALSE | M27: FALSE | O27: l | P27: TRUE | Q27: TRUE | R27: TRUE | S27: FALSE | U27: TRUE | V27: TRUE | W27: FALSE | X27: FALSE
G28: of | H28: TRUE | I28: TRUE | K28: x | L28: FALSE | M28: FALSE | O28: lf | P28: TRUE | Q28: TRUE | R28: TRUE | S28: FALSE | U28: TRUE | V28: TRUE | W28: FALSE | X28: FALSE
G29: r | H29: TRUE | I29: TRUE | K29: xc | L29: FALSE | M29: FALSE | O29: m | P29: TRUE | Q29: TRUE | R29: TRUE | S29: FALSE | U29: TRUE | V29: TRUE | W29: FALSE | X29: FALSE
G30: rd | H30: TRUE | I30: TRUE | O30: ms | P30: TRUE | Q30: TRUE | R30: TRUE | S30: FALSE | U30: TRUE | V30: TRUE | W30: FALSE | X30: FALSE
G31: v | H31: FALSE | I31: FALSE | O31: o | P31: TRUE | Q31: TRUE | R31: TRUE | S31: FALSE | U31: TRUE | V31: TRUE | W31: FALSE | X31: FALSE
G32: w | H32: TRUE | I32: TRUE | O32: od | P32: TRUE | Q32: TRUE | R32: TRUE | S32: FALSE | U32: TRUE | V32: TRUE | W32: FALSE | X32: FALSE
G33: wd | H33: TRUE | I33: TRUE | O33: of | P33: TRUE | Q33: TRUE | R33: TRUE | S33: FALSE | U33: TRUE | V33: TRUE | W33: FALSE | X33: FALSE
G34: z | H34: TRUE | I34: TRUE | O34: r | P34: TRUE | Q34: TRUE | R34: TRUE | S34: FALSE | U34: TRUE | V34: TRUE | W34: FALSE | X34: FALSE
G35: zd | H35: TRUE | I35: TRUE | O35: rd | P35: TRUE | Q35: TRUE | R35: TRUE | S35: FALSE | U35: TRUE | V35: TRUE | W35: FALSE | X35: FALSE
O36: s | P36: TRUE | Q36: TRUE | R36: TRUE | S36: FALSE | U36: TRUE | V36: TRUE | W36: FALSE | X36: FALSE
O37: sp | P37: TRUE | Q37: TRUE | R37: TRUE | S37: FALSE | U37: TRUE | V37: TRUE | W37: FALSE | X37: FALSE
O38: t | P38: TRUE | Q38: TRUE | R38: TRUE | S38: FALSE | U38: TRUE | V38: TRUE | W38: FALSE | X38: FALSE
O39: tc | P39: TRUE | Q39: TRUE | R39: TRUE | S39: FALSE | U39: TRUE | V39: TRUE | W39: FALSE | X39: FALSE
O40: u | P40: TRUE | Q40: TRUE | R40: TRUE | S40: FALSE | U40: TRUE | V40: TRUE | W40: FALSE | X40: FALSE
O41: uc | P41: TRUE | Q41: TRUE | R41: TRUE | S41: FALSE | U41: TRUE | V41: TRUE | W41: FALSE | X41: FALSE
O42: v | P42: TRUE | Q42: TRUE | R42: TRUE | S42: FALSE | U42: TRUE | V42: TRUE | W42: FALSE | X42: FALSE
O43: w | P43: TRUE | Q43: TRUE | R43: TRUE | S43: FALSE | U43: TRUE | V43: TRUE | W43: FALSE | X43: FALSE
O44: wd | P44: TRUE | Q44: TRUE | R44: TRUE | S44: FALSE | U44: TRUE | V44: TRUE | W44: FALSE | X44: FALSE
O45: x | P45: TRUE | Q45: TRUE | R45: TRUE | S45: FALSE | U45: TRUE | V45: TRUE | W45: FALSE | X45: FALSE
O46: xc | P46: TRUE | Q46: TRUE | R46: TRUE | S46: FALSE | U46: TRUE | V46: TRUE | W46: FALSE | X46: FALSE
O47: z | P47: TRUE | Q47: TRUE | R47: TRUE | S47: FALSE | U47: TRUE | V47: TRUE | W47: FALSE | X47: FALSE
O48: zd | P48: TRUE | Q48: TRUE | R48: TRUE | S48: FALSE | U48: TRUE | V48: TRUE | W48: FALSE | X48: FALSE
G54: =G14 -> Landuses | Y54: »
C59: «
E60: Däta | G60: Areas
C63: 0
G67: Area | M67: Costs - farm specific | Q67: Paddock Size
G68: lmu | H68: area | I68: non-cropable area | J68: Arable propn | M68: rail_cartage | N68: 28.1 | Q68: 80
G69: lmu0 | H69: 1096.74 | I69: 0 | J69: 1
G70: lmu1 | H70: 1096.74 | I70: 0 | J70: 1 | M70: road_cartage_distance | N70: 25
G71: lmu2 | H71: 548.37 | I71: 0 | J71: 1
G72: lmu3 | H72: 548.37 | I72: 0 | J72: 1
G73: lmu4 | H73: 822.555 | I73: 0 | J73: 1
G74: lmu5 | H74: 1096.74 | I74: 0 | J74: 1
G75: lmu6 | H75: 274.185 | I75: 0 | J75: 1
G76: lmu7 | H76: 609.3 | I76: 0 | J76: 1
G77: lmu8 | H77: 0 | I77: 0 | J77: 1
G84: =G60 -> Areas | W84: »
C88: «
E89: Däta | G89: Pastures Included | J89: Note
I90: Annual | J90: Lucerne | K90: Tedera | L90: Understory
H91: Exists? | I91: TRUE | J91: FALSE | K91: FALSE | L91: TRUE
H92: Included? | I92: TRUE | J92: FALSE | K92: FALSE | L92: FALSE
C93: 0
G95: =G89 -> Pastures Included | W95: »
C99: «
E100: Däta | G100: Season Types
L102: Note: add to the table below when the inputs for other seasons exist
C103: 0
J106: Description of season | N106: Identification node date | P106: Nodes | U106: Break of season | W106: Nodes | AB106: Break of season | AD106: Growing season end
J107: Erly rain - Quality Brk - win & spr rain | L107: probability | M107: included | P107: Dry seeding | Q107: Brk | R107: Quality brk | S107: Spring | W107: =P107 -> Dry seeding | X107: =Q107 -> Brk | Y107: =R107 -> Quality brk | Z107: =S107 -> Spring | AD107: gs0 | AE107: gs1
J108: Typical | K108: typ | L108: 1 | M108: =NOT(OR(M109:M117)) -> TRUE | N108: =W108 -> 91 | P108: =Periods!G21 -> 43560 | Q108: =Periods!F$22 -> 43600 | R108: =Periods!$J$23 -> 43631 | S108: =Periods!$G$25 -> 43709 | U108: =Periods!$F$22 -> 43600 | W108: =MIN(51,INT((P108 - DATE(YEAR(P108),1,1))/7))*7 -> 91 | X108: =MIN(51,INT((Q108 - DATE(YEAR(Q108),1,1))/7))*7 -> 133 | Y108: =MIN(51,INT((R108 - DATE(YEAR(R108),1,1))/7))*7 -> 161 | Z108: =MIN(51,INT((S108 - DATE(YEAR(S108),1,1))/7))*7 -> 238 | AB108: =MIN(51,INT((U108 - DATE(YEAR(U108),1,1))/7))*7 -> 133 | AD108: -1 | AE108: -1
J109: GoodNoGood | K109: z0 | L109: 0.090909091 | M109: FALSE | N109: =W109 -> 91 | P109: =P108 -> 43560 | Q109: =Periods!G$22 -> 43589 | R109: =Periods!$J$23 -> 43631 | S109: =Periods!$G$25 -> 43709 | U109: =Periods!G22 -> 43589 | W109: =MIN(51,INT((P109 - DATE(YEAR(P109),1,1))/7))*7 -> 91 | X109: =MIN(51,INT((Q109 - DATE(YEAR(Q109),1,1))/7))*7 -> 119 | Y109: =MIN(51,INT((R109 - DATE(YEAR(R109),1,1))/7))*7 -> 161 | Z109: =MIN(51,INT((S109 - DATE(YEAR(S109),1,1))/7))*7 -> 238 | AB109: =MIN(51,INT((U109 - DATE(YEAR(U109),1,1))/7))*7 -> 119
J110: GoodNoLow | K110: z1 | L110: 0.15909091 | M110: FALSE | N110: =Z110 -> 238 | P110: =P109 -> 43560 | Q110: =Q109 -> 43589 | R110: =R109 -> 43631 | S110: =S109 -> 43709 | U110: =U109 -> 43589 | W110: =MIN(51,INT((P110 - DATE(YEAR(P110),1,1))/7))*7 -> 91 | X110: =MIN(51,INT((Q110 - DATE(YEAR(Q110),1,1))/7))*7 -> 119 | Y110: =MIN(51,INT((R110 - DATE(YEAR(R110),1,1))/7))*7 -> 161 | Z110: =MIN(51,INT((S110 - DATE(YEAR(S110),1,1))/7))*7 -> 238 | AB110: =MIN(51,INT((U110 - DATE(YEAR(U110),1,1))/7))*7 -> 119
J111: GoodYesGood | K111: z2 | L111: 0.13636364 | M111: FALSE | N111: =Y111 -> 161 | P111: =P110 -> 43560 | Q111: =Q110 -> 43589 | R111: =R110 -> 43631 | S111: =S110 -> 43709 | U111: =U110 -> 43589 | W111: =MIN(51,INT((P111 - DATE(YEAR(P111),1,1))/7))*7 -> 91 | X111: =MIN(51,INT((Q111 - DATE(YEAR(Q111),1,1))/7))*7 -> 119 | Y111: =MIN(51,INT((R111 - DATE(YEAR(R111),1,1))/7))*7 -> 161 | Z111: =MIN(51,INT((S111 - DATE(YEAR(S111),1,1))/7))*7 -> 238 | AB111: =MIN(51,INT((U111 - DATE(YEAR(U111),1,1))/7))*7 -> 119
J112: GoodYesLow | K112: z3 | L112: 0.11363636 | M112: FALSE | N112: =Z112 -> 238 | P112: =P111 -> 43560 | Q112: =Q111 -> 43589 | R112: =R111 -> 43631 | S112: =S111 -> 43709 | U112: =U111 -> 43589 | W112: =MIN(51,INT((P112 - DATE(YEAR(P112),1,1))/7))*7 -> 91 | X112: =MIN(51,INT((Q112 - DATE(YEAR(Q112),1,1))/7))*7 -> 119 | Y112: =MIN(51,INT((R112 - DATE(YEAR(R112),1,1))/7))*7 -> 161 | Z112: =MIN(51,INT((S112 - DATE(YEAR(S112),1,1))/7))*7 -> 238 | AB112: =MIN(51,INT((U112 - DATE(YEAR(U112),1,1))/7))*7 -> 119
J113: LowNoGood | K113: z4 | L113: 0.11363636 | M113: FALSE | N113: =W113 -> 91 | P113: =P112 -> 43560 | Q113: =Periods!K$22 -> 43606 | R113: =R112 -> 43631 | S113: =Periods!$K$25 -> 43709 | U113: =Periods!K22 -> 43606 | W113: =MIN(51,INT((P113 - DATE(YEAR(P113),1,1))/7))*7 -> 91 | X113: =MIN(51,INT((Q113 - DATE(YEAR(Q113),1,1))/7))*7 -> 140 | Y113: =MIN(51,INT((R113 - DATE(YEAR(R113),1,1))/7))*7 -> 161 | Z113: =MIN(51,INT((S113 - DATE(YEAR(S113),1,1))/7))*7 -> 238 | AB113: =MIN(51,INT((U113 - DATE(YEAR(U113),1,1))/7))*7 -> 140
J114: LowNoLow | K114: z5 | L114: 0.13636364 | M114: FALSE | N114: =Z114 -> 238 | P114: =P113 -> 43560 | Q114: =Q113 -> 43606 | R114: =R113 -> 43631 | S114: =S113 -> 43709 | U114: =U113 -> 43606 | W114: =MIN(51,INT((P114 - DATE(YEAR(P114),1,1))/7))*7 -> 91 | X114: =MIN(51,INT((Q114 - DATE(YEAR(Q114),1,1))/7))*7 -> 140 | Y114: =MIN(51,INT((R114 - DATE(YEAR(R114),1,1))/7))*7 -> 161 | Z114: =MIN(51,INT((S114 - DATE(YEAR(S114),1,1))/7))*7 -> 238 | AB114: =MIN(51,INT((U114 - DATE(YEAR(U114),1,1))/7))*7 -> 140
J115: LowYesGood | K115: z6 | L115: 0.15909091 | M115: FALSE | N115: =Y115 -> 161 | P115: =P114 -> 43560 | Q115: =Q114 -> 43606 | R115: =R114 -> 43631 | S115: =S114 -> 43709 | U115: =U114 -> 43606 | W115: =MIN(51,INT((P115 - DATE(YEAR(P115),1,1))/7))*7 -> 91 | X115: =MIN(51,INT((Q115 - DATE(YEAR(Q115),1,1))/7))*7 -> 140 | Y115: =MIN(51,INT((R115 - DATE(YEAR(R115),1,1))/7))*7 -> 161 | Z115: =MIN(51,INT((S115 - DATE(YEAR(S115),1,1))/7))*7 -> 238 | AB115: =MIN(51,INT((U115 - DATE(YEAR(U115),1,1))/7))*7 -> 140
J116: LowYesLow | K116: z7 | L116: 0.090909091 | M116: FALSE | N116: =Z116 -> 238 | P116: =P115 -> 43560 | Q116: =Q115 -> 43606 | R116: =R115 -> 43631 | S116: =S115 -> 43709 | U116: =U115 -> 43606 | W116: =MIN(51,INT((P116 - DATE(YEAR(P116),1,1))/7))*7 -> 91 | X116: =MIN(51,INT((Q116 - DATE(YEAR(Q116),1,1))/7))*7 -> 140 | Y116: =MIN(51,INT((R116 - DATE(YEAR(R116),1,1))/7))*7 -> 161 | Z116: =MIN(51,INT((S116 - DATE(YEAR(S116),1,1))/7))*7 -> 238 | AB116: =MIN(51,INT((U116 - DATE(YEAR(U116),1,1))/7))*7 -> 140
J117: Not in Use | K117: z8 | L117: 0 | M117: FALSE | N117: =Z117 -> 238 | P117: =P116 -> 43560 | Q117: =Q116 -> 43606 | R117: =R116 -> 43631 | S117: =S116 -> 43709 | U117: =U116 -> 43606 | W117: =MIN(51,INT((P117 - DATE(YEAR(P117),1,1))/7))*7 -> 91 | X117: =MIN(51,INT((Q117 - DATE(YEAR(Q117),1,1))/7))*7 -> 140 | Y117: =MIN(51,INT((R117 - DATE(YEAR(R117),1,1))/7))*7 -> 161 | Z117: =MIN(51,INT((S117 - DATE(YEAR(S117),1,1))/7))*7 -> 238 | AB117: =MIN(51,INT((U117 - DATE(YEAR(U117),1,1))/7))*7 -> 140
O118: is FVP | P118: FALSE | Q118: FALSE | R118: FALSE | S118: FALSE
G119: Total | L119: =SUM(L109:L118) -> 1 | M119: =IF(L119<>1,"Error","")
G121: =G100 -> Season Types | AF121: »
C125: «
E126: Däta | G126: FINANCE - ANNUAL OVERHEADS
G127: Cost Item x Annual Cost
G128: 38576.729 | H128: Updated May 05 from Bankwest Benchmarks 03/04
C129: 0
J133: Annual Cost
I134: Electricity, gas | J134: 12000
I135: Shire rates & licenses | J135: 55000
I136: Blank | J136: 0
I137: Professional services, bank charges | J137: 15000
I138: Household, education | J138: 0
I139: phone & internet | J139: 2000
I140: Insurance (not inc in machinery) | J140: 15000
I141: Superannuation | J141: 0
I142: other | J142: 5000
G144: Total | J144: =SUM(J134:J142) -> 104000
G146: =G126 -> FINANCE - ANNUAL OVERHEADS | W146: »
...

Sheet Sup Feed
C3: «
E4: Däta | G4: LIVESTOCK FEEDS - FEED STORAGE CAPITAL COSTS
G5: Cost Item x Storage Type
G6: 43614 | I6: *Auger depriciation is accounted for in Mach sheet
C7: 0
J10: Grain Silo | K10: Hay Shed
J13: grain | K13: hay
I14: capacity | J14: 70 | K14: 120
I15: price | J15: 4760 | K15: 6752 | L15: $ | M15: *start price and end price are probably a bit low?
I16: life | J16: 30 | K16: 30 | L16: Years
I17: salvage value | J17: =J15/EXP(J16*LN(1.2)) -> 20.052548 | K17: =K15/EXP(K16*LN(1.2)) -> 28.444287 | L17: $
I18: other | J18: 3.6 | K18: 0 | L18: $/t
G20: =G4 -> LIVESTOCK FEEDS - FEED STORAGE CAPITAL COSTS | W20: »
C23: «
E24: Däta | G24: LIVESTOCK FEEDS - CONFINEMENT INFRASTRUCTURE COSTS
G26: 43909
C27: 0
K31: Dep - fixed | N31: R&M - variable
J32: price | K32: 15000 | L32: $ | N32: 4.5 | O32: $/t
J33: life | K33: 30 | L33: Years
J34: salvage value | K34: =K32/EXP(K33*LN(1.2)) -> 63.190803 | L34: $
G36: =G24 -> LIVESTOCK FEEDS - CONFINEMENT INFRASTRUCTURE COSTS | W36: »
C40: «
E41: Däta | G41: LIVESTOCK FEEDS - STORAGE COSTS
G42: Date to incur variable costs
G43: 43909
C44: 0
J49: date | K49: =MIN(364,INT((L49 - DATE(YEAR(L49),1,1)))) -> 341 | L49: 43807
G52: =G41 -> LIVESTOCK FEEDS - STORAGE COSTS | W52: »
C55: « | D55: 969.17525
D56: -40.80873 | E56: Däta | G56: LABOUR GRAIN FEEDING - LABOUR REQUIREMENT FOR GRAIN FEEDING SHEEP
G57: Filling & Emptying the Feeder
G58: 37780.587
C59: 1 | G59: Revised? | K59: info
K62: Time required to feed
K63: hrs/t
G65: Filling sheep feeder & get to paddock
H67: grain | I67: hay
G68: drive time | H68: 0.1 | I68: 0.2 | J68: hr | K68: =H68*60 -> 6 | L68: =I68*60 -> 12 | M68: mins
G69: fill time | H69: 0.1 | I69: 0.1 | J69: hr/load | K69: =H69*60 -> 6 | L69: =I69*60 -> 6 | M69: mins
G70: capacity | H70: 2 | I70: 2 | J70: cu metre
H71: =(H68+H69)/H70 -> 0.1 | I71: =(I68+I69)/I70 -> 0.15 | J71: hr/m3
N72: Transport between paddocks | Q72: note
H74: Emptying the feeder | N74: time | O74: 0.2 | P74: hr/paddock | Q74: =O74*60 -> 12 | R74: mins
N75: Frequency of feeding | O75: 2 | P75: /week
I77: grain | J77: hay
G78: date | H78: DOY | I78: empty rate lupins | J78: empty rate | N78: DOY | O78: feed rate | P78: mob size
G79: 43466 | H79: =MIN(364,INT((G79 - DATE(YEAR(G79),1,1)))) -> 0 | I79: 1.8 | J79: 10 | N79: =H79 -> 0 | O79: 100 | P79: 500
G80: 43525 | H80: =MIN(364,INT((G80 - DATE(YEAR(G80),1,1)))) -> 59 | I80: 1.8 | J80: 10 | N80: =H80 -> 59 | O80: 150 | P80: 500
G81: 43556 | H81: =MIN(364,INT((G81 - DATE(YEAR(G81),1,1)))) -> 90 | I81: 3.6 | J81: 10 | N81: =H81 -> 90 | O81: 200 | P81: 500
G82: 43615 | H82: =MIN(364,INT((G82 - DATE(YEAR(G82),1,1)))) -> 149 | I82: 1.8 | J82: 10 | N82: =H82 -> 149 | O82: 150 | P82: 500
G83: 43620 | H83: =MIN(364,INT((G83 - DATE(YEAR(G83),1,1)))) -> 154 | I83: 1.8 | J83: 10 | N83: =H83 -> 154 | O83: 100 | P83: 500
G84: 43678 | H84: =MIN(364,INT((G84 - DATE(YEAR(G84),1,1)))) -> 212 | I84: 1.8 | J84: 10 | N84: =H84 -> 212 | O84: 30 | P84: 500
G85: 43824 | H85: =MIN(364,INT((G85 - DATE(YEAR(G85),1,1)))) -> 358 | I85: 1.8 | J85: 10 | N85: =H85 -> 358 | O85: 50 | P85: 500
G87: =G56 -> LABOUR GRAIN FEEDING - LABOUR REQUIREMENT FOR GRAIN FEEDING SHEEP | W87: »

Sheet Crop
C3: «
E4: Däta | G4: Improvements
C17: 0
C22: «
E23: Däta | G23: General info
C26: 0
G31: grain income date | H31: =MIN(364,INT((I31 - DATE(YEAR(I31),1,1)))) -> 348 | I31: 43814 | J31: =IF(i_grain_income_date>MAX($U$99:$AD$117),"","**ERROR**")
G33: peak debt date | H33: =$H$31-7 -> 341
G34: cashflow date | H34: =$H$31+7 -> 355
G35: crop c0 inc | H35: TRUE
G37: Dry seeding
H38: dry seed start | I38: =MIN(51,INT((J38 - DATE(YEAR(J38),1,1))/7))*7 -> 91 | J38: 43560 | K38: =IF(dry_seed_start<MIN(General!i_date_node_zm),"**ERROR**","")
G41: Seeding Penalty
G43: seeding_penalty | I43: =I44 -> 91 | J43: =J44 -> 98 | K43: =K44 -> 105 | L43: =L44 -> 112 | M43: =M44 -> 119 | N43: =N44 -> 126 | O43: =O44 -> 133 | P43: =P44 -> 140
H44: landuse | I44: =dry_seed_start -> 91 | J44: =I44+7 -> 98 | K44: =J44+7 -> 105 | L44: =K44+7 -> 112 | M44: =L44+7 -> 119 | N44: =M44+7 -> 126 | O44: =N44+7 -> 133 | P44: =O44+7 -> 140
H45: =General!G17 -> b | I45: 13.367143 | J45: 13.367143 | K45: 6.3685714 | L45: 5.46 | M45: 0 | N45: 0 | O45: -17.554286 | P45: -21.865714
H46: =General!G18 -> bd | I46: 13.367143 | J46: 13.367143 | K46: 6.3685714 | L46: 5.46 | M46: 0 | N46: 0 | O46: -17.554286 | P46: -21.865714
H47: =General!G19 -> f | I47: 0 | J47: 0 | K47: 0 | L47: 0 | M47: 0 | N47: 0 | O47: -27.717429 | P47: -32.673429
H48: =General!G20 -> h | I48: 13.367143 | J48: 13.367143 | K48: 6.3685714 | L48: 5.46 | M48: 0 | N48: 0 | O48: -17.554286 | P48: -21.865714
H49: =General!G21 -> i | I49: 0 | J49: 0 | K49: 0 | L49: 0 | M49: 0 | N49: 0 | O49: -27.717429 | P49: -32.673429
H50: =General!G22 -> k | I50: 0 | J50: 0 | K50: 0 | L50: 0 | M50: 0 | N50: 0 | O50: -27.717429 | P50: -32.673429
H51: =General!G23 -> l | I51: 0 | J51: 0 | K51: 0 | L51: 0 | M51: 0 | N51: 0 | O51: -27.717429 | P51: -32.673429
H52: =General!G24 -> lf | I52: 0 | J52: 0 | K52: 0 | L52: 0 | M52: 0 | N52: 0 | O52: -27.717429 | P52: -32.673429
H53: =General!G25 -> ms | I53: =0.215*I45+0.215*I60+0.215*I47+0.215*I51+0.14*I62 -> 5.7478714 | J53: =0.215*J45+0.215*J60+0.215*J47+0.215*J51+0.14*J62 -> 5.7478714 | K53: =0.215*K45+0.215*K60+0.215*K47+0.215*K51+0.14*K62 -> 2.7384857 | L53: =0.215*L45+0.215*L60+0.215*L47+0.215*L51+0.14*L62 -> 2.3478 | M53: =0.215*M45+0.215*M60+0.215*M47+0.215*M51+0.14*M62 -> 0 | N53: =0.215*N45+0.215*N60+0.215*N47+0.215*N51+0.14*N62 -> 0 | O53: =0.215*O45+0.215*O60+0.215*O47+0.215*O51+0.14*O62 -> -23.347277 | P53: =0.215*P45+0.215*P60+0.215*P47+0.215*P51+0.14*P62 -> -28.026111
H54: =General!G26 -> o | I54: 13.367143 | J54: 13.367143 | K54: 6.3685714 | L54: 5.46 | M54: 0 | N54: 0 | O54: -17.554286 | P54: -21.865714
H55: =General!G27 -> od | I55: 13.367143 | J55: 13.367143 | K55: 6.3685714 | L55: 5.46 | M55: 0 | N55: 0 | O55: -17.554286 | P55: -21.865714
H56: =General!G28 -> of | I56: 13.367143 | J56: 13.367143 | K56: 6.3685714 | L56: 5.46 | M56: 0 | N56: 0 | O56: -17.554286 | P56: -21.865714
H57: =General!G29 -> r | I57: 0 | J57: 0 | K57: 0 | L57: 0 | M57: 0 | N57: 0 | O57: -27.717429 | P57: -32.673429
H58: =General!G30 -> rd | I58: 0 | J58: 0 | K58: 0 | L58: 0 | M58: 0 | N58: 0 | O58: -27.717429 | P58: -32.673429
H59: =General!G31 -> v | I59: 0 | J59: 0 | K59: 0 | L59: 0 | M59: 0 | N59: 0 | O59: -27.717429 | P59: -32.673429
H60: =General!G32 -> w | I60: 13.367143 | J60: 13.367143 | K60: 6.3685714 | L60: 5.46 | M60: 0 | N60: 0 | O60: -17.554286 | P60: -21.865714
H61: =General!G33 -> wd | I61: 13.367143 | J61: 13.367143 | K61: 6.3685714 | L61: 5.46 | M61: 0 | N61: 0 | O61: -17.554286 | P61: -21.865714
H62: =General!G34 -> z | I62: 0 | J62: 0 | K62: 0 | L62: 0 | M62: 0 | N62: 0 | O62: -27.717429 | P62: -32.673429
H63: =General!G35 -> zd | I63: 0 | J63: 0 | K63: 0 | L63: 0 | M63: 0 | N63: 0 | O63: -27.717429 | P63: -32.673429
H65: lmu | I65: =I44 -> 91 | J65: =J44 -> 98 | K65: =K44 -> 105 | L65: =L44 -> 112 | M65: =M44 -> 119 | N65: =N44 -> 126 | O65: =O44 -> 133 | P65: =P44 -> 140
H66: lmu0 | I66: 1 | J66: 1 | K66: 1 | L66: 1 | M66: 1 | N66: 1 | O66: 1 | P66: 1
H67: lmu1 | I67: 1 | J67: 1 | K67: 1 | L67: 1 | M67: 1 | N67: 1 | O67: 1 | P67: 1
H68: lmu2 | I68: 1 | J68: 1 | K68: 1 | L68: 1 | M68: 1 | N68: 1 | O68: 1 | P68: 1
H69: lmu3 | I69: 1 | J69: 1 | K69: 1 | L69: 1 | M69: 1 | N69: 1 | O69: 1 | P69: 1
H70: lmu4 | I70: 1 | J70: 1 | K70: 1 | L70: 1 | M70: 1 | N70: 1 | O70: 1 | P70: 1
H71: lmu5 | I71: 1 | J71: 1 | K71: 1 | L71: 1 | M71: 1 | N71: 1 | O71: 1 | P71: 1
H72: lmu6 | I72: 1 | J72: 1 | K72: 1 | L72: 1 | M72: 1 | N72: 1 | O72: 1 | P72: 1
H73: lmu7 | I73: 1 | J73: 1 | K73: 1 | L73: 1 | M73: 1 | N73: 1 | O73: 1 | P73: 1
H74: lmu8 | I74: 1 | J74: 1 | K74: 1 | L74: 1 | M74: 1 | N74: 1 | O74: 1 | P74: 1
H76: season | I76: typ | J76: z0 | K76: z1 | L76: z2 | M76: z3 | N76: z4 | O76: z5 | P76: z6 | Q76: z7 | R76: z8
H77: =H45 -> b | I77: 1 | J77: 1 | K77: 1 | L77: 1 | M77: 1 | N77: 1 | O77: 1 | P77: 1 | Q77: 1 | R77: 1
H78: =H46 -> bd | I78: 1 | J78: 1 | K78: 1 | L78: 1 | M78: 1 | N78: 1 | O78: 1 | P78: 1 | Q78: 1 | R78: 1
H79: =H47 -> f | I79: 1 | J79: 1 | K79: 1 | L79: 1 | M79: 1 | N79: 1 | O79: 1 | P79: 1 | Q79: 1 | R79: 1
H80: =H48 -> h | I80: 1 | J80: 1 | K80: 1 | L80: 1 | M80: 1 | N80: 1 | O80: 1 | P80: 1 | Q80: 1 | R80: 1
H81: =H49 -> i | I81: 1 | J81: 1 | K81: 1 | L81: 1 | M81: 1 | N81: 1 | O81: 1 | P81: 1 | Q81: 1 | R81: 1
H82: =H50 -> k | I82: 1 | J82: 1 | K82: 1 | L82: 1 | M82: 1 | N82: 1 | O82: 1 | P82: 1 | Q82: 1 | R82: 1
H83: =H51 -> l | I83: 1 | J83: 1 | K83: 1 | L83: 1 | M83: 1 | N83: 1 | O83: 1 | P83: 1 | Q83: 1 | R83: 1
H84: =H52 -> lf | I84: 1 | J84: 1 | K84: 1 | L84: 1 | M84: 1 | N84: 1 | O84: 1 | P84: 1 | Q84: 1 | R84: 1
H85: =H53 -> ms | I85: 1 | J85: 1 | K85: 1 | L85: 1 | M85: 1 | N85: 1 | O85: 1 | P85: 1 | Q85: 1 | R85: 1
H86: =H54 -> o | I86: 1 | J86: 1 | K86: 1 | L86: 1 | M86: 1 | N86: 1 | O86: 1 | P86: 1 | Q86: 1 | R86: 1
H87: =H55 -> od | I87: 1 | J87: 1 | K87: 1 | L87: 1 | M87: 1 | N87: 1 | O87: 1 | P87: 1 | Q87: 1 | R87: 1
H88: =H56 -> of | I88: 1 | J88: 1 | K88: 1 | L88: 1 | M88: 1 | N88: 1 | O88: 1 | P88: 1 | Q88: 1 | R88: 1
... H95: =H63 -> zd | I95: 1 | J95: 1 | K95: 1 | L95: 1 | M95: 1 | N95: 1 | O95: 1 | P95: 1 | Q95: 1 | R95: 1
G97: Harvest
H98: crop | I98: typ | J98: z0 | K98: z1 | L98: z2 | M98: z3 | N98: z4 | O98: z5 | P98: z6 | Q98: z7 | R98: z8 | T98: crop | U98: typ | V98: z0 | W98: z1 | X98: z2 | Y98: z3 | Z98: z4 | AA98: z5 | AB98: z6 | AC98: z7 | AD98: z8
H99: =General!G17 -> b | I99: 43794 | J99: 43794 | K99: 43794 | L99: 43794 | M99: 43794 | N99: 43794 | O99: 43794 | P99: 43794 | Q99: 43794 | R99: 43794 | T99: =H99 -> b | U99: =MIN(364,INT((I99 - DATE(YEAR(I99),1,1)))) -> 328 | V99: =MIN(364,INT((J99 - DATE(YEAR(J99),1,1)))) -> 328 | W99: =MIN(364,INT((K99 - DATE(YEAR(K99),1,1)))) -> 328 | X99: =MIN(364,INT((L99 - DATE(YEAR(L99),1,1)))) -> 328 | Y99: =MIN(364,INT((M99 - DATE(YEAR(M99),1,1)))) -> 328 | Z99: =MIN(364,INT((N99 - DATE(YEAR(N99),1,1)))) -> 328 | AA99: =MIN(364,INT((O99 - DATE(YEAR(O99),1,1)))) -> 328 | AB99: =MIN(364,INT((P99 - DATE(YEAR(P99),1,1)))) -> 328 | ... AD99: =MIN(364,INT((R99 - DATE(YEAR(R99),1,1)))) -> 328
H100: =General!G18 -> bd | I100: 43794 | J100: 43794 | K100: 43794 | L100: 43794 | M100: 43794 | N100: 43794 | O100: 43794 | P100: 43794 | Q100: 43794 | R100: 43794 | T100: =H100 -> bd | U100: =MIN(364,INT((I100 - DATE(YEAR(I100),1,1)))) -> 328 | V100: =MIN(364,INT((J100 - DATE(YEAR(J100),1,1)))) -> 328 | W100: =MIN(364,INT((K100 - DATE(YEAR(K100),1,1)))) -> 328 | X100: =MIN(364,INT((L100 - DATE(YEAR(L100),1,1)))) -> 328 | Y100: =MIN(364,INT((M100 - DATE(YEAR(M100),1,1)))) -> 328 | Z100: =MIN(364,INT((N100 - DATE(YEAR(N100),1,1)))) -> 328 | AA100: =MIN(364,INT((O100 - DATE(YEAR(O100),1,1)))) -> 328 | AB100: =MIN(364,INT((P100 - DATE(YEAR(P100),1,1)))) -> 328 | ... AD100: =MIN(364,INT((R100 - DATE(YEAR(R100),1,1)))) -> 328
H101: =General!G19 -> f | I101: 43794 | J101: 43794 | K101: 43794 | L101: 43794 | M101: 43794 | N101: 43794 | O101: 43794 | P101: 43794 | Q101: 43794 | R101: 43794 | T101: =H101 -> f | U101: =MIN(364,INT((I101 - DATE(YEAR(I101),1,1)))) -> 328 | V101: =MIN(364,INT((J101 - DATE(YEAR(J101),1,1)))) -> 328 | W101: =MIN(364,INT((K101 - DATE(YEAR(K101),1,1)))) -> 328 | X101: =MIN(364,INT((L101 - DATE(YEAR(L101),1,1)))) -> 328 | Y101: =MIN(364,INT((M101 - DATE(YEAR(M101),1,1)))) -> 328 | Z101: =MIN(364,INT((N101 - DATE(YEAR(N101),1,1)))) -> 328 | AA101: =MIN(364,INT((O101 - DATE(YEAR(O101),1,1)))) -> 328 | AB101: =MIN(364,INT((P101 - DATE(YEAR(P101),1,1)))) -> 328 | ... AD101: =MIN(364,INT((R101 - DATE(YEAR(R101),1,1)))) -> 328
H102: =General!G20 -> h | I102: 43784 | J102: 43794 | K102: 43794 | L102: 43794 | M102: 43794 | N102: 43794 | O102: 43794 | P102: 43794 | Q102: 43794 | R102: 43794 | T102: =H102 -> h | U102: =MIN(364,INT((I102 - DATE(YEAR(I102),1,1)))) -> 318 | V102: =MIN(364,INT((J102 - DATE(YEAR(J102),1,1)))) -> 328 | W102: =MIN(364,INT((K102 - DATE(YEAR(K102),1,1)))) -> 328 | X102: =MIN(364,INT((L102 - DATE(YEAR(L102),1,1)))) -> 328 | Y102: =MIN(364,INT((M102 - DATE(YEAR(M102),1,1)))) -> 328 | Z102: =MIN(364,INT((N102 - DATE(YEAR(N102),1,1)))) -> 328 | AA102: =MIN(364,INT((O102 - DATE(YEAR(O102),1,1)))) -> 328 | AB102: =MIN(364,INT((P102 - DATE(YEAR(P102),1,1)))) -> 328 | ... AD102: =MIN(364,INT((R102 - DATE(YEAR(R102),1,1)))) -> 328
H103: =General!G21 -> i | I103: 43794 | J103: 43794 | K103: 43794 | L103: 43794 | M103: 43794 | N103: 43794 | O103: 43794 | P103: 43794 | Q103: 43794 | R103: 43794 | T103: =H103 -> i | U103: =MIN(364,INT((I103 - DATE(YEAR(I103),1,1)))) -> 328 | V103: =MIN(364,INT((J103 - DATE(YEAR(J103),1,1)))) -> 328 | W103: =MIN(364,INT((K103 - DATE(YEAR(K103),1,1)))) -> 328 | X103: =MIN(364,INT((L103 - DATE(YEAR(L103),1,1)))) -> 328 | Y103: =MIN(364,INT((M103 - DATE(YEAR(M103),1,1)))) -> 328 | Z103: =MIN(364,INT((N103 - DATE(YEAR(N103),1,1)))) -> 328 | AA103: =MIN(364,INT((O103 - DATE(YEAR(O103),1,1)))) -> 328 | AB103: =MIN(364,INT((P103 - DATE(YEAR(P103),1,1)))) -> 328 | ... AD103: =MIN(364,INT((R103 - DATE(YEAR(R103),1,1)))) -> 328
H104: =General!G22 -> k | I104: 43794 | J104: 43794 | K104: 43794 | L104: 43794 | M104: 43794 | N104: 43794 | O104: 43794 | P104: 43794 | Q104: 43794 | R104: 43794 | T104: =H104 -> k | U104: =MIN(364,INT((I104 - DATE(YEAR(I104),1,1)))) -> 328 | V104: =MIN(364,INT((J104 - DATE(YEAR(J104),1,1)))) -> 328 | W104: =MIN(364,INT((K104 - DATE(YEAR(K104),1,1)))) -> 328 | X104: =MIN(364,INT((L104 - DATE(YEAR(L104),1,1)))) -> 328 | Y104: =MIN(364,INT((M104 - DATE(YEAR(M104),1,1)))) -> 328 | Z104: =MIN(364,INT((N104 - DATE(YEAR(N104),1,1)))) -> 328 | AA104: =MIN(364,INT((O104 - DATE(YEAR(O104),1,1)))) -> 328 | AB104: =MIN(364,INT((P104 - DATE(YEAR(P104),1,1)))) -> 328 | ... AD104: =MIN(364,INT((R104 - DATE(YEAR(R104),1,1)))) -> 328
H105: =General!G23 -> l | I105: 43794 | J105: 43794 | K105: 43794 | L105: 43794 | M105: 43794 | N105: 43794 | O105: 43794 | P105: 43794 | Q105: 43794 | R105: 43794 | T105: =H105 -> l | U105: =MIN(364,INT((I105 - DATE(YEAR(I105),1,1)))) -> 328 | V105: =MIN(364,INT((J105 - DATE(YEAR(J105),1,1)))) -> 328 | W105: =MIN(364,INT((K105 - DATE(YEAR(K105),1,1)))) -> 328 | X105: =MIN(364,INT((L105 - DATE(YEAR(L105),1,1)))) -> 328 | Y105: =MIN(364,INT((M105 - DATE(YEAR(M105),1,1)))) -> 328 | Z105: =MIN(364,INT((N105 - DATE(YEAR(N105),1,1)))) -> 328 | AA105: =MIN(364,INT((O105 - DATE(YEAR(O105),1,1)))) -> 328 | AB105: =MIN(364,INT((P105 - DATE(YEAR(P105),1,1)))) -> 328 | ... AD105: =MIN(364,INT((R105 - DATE(YEAR(R105),1,1)))) -> 328
H106: =General!G24 -> lf | I106: 43784 | J106: 43784 | K106: 43784 | L106: 43784 | M106: 43784 | N106: 43784 | O106: 43784 | P106: 43784 | Q106: 43784 | R106: 43784 | T106: =H106 -> lf | U106: =MIN(364,INT((I106 - DATE(YEAR(I106),1,1)))) -> 318 | V106: =MIN(364,INT((J106 - DATE(YEAR(J106),1,1)))) -> 318 | W106: =MIN(364,INT((K106 - DATE(YEAR(K106),1,1)))) -> 318 | X106: =MIN(364,INT((L106 - DATE(YEAR(L106),1,1)))) -> 318 | Y106: =MIN(364,INT((M106 - DATE(YEAR(M106),1,1)))) -> 318 | Z106: =MIN(364,INT((N106 - DATE(YEAR(N106),1,1)))) -> 318 | AA106: =MIN(364,INT((O106 - DATE(YEAR(O106),1,1)))) -> 318 | AB106: =MIN(364,INT((P106 - DATE(YEAR(P106),1,1)))) -> 318 | ... AD106: =MIN(364,INT((R106 - DATE(YEAR(R106),1,1)))) -> 318
H107: =General!G25 -> ms | I107: 43794 | J107: 43794 | K107: 43794 | L107: 43794 | M107: 43794 | N107: 43794 | O107: 43794 | P107: 43794 | Q107: 43794 | R107: 43794 | T107: =H107 -> ms | U107: =MIN(364,INT((I107 - DATE(YEAR(I107),1,1)))) -> 328 | V107: =MIN(364,INT((J107 - DATE(YEAR(J107),1,1)))) -> 328 | W107: =MIN(364,INT((K107 - DATE(YEAR(K107),1,1)))) -> 328 | X107: =MIN(364,INT((L107 - DATE(YEAR(L107),1,1)))) -> 328 | Y107: =MIN(364,INT((M107 - DATE(YEAR(M107),1,1)))) -> 328 | Z107: =MIN(364,INT((N107 - DATE(YEAR(N107),1,1)))) -> 328 | AA107: =MIN(364,INT((O107 - DATE(YEAR(O107),1,1)))) -> 328 | AB107: =MIN(364,INT((P107 - DATE(YEAR(P107),1,1)))) -> 328 | ... AD107: =MIN(364,INT((R107 - DATE(YEAR(R107),1,1)))) -> 328
H108: =General!G26 -> o | I108: 43794 | J108: 43794 | K108: 43794 | L108: 43794 | M108: 43794 | N108: 43794 | O108: 43794 | P108: 43794 | Q108: 43794 | R108: 43794 | T108: =H108 -> o | U108: =MIN(364,INT((I108 - DATE(YEAR(I108),1,1)))) -> 328 | V108: =MIN(364,INT((J108 - DATE(YEAR(J108),1,1)))) -> 328 | W108: =MIN(364,INT((K108 - DATE(YEAR(K108),1,1)))) -> 328 | X108: =MIN(364,INT((L108 - DATE(YEAR(L108),1,1)))) -> 328 | Y108: =MIN(364,INT((M108 - DATE(YEAR(M108),1,1)))) -> 328 | Z108: =MIN(364,INT((N108 - DATE(YEAR(N108),1,1)))) -> 328 | AA108: =MIN(364,INT((O108 - DATE(YEAR(O108),1,1)))) -> 328 | AB108: =MIN(364,INT((P108 - DATE(YEAR(P108),1,1)))) -> 328 | ... AD108: =MIN(364,INT((R108 - DATE(YEAR(R108),1,1)))) -> 328
H109: =General!G27 -> od | I109: 43794 | J109: 43794 | K109: 43794 | L109: 43794 | M109: 43794 | N109: 43794 | O109: 43794 | P109: 43794 | Q109: 43794 | R109: 43794 | T109: =H109 -> od | U109: =MIN(364,INT((I109 - DATE(YEAR(I109),1,1)))) -> 328 | V109: =MIN(364,INT((J109 - DATE(YEAR(J109),1,1)))) -> 328 | W109: =MIN(364,INT((K109 - DATE(YEAR(K109),1,1)))) -> 328 | X109: =MIN(364,INT((L109 - DATE(YEAR(L109),1,1)))) -> 328 | Y109: =MIN(364,INT((M109 - DATE(YEAR(M109),1,1)))) -> 328 | Z109: =MIN(364,INT((N109 - DATE(YEAR(N109),1,1)))) -> 328 | AA109: =MIN(364,INT((O109 - DATE(YEAR(O109),1,1)))) -> 328 | AB109: =MIN(364,INT((P109 - DATE(YEAR(P109),1,1)))) -> 328 | ... AD109: =MIN(364,INT((R109 - DATE(YEAR(R109),1,1)))) -> 328
H110: =General!G28 -> of | I110: 43784 | J110: 43784 | K110: 43784 | L110: 43784 | M110: 43784 | N110: 43784 | O110: 43784 | P110: 43784 | Q110: 43784 | R110: 43784 | T110: =H110 -> of | U110: =MIN(364,INT((I110 - DATE(YEAR(I110),1,1)))) -> 318 | V110: =MIN(364,INT((J110 - DATE(YEAR(J110),1,1)))) -> 318 | W110: =MIN(364,INT((K110 - DATE(YEAR(K110),1,1)))) -> 318 | X110: =MIN(364,INT((L110 - DATE(YEAR(L110),1,1)))) -> 318 | Y110: =MIN(364,INT((M110 - DATE(YEAR(M110),1,1)))) -> 318 | Z110: =MIN(364,INT((N110 - DATE(YEAR(N110),1,1)))) -> 318 | AA110: =MIN(364,INT((O110 - DATE(YEAR(O110),1,1)))) -> 318 | AB110: =MIN(364,INT((P110 - DATE(YEAR(P110),1,1)))) -> 318 | ... AD110: =MIN(364,INT((R110 - DATE(YEAR(R110),1,1)))) -> 318
... H117: =General!G35 -> zd | I117: 43784 | J117: 43784 | K117: 43784 | L117: 43784 | M117: 43784 | N117: 43784 | O117: 43784 | P117: 43784 | Q117: 43784 | R117: 43784 | T117: =H117 -> zd | U117: =MIN(364,INT((I117 - DATE(YEAR(I117),1,1)))) -> 318 | V117: =MIN(364,INT((J117 - DATE(YEAR(J117),1,1)))) -> 318 | W117: =MIN(364,INT((K117 - DATE(YEAR(K117),1,1)))) -> 318 | X117: =MIN(364,INT((L117 - DATE(YEAR(L117),1,1)))) -> 318 | Y117: =MIN(364,INT((M117 - DATE(YEAR(M117),1,1)))) -> 318 | Z117: =MIN(364,INT((N117 - DATE(YEAR(N117),1,1)))) -> 318 | AA117: =MIN(364,INT((O117 - DATE(YEAR(O117),1,1)))) -> 318 | AB117: =MIN(364,INT((P117 - DATE(YEAR(P117),1,1)))) -> 318 | ... AD117: =MIN(364,INT((R117 - DATE(YEAR(R117),1,1)))) -> 318
H119: hay_making_date | I119: =MIN(364,INT((J119 - DATE(YEAR(J119),1,1)))) -> 304 | J119: 43770
G122: POC
H123: poc included | I123: TRUE
H124: how long before seeding is the paddock destocked | I124: 10
G127: =G23 -> General info | AH127: »
C131: «
E132: Däta | G132: Fixed Inputs
C135: 0
H137: Fert ($/ha) | J137: Proportion of farm limed each year
H139: lime | J139: lime
H140: 50 | J140: =0.16*0.8 -> 0.128
G145: =G132 -> Fixed Inputs | W145: »
C149: «
E150: Däta | G150: User defined rotations
I151: Enabled | J151: TRUE
C153: 0
N159: *note this types of inputs must be the same as the ones in AusFarm (if you change/add you must make the changes in AusFarm too)
I160: Note
H162: History yr5 | I162: History yr4 | J162: History yr3 | K162: History yr2 | L162: History yr1 | M162: Landuse | N162: Double up | Q162: Included? | T162: Seeding Freq | V162: nap scalar
G163: =_xlfn.CONCAT(H163:M163) -> AAAA2A1a | H163: A | I163: A | J163: A | K163: A2 | L163: A1 | M163: a | N163: =AND(COUNTIF(G176:$G$216,G163)) -> FALSE | O163: A | Q163: TRUE | T163: =IF(OR(M163="a",M163="a2",M163="sp"),0,1) -> 0 | V163: =1-T163 -> 1 | X163: Yield | Z163: Base | AC163: Scalar based on previous landuse
G164: =_xlfn.CONCAT(H164:M164) -> GGGGAg1a2 | H164: G | I164: G | J164: G | K164: G | L164: Ag1 | M164: a2 | N164: =AND(COUNTIF(G178:$G$216,G164)) -> FALSE | O164: PNC | Q164: TRUE | T164: =IF(OR(M164="a",M164="a2",M164="sp"),0,1) -> 0 | V164: =1-T164 -> 1 | Y164: b | Z164: 2000 | AC164: {=TRANSPOSE(Y164:Y176)} -> b | AD164: bd | AE164: o | AF164: od | AG164: of | AH164: l | AI164: ms | AJ164: w | AK164: wd | AL164: r | AM164: rd | AN164: z | AO164: zd
G165: =_xlfn.CONCAT(H165:M165) -> GGGGSg1a2 | H165: G | I165: G | J165: G | K165: G | L165: Sg1 | M165: a2 | N165: =AND(COUNTIF(G180:$G$216,G165)) -> FALSE | O165: PNC | Q165: TRUE | T165: =IF(OR(M165="a",M165="a2",M165="sp"),0,1) -> 0 | V165: =1-T165 -> 1 | Y165: bd | Z165: 2000 | AB165: A1 | AC165: 0.15 | AD165: 0.15 | AE165: 0.15 | AF165: 0.15 | AG165: 0.15 | AH165: 0 | AI165: 0.15 | AJ165: 0.15 | AK165: 0.15 | AL165: 0.15 | AM165: 0.15 | AN165: 0.15 | AO165: 0.15
G166: =_xlfn.CONCAT(H166:M166) -> GGGAg2Na2 | H166: G | I166: G | J166: G | K166: Ag2 | L166: N | M166: a2 | N166: =AND(COUNTIF(G182:$G$216,G166)) -> FALSE | O166: PNC | Q166: TRUE | T166: =IF(OR(M166="a",M166="a2",M166="sp"),0,1) -> 0 | V166: =1-T166 -> 1 | Y166: o | Z166: 1800 | AB166: Ag1 | AC166: 0.15 | AD166: 0.15 | AE166: 0.15 | AF166: 0.15 | AG166: 0.15 | AH166: 0 | AI166: 0.15 | AJ166: 0.15 | AK166: 0.15 | AL166: 0.15 | AM166: 0.15 | AN166: 0.15 | AO166: 0.15
G167: =_xlfn.CONCAT(H167:M167) -> GGGAg2Ea2 | H167: G | I167: G | J167: G | K167: Ag2 | L167: E | M167: a2 | N167: =AND(COUNTIF(G184:$G$216,G167)) -> FALSE | O167: PNC | Q167: TRUE | T167: =IF(OR(M167="a",M167="a2",M167="sp"),0,1) -> 0 | V167: =1-T167 -> 1 | Y167: od | Z167: 1800 | AB167: B | AC167: 0 | AD167: 0 | AE167: 0 | AF167: 0 | AG167: 0 | AH167: 0 | AI167: 0 | AJ167: 0 | AK167: 0 | AL167: 0 | AM167: 0 | AN167: 0 | AO167: 0
G168: =_xlfn.CONCAT(H168:M168) -> GGGAg2OFa2 | H168: G | I168: G | J168: G | K168: Ag2 | L168: OF | M168: a2 | N168: =AND(COUNTIF(G185:$G$216,G168)) -> FALSE | O168: PNC | Q168: TRUE | T168: =IF(OR(M168="a",M168="a2",M168="sp"),0,1) -> 0 | V168: =1-T168 -> 1 | Y168: of | Z168: 1260 | AB168: E | AC168: 0 | AD168: 0 | AE168: 0 | AF168: 0 | AG168: 0 | AH168: 0 | AI168: 0 | AJ168: 0 | AK168: 0 | AL168: 0 | AM168: 0 | AN168: 0 | AO168: 0
G169: =_xlfn.CONCAT(H169:M169) -> GGGAg2LFa2 | H169: G | I169: G | J169: G | K169: Ag2 | L169: LF | M169: a2 | N169: =AND(COUNTIF(G186:$G$216,G169)) -> FALSE | O169: PNC | Q169: TRUE | T169: =IF(OR(M169="a",M169="a2",M169="sp"),0,1) -> 0 | V169: =1-T169 -> 1 | Y169: l | Z169: 1000 | AB169: L | AC169: 0.2 | AD169: 0.2 | AE169: 0.2 | AF169: 0.2 | AG169: 0.2 | AH169: 0 | AI169: 0.2 | AJ169: 0.2 | AK169: 0.2 | AL169: 0.2 | AM169: 0.2 | AN169: 0.2 | AO169: 0.2
G170: =_xlfn.CONCAT(H170:M170) -> GGGC1Na2 | H170: G | I170: G | J170: G | K170: C1 | L170: N | M170: a2 | N170: =AND(COUNTIF(G186:$G$216,G170)) -> FALSE | O170: PNC | Q170: TRUE | T170: =IF(OR(M170="a",M170="a2",M170="sp"),0,1) -> 0 | V170: =1-T170 -> 1 | Y170: ms | Z170: 1580 | AB170: MS | AC170: 0 | AD170: 0 | AE170: 0 | AF170: 0 | AG170: 0 | AH170: 0 | AI170: 0 | AJ170: 0 | AK170: 0 | AL170: 0 | AM170: 0 | AN170: 0 | AO170: 0
...

Sheet Emissions
C3: «
E4: Däta | G4: Annual Electricity Use (State Grid)
H6: 4000 | I6: KWh
G10: =G4 -> Annual Electricity Use (State Grid) | W10: »
C14: «
E15: Däta | G15: Leaching factor rainfal adjuster
G17: Does your farm get enough rainfall or irrigation to drain through the soil profile i.e. typically above 600mm
H18: FALSE
G21: =G15 -> Leaching factor rainfal adjuster | W21: »
C25: «
E26: Däta | G26: Residue Burning
H27: Date of residue burning | M27: Proportion of harvested area that is burnt - Acording to GRDC survey 2021
H28: =MIN(364,INT((I28 - DATE(YEAR(I28),1,1)))) -> 59 | I28: 43525 | L28: =General!G17 -> b | M28: 0.04
L29: =General!G18 -> bd | M29: 0.04
L30: =General!G19 -> f | M30: 0.04
L31: =General!G20 -> h | M31: 0.04
L32: =General!G21 -> i | M32: 0.04
L33: =General!G22 -> k | M33: 0.04
L34: =General!G23 -> l | M34: 0.04
L35: =General!G24 -> lf | M35: 0.04
L36: =General!G25 -> ms | M36: 0.04
L37: =General!G26 -> o | M37: 0.04
L38: =General!G27 -> od | M38: 0.04
L39: =General!G28 -> of | M39: 0.04
L40: =General!G29 -> r | M40: 0.04
... L46: =General!G35 -> zd | M46: 0.04
G51: =G26 -> Residue Burning | W51: »

Sheet CropGrazing
G4: Crop Grazing included
H5: TRUE
G9: =G4 -> Crop Grazing included
C12: «
E13: Däta | G13: Proportion of area that can be grazed
C16: 0
G20: Landuse | H20: lmu0 | I20: lmu1 | J20: lmu2 | K20: lmu3 | L20: lmu4 | M20: lmu5 | N20: lmu6 | O20: lmu7 | P20: lmu8
G21: =General!G17 -> b | H21: 1 | I21: 1 | J21: 1 | K21: 1 | L21: 1 | M21: 1 | N21: 1 | O21: 1 | P21: 1
G22: =General!G18 -> bd | H22: 1 | I22: 1 | J22: 1 | K22: 1 | L22: 1 | M22: 1 | N22: 1 | O22: 1 | P22: 1
G23: =General!G19 -> f | H23: 1 | I23: 1 | J23: 1 | K23: 1 | L23: 1 | M23: 1 | N23: 1 | O23: 1 | P23: 1
G24: =General!G20 -> h | H24: 1 | I24: 1 | J24: 1 | K24: 1 | L24: 1 | M24: 1 | N24: 1 | O24: 1 | P24: 1
G25: =General!G21 -> i | H25: 1 | I25: 1 | J25: 1 | K25: 1 | L25: 1 | M25: 1 | N25: 1 | O25: 1 | P25: 1
G26: =General!G22 -> k | H26: 1 | I26: 1 | J26: 1 | K26: 1 | L26: 1 | M26: 1 | N26: 1 | O26: 1 | P26: 1
G27: =General!G23 -> l | H27: 1 | I27: 1 | J27: 1 | K27: 1 | L27: 1 | M27: 1 | N27: 1 | O27: 1 | P27: 1
G28: =General!G24 -> lf | H28: 1 | I28: 1 | J28: 1 | K28: 1 | L28: 1 | M28: 1 | N28: 1 | O28: 1 | P28: 1
G29: =General!G25 -> ms | H29: 1 | I29: 1 | J29: 1 | K29: 1 | L29: 1 | M29: 1 | N29: 1 | O29: 1 | P29: 1
G30: =General!G26 -> o | H30: 1 | I30: 1 | J30: 1 | K30: 1 | L30: 1 | M30: 1 | N30: 1 | O30: 1 | P30: 1
G31: =General!G27 -> od | H31: 1 | I31: 1 | J31: 1 | K31: 1 | L31: 1 | M31: 1 | N31: 1 | O31: 1 | P31: 1
G32: =General!G28 -> of | H32: 1 | I32: 1 | J32: 1 | K32: 1 | L32: 1 | M32: 1 | N32: 1 | O32: 1 | P32: 1
... G39: =General!G35 -> zd | H39: 1 | I39: 1 | J39: 1 | K39: 1 | L39: 1 | M39: 1 | N39: 1 | O39: 1 | P39: 1
G44: =G13 -> Proportion of area that can be grazed | W44: »
C47: « | D47: =SUM(F72:V112) -> 1213.204
D48: 80 | E48: Däta | G48: GRAZING CROPS - ESTIMATED GROWTH RATE & CONSUMPTION
D49: =OR(ISNA(VLOOKUP(G48,Index_Table_Names,1,FALSE)),G48="") -> FALSE
D50: =(D48<>D47) -> TRUE | H50: Days after sowing grazing can occur | K50: 30
G52: Height Ratio
D53: 80 | E53: Däta | J53: HR | K53: 1
D54: =OR(ISNA(VLOOKUP(G53,Index_Table_Names,1,FALSE)),G53="") -> TRUE
D55: =(D53<>#REF!) -> #REF!
G56: Propn of growth that can be consumed | K56: P0 | L56: P1 | M56: P2 | N56: P3 | O56: P4 | P56: P5 | Q56: P6 | R56: P7 | S56: P8 | T56: P9
D57: 80 | E57: Däta | J57: typ | K57: 0 | L57: 0.21 | M57: 0.21 | N57: 0 | O57: 0 | P57: 0 | Q57: 0 | R57: 0 | S57: 0 | T57: 0
J58: z0 | K58: 0 | L58: 0.21 | M58: 0.21 | N58: 0 | O58: 0 | P58: 0 | Q58: 0 | R58: 0 | S58: 0 | T58: 0
J59: z1 | K59: 0 | L59: 0.21 | M59: 0.21 | N59: 0 | O59: 0 | P59: 0 | Q59: 0 | R59: 0 | S59: 0 | T59: 0
J60: z2 | K60: 0 | L60: 0.21 | M60: 0 | N60: 0 | O60: 0 | P60: 0 | Q60: 0 | R60: 0 | S60: 0 | T60: 0
J61: z3 | K61: 0 | L61: 0.21 | M61: 0 | N61: 0 | O61: 0 | P61: 0 | Q61: 0 | R61: 0 | S61: 0 | T61: 0
J62: z4 | K62: 0 | L62: 0.21 | M62: 0.21 | N62: 0 | O62: 0 | P62: 0 | Q62: 0 | R62: 0 | S62: 0 | T62: 0
J63: z5 | K63: 0 | L63: 0.21 | M63: 0.21 | N63: 0 | O63: 0 | P63: 0 | Q63: 0 | R63: 0 | S63: 0 | T63: 0
J64: z6 | K64: 0 | L64: 0.21 | M64: 0 | N64: 0 | O64: 0 | P64: 0 | Q64: 0 | R64: 0 | S64: 0 | T64: 0
J65: z7 | K65: 0 | L65: 0.21 | M65: 0 | N65: 0 | O65: 0 | P65: 0 | Q65: 0 | R65: 0 | S65: 0 | T65: 0
J66: z8 | K66: 0 | L66: 0.21 | M66: 0.21 | N66: 0 | O66: 0 | P66: 0 | Q66: 0 | R66: 0 | S66: 0 | T66: 0
D67: =OR(ISNA(VLOOKUP(G57,Index_Table_Names,1,FALSE)),G57="") -> TRUE | K67: Note: if these numbers change the yield penalty should also change.
D68: =(D57<>#REF!) -> #REF!
G70: Estimated growth rate on base LMU | J70: Feed period | K70: P0 | L70: P1 | M70: P2 | N70: P3 | O70: P4 | P70: P5 | Q70: P6 | R70: P7 | S70: P8 | T70: P9
K71: kg / ha / d | L71: kg / ha / d | M71: kg / ha / d | N71: kg / ha / d | O71: kg / ha / d | P71: kg / ha / d | Q71: kg / ha / d | R71: kg / ha / d | S71: kg / ha / d | T71: kg / ha / d
G72: =G21 -> b | H72: 1 | J72: typ | K72: 0 | L72: 20.847277 | M72: 40.246377 | N72: 38.482164 | O72: 10.536944 | P72: 0 | Q72: 0 | R72: 0 | S72: 0 | T72: 0
G73: =G22 -> bd | H73: 1 | J73: z0 | K73: 0 | L73: 33.599095 | M73: 50.313677 | N73: 47.106211 | O73: 19 | P73: 0 | Q73: 0 | R73: 0 | S73: 0 | T73: 0
G74: =G23 -> f | H74: 1 | J74: z1 | K74: 0 | L74: 33.599095 | M74: 50.313677 | N74: 47.106211 | O74: 0 | P74: 0 | Q74: 0 | R74: 0 | S74: 0 | T74: 0
G75: =G24 -> h | H75: 1 | J75: z2 | K75: 0 | L75: 33.599095 | M75: 50.313677 | N75: 47.106211 | O75: 19 | P75: 0 | Q75: 0 | R75: 0 | S75: 0 | T75: 0
G76: =G25 -> i | H76: 1 | J76: z3 | K76: 0 | L76: 33.599095 | M76: 50.313677 | N76: 47.106211 | O76: 0 | P76: 0 | Q76: 0 | R76: 0 | S76: 0 | T76: 0
G77: =G26 -> k | H77: 1 | J77: z4 | K77: 0 | L77: 8.6730658 | M77: 30.840632 | N77: 44.424619 | O77: 27 | P77: 0 | Q77: 0 | R77: 0 | S77: 0 | T77: 0
G78: =G27 -> l | H78: 1 | J78: z5 | K78: 0 | L78: 8.6730658 | M78: 30.840632 | N78: 44.424619 | O78: 0 | P78: 0 | Q78: 0 | R78: 0 | S78: 0 | T78: 0
G79: =G28 -> lf | H79: 1 | J79: z6 | K79: 0 | L79: 8.6730658 | M79: 30.840632 | N79: 44.424619 | O79: 27 | P79: 0 | Q79: 0 | R79: 0 | S79: 0 | T79: 0
G80: =G29 -> ms | H80: 1 | J80: z7 | K80: 0 | L80: 8.6730658 | M80: 30.840632 | N80: 44.424619 | O80: 0 | P80: 0 | Q80: 0 | R80: 0 | S80: 0 | T80: 0
G81: =G30 -> o | H81: 1 | J81: z8 | K81: 0 | L81: 0 | M81: 0 | N81: 0 | O81: 0 | P81: 0 | Q81: 0 | R81: 0 | S81: 0 | T81: 0
G82: =G31 -> od | H82: 1
G83: =G32 -> of | H83: 1
G84: =G33 -> r | H84: 1
G85: =G34 -> rd | H85: 1
G86: =G35 -> v | H86: 1
G87: =G36 -> w | H87: 1
G88: =G37 -> wd | H88: 1
G89: =G38 -> z | H89: 1
G90: =G39 -> zd | H90: 1
G92: Estimated LMU growth factor | K92: LMU0 | L92: LMU1 | M92: LMU2 | N92: LMU3 | O92: LMU4 | P92: LMU5 | Q92: LMU6 | R92: LMU7 | S92: LMU8
I93: =G72 -> b | K93: 0.67 | L93: 0.92 | M93: 1.02 | N93: 1 | O93: 0.97 | P93: 0.82 | Q93: 0.81 | R93: 0.56 | S93: 0
I94: =G73 -> bd | K94: 0.67 | L94: 0.92 | M94: 1.02 | N94: 1 | O94: 0.97 | P94: 0.82 | Q94: 0.81 | R94: 0.56 | S94: 0
I95: =G74 -> f | K95: 0.78 | L95: 1.15 | M95: 1.04 | N95: 1 | O95: 0.95 | P95: 0.88 | Q95: 0.89 | R95: 0.56 | S95: 0
I96: =G75 -> h | K96: 0.67 | L96: 0.92 | M96: 1.02 | N96: 1 | O96: 0.97 | P96: 0.82 | Q96: 0.81 | R96: 0.56 | S96: 0
I97: =G76 -> i | K97: 0.78 | L97: 1.15 | M97: 1.04 | N97: 1 | O97: 0.95 | P97: 0.88 | Q97: 0.89 | R97: 0.56 | S97: 0
I98: =G77 -> k | K98: 0.78 | L98: 1.15 | M98: 1.04 | N98: 1 | O98: 0.95 | P98: 0.88 | Q98: 0.89 | R98: 0.56 | S98: 0
I99: =G78 -> l | K99: 0.78 | L99: 1.15 | M99: 1.04 | N99: 1 | O99: 0.95 | P99: 0.88 | Q99: 0.89 | R99: 0.56 | S99: 0
I100: =G79 -> lf | K100: 0.78 | L100: 1.15 | M100: 1.04 | N100: 1 | O100: 0.95 | P100: 0.88 | Q100: 0.89 | R100: 0.56 | S100: 0
I101: =G80 -> ms | K101: =AVERAGE(K93,K108,K95,K99,K102) -> 0.714 | L101: =AVERAGE(L93,L108,L95,L99,L102) -> 1.012 | M101: =AVERAGE(M93,M108,M95,M99,M102) -> 1.028 | N101: =AVERAGE(N93,N108,N95,N99,N102) -> 1 | O101: =AVERAGE(O93,O108,O95,O99,O102) -> 0.962 | P101: =AVERAGE(P93,P108,P95,P99,P102) -> 0.844 | Q101: =AVERAGE(Q93,Q108,Q95,Q99,Q102) -> 0.842 | R101: =AVERAGE(R93,R108,R95,R99,R102) -> 0.56 | S101: =0.65*S108+0.35*S99 -> 0
I102: =G81 -> o | K102: 0.67 | L102: 0.92 | M102: 1.02 | N102: 1 | O102: 0.97 | P102: 0.82 | Q102: 0.81 | R102: 0.56 | S102: 0
I103: =G82 -> od | K103: 0.67 | L103: 0.92 | M103: 1.02 | N103: 1 | O103: 0.97 | P103: 0.82 | Q103: 0.81 | R103: 0.56 | S103: 0
I104: =G83 -> of | K104: 0.67 | L104: 0.92 | M104: 1.02 | N104: 1 | O104: 0.97 | P104: 0.82 | Q104: 0.81 | R104: 0.56 | S104: 0
I105: =G84 -> r | K105: 0.75 | L105: 1 | M105: 1.13 | N105: 1 | O105: 0.97 | P105: 0.73 | Q105: 0.77 | R105: 0.56 | S105: 0
I106: =G85 -> rd | K106: 0.75 | L106: 1 | M106: 1.13 | N106: 1 | O106: 0.97 | P106: 0.73 | Q106: 0.77 | R106: 0.56 | S106: 0
I107: =G86 -> v | K107: 0.78 | L107: 1.15 | M107: 1.04 | N107: 1 | O107: 0.95 | P107: 0.88 | Q107: 0.89 | R107: 0.56 | S107: 0
I108: =G87 -> w | K108: 0.67 | L108: 0.92 | M108: 1.02 | N108: 1 | O108: 0.97 | P108: 0.82 | Q108: 0.81 | R108: 0.56 | S108: 0
I109: =G88 -> wd | K109: 0.67 | L109: 0.92 | M109: 1.02 | N109: 1 | O109: 0.97 | P109: 0.82 | Q109: 0.81 | R109: 0.56 | S109: 0
I110: =G89 -> z | K110: 0.75 | L110: 1 | M110: 1.13 | N110: 1 | O110: 0.97 | P110: 0.73 | Q110: 0.77 | R110: 0.56 | S110: 0
I111: =G90 -> zd | K111: 0.75 | L111: 1 | M111: 1.13 | N111: 1 | O111: 0.97 | P111: 0.73 | Q111: 0.77 | R111: 0.56 | S111: 0
G113: =G48 -> GRAZING CROPS - ESTIMATED GROWTH RATE & CONSUMPTION | W113: «»
C116: « | D116: =SUM(F149:V170) -> 1.9
D117: 2167.88 | E117: Däta | G117: GRAZING CROPS - QUALITY AND WASTAGE
D118: =OR(ISNA(VLOOKUP(G117,Index_Table_Names,1,FALSE)),G117="") -> FALSE
D119: =(D117<>D116) -> TRUE | G119: 37780.587
J121: Feed period | K121: P0 | L121: P1 | M121: P2 | N121: P3 | O121: P4 | P121: P5 | Q121: P6 | R121: P7 | S121: P8 | T121: P9
G122: DMD | K122: DMD | L122: DMD | M122: DMD | N122: DMD | O122: DMD | P122: DMD | Q122: DMD | R122: DMD | S122: DMD | T122: DMD
I123: =G21 -> b | K123: 0.81 | L123: 0.81 | M123: 0.81 | N123: 0.81 | O123: 0.81 | P123: 0.81 | Q123: 0.81 | R123: 0.81 | S123: 0.81 | T123: 0.81
I124: =G22 -> bd | K124: 0.81 | L124: 0.81 | M124: 0.81 | N124: 0.81 | O124: 0.81 | P124: 0.81 | Q124: 0.81 | R124: 0.81 | S124: 0.81 | T124: 0.81
I125: =G23 -> f | K125: 0.81 | L125: 0.81 | M125: 0.81 | N125: 0.81 | O125: 0.81 | P125: 0.81 | Q125: 0.81 | R125: 0.81 | S125: 0.81 | T125: 0.81
I126: =G24 -> h | K126: 0.81 | L126: 0.81 | M126: 0.81 | N126: 0.81 | O126: 0.81 | P126: 0.81 | Q126: 0.81 | R126: 0.81 | S126: 0.81 | T126: 0.81
I127: =G25 -> i | K127: 0.81 | L127: 0.81 | M127: 0.81 | N127: 0.81 | O127: 0.81 | P127: 0.81 | Q127: 0.81 | R127: 0.81 | S127: 0.81 | T127: 0.81
I128: =G26 -> k | K128: 0.81 | L128: 0.81 | M128: 0.81 | N128: 0.81 | O128: 0.81 | P128: 0.81 | Q128: 0.81 | R128: 0.81 | S128: 0.81 | T128: 0.81
I129: =G27 -> l | K129: 0.81 | L129: 0.81 | M129: 0.81 | N129: 0.81 | O129: 0.81 | P129: 0.81 | Q129: 0.81 | R129: 0.81 | S129: 0.81 | T129: 0.81
I130: =G28 -> lf | K130: 0.81 | L130: 0.81 | M130: 0.81 | N130: 0.81 | O130: 0.81 | P130: 0.81 | Q130: 0.81 | R130: 0.81 | S130: 0.81 | T130: 0.81
I131: =G29 -> ms | K131: 0.81 | L131: 0.81 | M131: 0.81 | N131: 0.81 | O131: 0.81 | P131: 0.81 | Q131: 0.81 | R131: 0.81 | S131: 0.81 | T131: 0.81
I132: =G30 -> o | K132: 0.81 | L132: 0.81 | M132: 0.81 | N132: 0.81 | O132: 0.81 | P132: 0.81 | Q132: 0.81 | R132: 0.81 | S132: 0.81 | T132: 0.81
...

Sheet Periods
E4: Stocashtic Feed Periods
U18: Day of yr - input for AFO
E20: period | F20: typ | G20: season0 | H20: season1 | I20: season2 | J20: season3 | K20: season4 | L20: season5 | M20: season6 | N20: season7 | O20: season8 | T20: period | U20: typ | V20: season0 | W20: season1 | X20: season2 | Y20: season3 | Z20: season4 | AA20: season5 | AB20: season6 | AC20: season7 | AD20: season8
E21: FP0 | F21: 43560 | G21: 43560 | H21: =G21 -> 43560 | I21: =H21 -> 43560 | J21: =G21 -> 43560 | K21: =J21 -> 43560 | L21: =K21 -> 43560 | M21: =J21 -> 43560 | N21: =M21 -> 43560 | O21: =N21 -> 43560 | P21: First feed period is the start of the season (beginning of dry seeding) | T21: FP0 | U21: =MIN(51,INT((F21 - DATE(YEAR(F21),1,1))/7))*7+IF(YEAR(F21)>YEAR(F$21),364,0) -> 91 | V21: =MIN(51,INT((G21 - DATE(YEAR(G21),1,1))/7))*7+IF(YEAR(G21)>YEAR(G$21),364,0) -> 91 | W21: =MIN(51,INT((H21 - DATE(YEAR(H21),1,1))/7))*7+IF(YEAR(H21)>YEAR(H$21),364,0) -> 91 | X21: =MIN(51,INT((I21 - DATE(YEAR(I21),1,1))/7))*7+IF(YEAR(I21)>YEAR(I$21),364,0) -> 91 | Y21: =MIN(51,INT((J21 - DATE(YEAR(J21),1,1))/7))*7+IF(YEAR(J21)>YEAR(J$21),364,0) -> 91 | Z21: =MIN(51,INT((K21 - DATE(YEAR(K21),1,1))/7))*7+IF(YEAR(K21)>YEAR(K$21),364,0) -> 91 | AA21: =MIN(51,INT((L21 - DATE(YEAR(L21),1,1))/7))*7+IF(YEAR(L21)>YEAR(L$21),364,0) -> 91 | AB21: =MIN(51,INT((M21 - DATE(YEAR(M21),1,1))/7))*7+IF(YEAR(M21)>YEAR(M$21),364,0) -> 91 | ... AD21: =MIN(51,INT((O21 - DATE(YEAR(O21),1,1))/7))*7+IF(YEAR(O21)>YEAR(O$21),364,0) -> 91
E22: FP1 | F22: 43600 | G22: 43589 | H22: =G22 -> 43589 | I22: =H22 -> 43589 | J22: =I22 -> 43589 | K22: 43606 | L22: =K22 -> 43606 | M22: =K22 -> 43606 | N22: =M22 -> 43606 | O22: =N22 -> 43606 | T22: FP1 | U22: =MIN(51,INT((F22 - DATE(YEAR(F22),1,1))/7))*7+IF(YEAR(F22)>YEAR(F$21),364,0) -> 133 | V22: =MIN(51,INT((G22 - DATE(YEAR(G22),1,1))/7))*7+IF(YEAR(G22)>YEAR(G$21),364,0) -> 119 | W22: =MIN(51,INT((H22 - DATE(YEAR(H22),1,1))/7))*7+IF(YEAR(H22)>YEAR(H$21),364,0) -> 119 | X22: =MIN(51,INT((I22 - DATE(YEAR(I22),1,1))/7))*7+IF(YEAR(I22)>YEAR(I$21),364,0) -> 119 | Y22: =MIN(51,INT((J22 - DATE(YEAR(J22),1,1))/7))*7+IF(YEAR(J22)>YEAR(J$21),364,0) -> 119 | Z22: =MIN(51,INT((K22 - DATE(YEAR(K22),1,1))/7))*7+IF(YEAR(K22)>YEAR(K$21),364,0) -> 140 | AA22: =MIN(51,INT((L22 - DATE(YEAR(L22),1,1))/7))*7+IF(YEAR(L22)>YEAR(L$21),364,0) -> 140 | AB22: =MIN(51,INT((M22 - DATE(YEAR(M22),1,1))/7))*7+IF(YEAR(M22)>YEAR(M$21),364,0) -> 140 | ... AD22: =MIN(51,INT((O22 - DATE(YEAR(O22),1,1))/7))*7+IF(YEAR(O22)>YEAR(O$21),364,0) -> 140
E23: FP2 | F23: 43631 | G23: 43631 | H23: =G23 -> 43631 | I23: =H23 -> 43631 | J23: =I23 -> 43631 | K23: =J23 -> 43631 | L23: =K23 -> 43631 | M23: =L23 -> 43631 | N23: =M23 -> 43631 | O23: =N23 -> 43631 | T23: FP2 | U23: =MIN(51,INT((F23 - DATE(YEAR(F23),1,1))/7))*7+IF(YEAR(F23)>YEAR(F$21),364,0) -> 161 | V23: =MIN(51,INT((G23 - DATE(YEAR(G23),1,1))/7))*7+IF(YEAR(G23)>YEAR(G$21),364,0) -> 161 | W23: =MIN(51,INT((H23 - DATE(YEAR(H23),1,1))/7))*7+IF(YEAR(H23)>YEAR(H$21),364,0) -> 161 | X23: =MIN(51,INT((I23 - DATE(YEAR(I23),1,1))/7))*7+IF(YEAR(I23)>YEAR(I$21),364,0) -> 161 | Y23: =MIN(51,INT((J23 - DATE(YEAR(J23),1,1))/7))*7+IF(YEAR(J23)>YEAR(J$21),364,0) -> 161 | Z23: =MIN(51,INT((K23 - DATE(YEAR(K23),1,1))/7))*7+IF(YEAR(K23)>YEAR(K$21),364,0) -> 161 | AA23: =MIN(51,INT((L23 - DATE(YEAR(L23),1,1))/7))*7+IF(YEAR(L23)>YEAR(L$21),364,0) -> 161 | AB23: =MIN(51,INT((M23 - DATE(YEAR(M23),1,1))/7))*7+IF(YEAR(M23)>YEAR(M$21),364,0) -> 161 | ... AD23: =MIN(51,INT((O23 - DATE(YEAR(O23),1,1))/7))*7+IF(YEAR(O23)>YEAR(O$21),364,0) -> 161
E24: FP3 | F24: 43684 | G24: 43684 | H24: =G24 -> 43684 | I24: 43684 | J24: =I24 -> 43684 | K24: 43684 | L24: =K24 -> 43684 | M24: 43684 | N24: =M24 -> 43684 | O24: =N24 -> 43684 | T24: FP3 | U24: =MIN(51,INT((F24 - DATE(YEAR(F24),1,1))/7))*7+IF(YEAR(F24)>YEAR(F$21),364,0) -> 217 | V24: =MIN(51,INT((G24 - DATE(YEAR(G24),1,1))/7))*7+IF(YEAR(G24)>YEAR(G$21),364,0) -> 217 | W24: =MIN(51,INT((H24 - DATE(YEAR(H24),1,1))/7))*7+IF(YEAR(H24)>YEAR(H$21),364,0) -> 217 | X24: =MIN(51,INT((I24 - DATE(YEAR(I24),1,1))/7))*7+IF(YEAR(I24)>YEAR(I$21),364,0) -> 217 | Y24: =MIN(51,INT((J24 - DATE(YEAR(J24),1,1))/7))*7+IF(YEAR(J24)>YEAR(J$21),364,0) -> 217 | Z24: =MIN(51,INT((K24 - DATE(YEAR(K24),1,1))/7))*7+IF(YEAR(K24)>YEAR(K$21),364,0) -> 217 | AA24: =MIN(51,INT((L24 - DATE(YEAR(L24),1,1))/7))*7+IF(YEAR(L24)>YEAR(L$21),364,0) -> 217 | AB24: =MIN(51,INT((M24 - DATE(YEAR(M24),1,1))/7))*7+IF(YEAR(M24)>YEAR(M$21),364,0) -> 217 | ... AD24: =MIN(51,INT((O24 - DATE(YEAR(O24),1,1))/7))*7+IF(YEAR(O24)>YEAR(O$21),364,0) -> 217
E25: FP4 | F25: 43709 | G25: 43709 | H25: =G25 -> 43709 | I25: =H25 -> 43709 | J25: =I25 -> 43709 | K25: =J25 -> 43709 | L25: =K25 -> 43709 | M25: =L25 -> 43709 | N25: =M25 -> 43709 | O25: =N25 -> 43709 | T25: FP4 | U25: =MIN(51,INT((F25 - DATE(YEAR(F25),1,1))/7))*7+IF(YEAR(F25)>YEAR(F$21),364,0) -> 238 | V25: =MIN(51,INT((G25 - DATE(YEAR(G25),1,1))/7))*7+IF(YEAR(G25)>YEAR(G$21),364,0) -> 238 | W25: =MIN(51,INT((H25 - DATE(YEAR(H25),1,1))/7))*7+IF(YEAR(H25)>YEAR(H$21),364,0) -> 238 | X25: =MIN(51,INT((I25 - DATE(YEAR(I25),1,1))/7))*7+IF(YEAR(I25)>YEAR(I$21),364,0) -> 238 | Y25: =MIN(51,INT((J25 - DATE(YEAR(J25),1,1))/7))*7+IF(YEAR(J25)>YEAR(J$21),364,0) -> 238 | Z25: =MIN(51,INT((K25 - DATE(YEAR(K25),1,1))/7))*7+IF(YEAR(K25)>YEAR(K$21),364,0) -> 238 | AA25: =MIN(51,INT((L25 - DATE(YEAR(L25),1,1))/7))*7+IF(YEAR(L25)>YEAR(L$21),364,0) -> 238 | AB25: =MIN(51,INT((M25 - DATE(YEAR(M25),1,1))/7))*7+IF(YEAR(M25)>YEAR(M$21),364,0) -> 238 | ... AD25: =MIN(51,INT((O25 - DATE(YEAR(O25),1,1))/7))*7+IF(YEAR(O25)>YEAR(O$21),364,0) -> 238
E26: FP5 | F26: 43738 | G26: 43738 | H26: =F26 -> 43738 | I26: =G26 -> 43738 | J26: =H26 -> 43738 | K26: 43738 | L26: =J26 -> 43738 | M26: =K26 -> 43738 | N26: =L26 -> 43738 | O26: =N26 -> 43738 | T26: FP5 | U26: =MIN(51,INT((F26 - DATE(YEAR(F26),1,1))/7))*7+IF(YEAR(F26)>YEAR(F$21),364,0) -> 266 | V26: =MIN(51,INT((G26 - DATE(YEAR(G26),1,1))/7))*7+IF(YEAR(G26)>YEAR(G$21),364,0) -> 266 | W26: =MIN(51,INT((H26 - DATE(YEAR(H26),1,1))/7))*7+IF(YEAR(H26)>YEAR(H$21),364,0) -> 266 | X26: =MIN(51,INT((I26 - DATE(YEAR(I26),1,1))/7))*7+IF(YEAR(I26)>YEAR(I$21),364,0) -> 266 | Y26: =MIN(51,INT((J26 - DATE(YEAR(J26),1,1))/7))*7+IF(YEAR(J26)>YEAR(J$21),364,0) -> 266 | Z26: =MIN(51,INT((K26 - DATE(YEAR(K26),1,1))/7))*7+IF(YEAR(K26)>YEAR(K$21),364,0) -> 266 | AA26: =MIN(51,INT((L26 - DATE(YEAR(L26),1,1))/7))*7+IF(YEAR(L26)>YEAR(L$21),364,0) -> 266 | AB26: =MIN(51,INT((M26 - DATE(YEAR(M26),1,1))/7))*7+IF(YEAR(M26)>YEAR(M$21),364,0) -> 266 | ... AD26: =MIN(51,INT((O26 - DATE(YEAR(O26),1,1))/7))*7+IF(YEAR(O26)>YEAR(O$21),364,0) -> 266
E27: FP6 | F27: 43753 | G27: 43758 | H27: =G27 -> 43758 | I27: =H27 -> 43758 | J27: =I27 -> 43758 | K27: 43748 | L27: =K27 -> 43748 | M27: =L27 -> 43748 | N27: =M27 -> 43748 | O27: =N27 -> 43748 | T27: FP6 | U27: =MIN(51,INT((F27 - DATE(YEAR(F27),1,1))/7))*7+IF(YEAR(F27)>YEAR(F$21),364,0) -> 287 | V27: =MIN(51,INT((G27 - DATE(YEAR(G27),1,1))/7))*7+IF(YEAR(G27)>YEAR(G$21),364,0) -> 287 | W27: =MIN(51,INT((H27 - DATE(YEAR(H27),1,1))/7))*7+IF(YEAR(H27)>YEAR(H$21),364,0) -> 287 | X27: =MIN(51,INT((I27 - DATE(YEAR(I27),1,1))/7))*7+IF(YEAR(I27)>YEAR(I$21),364,0) -> 287 | Y27: =MIN(51,INT((J27 - DATE(YEAR(J27),1,1))/7))*7+IF(YEAR(J27)>YEAR(J$21),364,0) -> 287 | Z27: =MIN(51,INT((K27 - DATE(YEAR(K27),1,1))/7))*7+IF(YEAR(K27)>YEAR(K$21),364,0) -> 280 | AA27: =MIN(51,INT((L27 - DATE(YEAR(L27),1,1))/7))*7+IF(YEAR(L27)>YEAR(L$21),364,0) -> 280 | AB27: =MIN(51,INT((M27 - DATE(YEAR(M27),1,1))/7))*7+IF(YEAR(M27)>YEAR(M$21),364,0) -> 280 | ... AD27: =MIN(51,INT((O27 - DATE(YEAR(O27),1,1))/7))*7+IF(YEAR(O27)>YEAR(O$21),364,0) -> 280
E28: FP7 | F28: 43794 | G28: 43794 | H28: =G28 -> 43794 | I28: =H28 -> 43794 | J28: =I28 -> 43794 | K28: =J28 -> 43794 | L28: =K28 -> 43794 | M28: =L28 -> 43794 | N28: =M28 -> 43794 | O28: =N28 -> 43794 | T28: FP7 | U28: =MIN(51,INT((F28 - DATE(YEAR(F28),1,1))/7))*7+IF(YEAR(F28)>YEAR(F$21),364,0) -> 322 | V28: =MIN(51,INT((G28 - DATE(YEAR(G28),1,1))/7))*7+IF(YEAR(G28)>YEAR(G$21),364,0) -> 322 | W28: =MIN(51,INT((H28 - DATE(YEAR(H28),1,1))/7))*7+IF(YEAR(H28)>YEAR(H$21),364,0) -> 322 | X28: =MIN(51,INT((I28 - DATE(YEAR(I28),1,1))/7))*7+IF(YEAR(I28)>YEAR(I$21),364,0) -> 322 | Y28: =MIN(51,INT((J28 - DATE(YEAR(J28),1,1))/7))*7+IF(YEAR(J28)>YEAR(J$21),364,0) -> 322 | Z28: =MIN(51,INT((K28 - DATE(YEAR(K28),1,1))/7))*7+IF(YEAR(K28)>YEAR(K$21),364,0) -> 322 | AA28: =MIN(51,INT((L28 - DATE(YEAR(L28),1,1))/7))*7+IF(YEAR(L28)>YEAR(L$21),364,0) -> 322 | AB28: =MIN(51,INT((M28 - DATE(YEAR(M28),1,1))/7))*7+IF(YEAR(M28)>YEAR(M$21),364,0) -> 322 | ... AD28: =MIN(51,INT((O28 - DATE(YEAR(O28),1,1))/7))*7+IF(YEAR(O28)>YEAR(O$21),364,0) -> 322
E29: FP8 | F29: 43831 | G29: 43831 | H29: =G29 -> 43831 | I29: =H29 -> 43831 | J29: =I29 -> 43831 | K29: =J29 -> 43831 | L29: =K29 -> 43831 | M29: =L29 -> 43831 | N29: =M29 -> 43831 | O29: =N29 -> 43831 | T29: FP8 | U29: =MIN(51,INT((F29 - DATE(YEAR(F29),1,1))/7))*7+IF(YEAR(F29)>YEAR(F$21),364,0) -> 364 | V29: =MIN(51,INT((G29 - DATE(YEAR(G29),1,1))/7))*7+IF(YEAR(G29)>YEAR(G$21),364,0) -> 364 | W29: =MIN(51,INT((H29 - DATE(YEAR(H29),1,1))/7))*7+IF(YEAR(H29)>YEAR(H$21),364,0) -> 364 | X29: =MIN(51,INT((I29 - DATE(YEAR(I29),1,1))/7))*7+IF(YEAR(I29)>YEAR(I$21),364,0) -> 364 | Y29: =MIN(51,INT((J29 - DATE(YEAR(J29),1,1))/7))*7+IF(YEAR(J29)>YEAR(J$21),364,0) -> 364 | Z29: =MIN(51,INT((K29 - DATE(YEAR(K29),1,1))/7))*7+IF(YEAR(K29)>YEAR(K$21),364,0) -> 364 | AA29: =MIN(51,INT((L29 - DATE(YEAR(L29),1,1))/7))*7+IF(YEAR(L29)>YEAR(L$21),364,0) -> 364 | AB29: =MIN(51,INT((M29 - DATE(YEAR(M29),1,1))/7))*7+IF(YEAR(M29)>YEAR(M$21),364,0) -> 364 | ... AD29: =MIN(51,INT((O29 - DATE(YEAR(O29),1,1))/7))*7+IF(YEAR(O29)>YEAR(O$21),364,0) -> 364
E30: FP9 | F30: 43876 | G30: 43876 | H30: =G30 -> 43876 | I30: =H30 -> 43876 | J30: =I30 -> 43876 | K30: =J30 -> 43876 | L30: =K30 -> 43876 | M30: =L30 -> 43876 | N30: =M30 -> 43876 | O30: =N30 -> 43876 | T30: FP9 | U30: =MIN(51,INT((F30 - DATE(YEAR(F30),1,1))/7))*7+IF(YEAR(F30)>YEAR(F$21),364,0) -> 406 | V30: =MIN(51,INT((G30 - DATE(YEAR(G30),1,1))/7))*7+IF(YEAR(G30)>YEAR(G$21),364,0) -> 406 | W30: =MIN(51,INT((H30 - DATE(YEAR(H30),1,1))/7))*7+IF(YEAR(H30)>YEAR(H$21),364,0) -> 406 | X30: =MIN(51,INT((I30 - DATE(YEAR(I30),1,1))/7))*7+IF(YEAR(I30)>YEAR(I$21),364,0) -> 406 | Y30: =MIN(51,INT((J30 - DATE(YEAR(J30),1,1))/7))*7+IF(YEAR(J30)>YEAR(J$21),364,0) -> 406 | Z30: =MIN(51,INT((K30 - DATE(YEAR(K30),1,1))/7))*7+IF(YEAR(K30)>YEAR(K$21),364,0) -> 406 | AA30: =MIN(51,INT((L30 - DATE(YEAR(L30),1,1))/7))*7+IF(YEAR(L30)>YEAR(L$21),364,0) -> 406 | AB30: =MIN(51,INT((M30 - DATE(YEAR(M30),1,1))/7))*7+IF(YEAR(M30)>YEAR(M$21),364,0) -> 406 | ... AD30: =MIN(51,INT((O30 - DATE(YEAR(O30),1,1))/7))*7+IF(YEAR(O30)>YEAR(O$21),364,0) -> 406
E31: FP10 | F31: =F21+364 -> 43924 | G31: =G21+364 -> 43924 | H31: =H21+364 -> 43924 | I31: =I21+364 -> 43924 | J31: =J21+364 -> 43924 | K31: =K21+364 -> 43924 | L31: =L21+364 -> 43924 | M31: =M21+364 -> 43924 | ... O31: =O21+364 -> 43924 | T31: FP10 | U31: =MIN(51,INT((F31 - DATE(YEAR(F31),1,1))/7))*7+IF(YEAR(F31)>YEAR(F$21),364,0) -> 455 | V31: =MIN(51,INT((G31 - DATE(YEAR(G31),1,1))/7))*7+IF(YEAR(G31)>YEAR(G$21),364,0) -> 455 | W31: =MIN(51,INT((H31 - DATE(YEAR(H31),1,1))/7))*7+IF(YEAR(H31)>YEAR(H$21),364,0) -> 455 | X31: =MIN(51,INT((I31 - DATE(YEAR(I31),1,1))/7))*7+IF(YEAR(I31)>YEAR(I$21),364,0) -> 455 | Y31: =MIN(51,INT((J31 - DATE(YEAR(J31),1,1))/7))*7+IF(YEAR(J31)>YEAR(J$21),364,0) -> 455 | Z31: =MIN(51,INT((K31 - DATE(YEAR(K31),1,1))/7))*7+IF(YEAR(K31)>YEAR(K$21),364,0) -> 455 | AA31: =MIN(51,INT((L31 - DATE(YEAR(L31),1,1))/7))*7+IF(YEAR(L31)>YEAR(L$21),364,0) -> 455 | AB31: =MIN(51,INT((M31 - DATE(YEAR(M31),1,1))/7))*7+IF(YEAR(M31)>YEAR(M$21),364,0) -> 455 | ... AD31: =MIN(51,INT((O31 - DATE(YEAR(O31),1,1))/7))*7+IF(YEAR(O31)>YEAR(O$21),364,0) -> 455
U32: =MIN(51,INT((F32 - DATE(YEAR(F32),1,1))/7))*7+IF(YEAR(F32)>YEAR(F$21),364,0) -> -7
E35: =E4 -> Stocashtic Feed Periods | AL35: »
E40: Static Labour Periods
G46: typ | H46: season0 | I46: season1 | J46: season2 | K46: season3 | L46: season4 | M46: season5 | N46: season6 | O46: season7 | P46: season8
E47: Seeding periods
F48: start_wet_seeding_gs1 | G48: =F102 -> 43600 | H48: =G102 -> 43589 | I48: =H102 -> 43589 | J48: =I102 -> 43589 | K48: =J102 -> 43589 | L48: =K102 -> 43606 | M48: =L102 -> 43606 | N48: =M102 -> 43606 | ... P48: =O102 -> 43606
F49: AFO version | G49: =MIN(51,INT((G48 - DATE(YEAR(G48),1,1))/7))*7+IF(YEAR(G48)>YEAR(G48),364,0) -> 133 | H49: =MIN(51,INT((H48 - DATE(YEAR(H48),1,1))/7))*7+IF(YEAR(H48)>YEAR(H48),364,0) -> 119 | I49: =MIN(51,INT((I48 - DATE(YEAR(I48),1,1))/7))*7+IF(YEAR(I48)>YEAR(I48),364,0) -> 119 | J49: =MIN(51,INT((J48 - DATE(YEAR(J48),1,1))/7))*7+IF(YEAR(J48)>YEAR(J48),364,0) -> 119 | K49: =MIN(51,INT((K48 - DATE(YEAR(K48),1,1))/7))*7+IF(YEAR(K48)>YEAR(K48),364,0) -> 119 | L49: =MIN(51,INT((L48 - DATE(YEAR(L48),1,1))/7))*7+IF(YEAR(L48)>YEAR(L48),364,0) -> 140 | M49: =MIN(51,INT((M48 - DATE(YEAR(M48),1,1))/7))*7+IF(YEAR(M48)>YEAR(M48),364,0) -> 140 | N49: =MIN(51,INT((N48 - DATE(YEAR(N48),1,1))/7))*7+IF(YEAR(N48)>YEAR(N48),364,0) -> 140 | ... P49: =MIN(51,INT((P48 - DATE(YEAR(P48),1,1))/7))*7+IF(YEAR(P48)>YEAR(P48),364,0) -> 140
F51: end_wet_seeding_gs1 | G51: =F105 -> 43621 | H51: =G105 -> 43610 | I51: =H105 -> 43610 | J51: =I105 -> 43610 | K51: =J105 -> 43610 | L51: =K105 -> 43627 | M51: =L105 -> 43627 | N51: =M105 -> 43627 | ... P51: =O105 -> 43627
F52: AFO version | G52: =MIN(51,INT((G51 - DATE(YEAR(G51),1,1))/7))*7+IF(YEAR(G51)>YEAR(G51),364,0) -> 154 | H52: =MIN(51,INT((H51 - DATE(YEAR(H51),1,1))/7))*7+IF(YEAR(H51)>YEAR(H51),364,0) -> 140 | I52: =MIN(51,INT((I51 - DATE(YEAR(I51),1,1))/7))*7+IF(YEAR(I51)>YEAR(I51),364,0) -> 140 | J52: =MIN(51,INT((J51 - DATE(YEAR(J51),1,1))/7))*7+IF(YEAR(J51)>YEAR(J51),364,0) -> 140 | K52: =MIN(51,INT((K51 - DATE(YEAR(K51),1,1))/7))*7+IF(YEAR(K51)>YEAR(K51),364,0) -> 140 | L52: =MIN(51,INT((L51 - DATE(YEAR(L51),1,1))/7))*7+IF(YEAR(L51)>YEAR(L51),364,0) -> 161 | M52: =MIN(51,INT((M51 - DATE(YEAR(M51),1,1))/7))*7+IF(YEAR(M51)>YEAR(M51),364,0) -> 161 | N52: =MIN(51,INT((N51 - DATE(YEAR(N51),1,1))/7))*7+IF(YEAR(N51)>YEAR(N51),364,0) -> 161 | ... P52: =MIN(51,INT((P51 - DATE(YEAR(P51),1,1))/7))*7+IF(YEAR(P51)>YEAR(P51),364,0) -> 161
E54: Contract seeding
F55: start_contract_seeding_gs1 | G55: 43572 | H55: 43572 | I55: 43572 | J55: 43572 | K55: 43572 | L55: 43572 | M55: 43572 | N55: 43572 | O55: 43572 | P55: 43572
F56: AFO version | G56: =MIN(51,INT((G55 - DATE(YEAR(G55),1,1))/7))*7+IF(YEAR(G55)>YEAR(G55),364,0) -> 105 | H56: =MIN(51,INT((H55 - DATE(YEAR(H55),1,1))/7))*7+IF(YEAR(H55)>YEAR(H55),364,0) -> 105 | I56: =MIN(51,INT((I55 - DATE(YEAR(I55),1,1))/7))*7+IF(YEAR(I55)>YEAR(I55),364,0) -> 105 | J56: =MIN(51,INT((J55 - DATE(YEAR(J55),1,1))/7))*7+IF(YEAR(J55)>YEAR(J55),364,0) -> 105 | K56: =MIN(51,INT((K55 - DATE(YEAR(K55),1,1))/7))*7+IF(YEAR(K55)>YEAR(K55),364,0) -> 105 | L56: =MIN(51,INT((L55 - DATE(YEAR(L55),1,1))/7))*7+IF(YEAR(L55)>YEAR(L55),364,0) -> 105 | M56: =MIN(51,INT((M55 - DATE(YEAR(M55),1,1))/7))*7+IF(YEAR(M55)>YEAR(M55),364,0) -> 105 | N56: =MIN(51,INT((N55 - DATE(YEAR(N55),1,1))/7))*7+IF(YEAR(N55)>YEAR(N55),364,0) -> 105 | ... P56: =MIN(51,INT((P55 - DATE(YEAR(P55),1,1))/7))*7+IF(YEAR(P55)>YEAR(P55),364,0) -> 105
F58: end_contract_seeding_gs1 | G58: =G51 -> 43621 | H58: =H51 -> 43610 | I58: =I51 -> 43610 | J58: =J51 -> 43610 | K58: =K51 -> 43610 | L58: =L51 -> 43627 | M58: =M51 -> 43627 | N58: =N51 -> 43627 | ... P58: =P51 -> 43627
F59: AFO version | G59: =MIN(51,INT((G58 - DATE(YEAR(G58),1,1))/7))*7+IF(YEAR(G58)>YEAR(G58),364,0) -> 154 | H59: =MIN(51,INT((H58 - DATE(YEAR(H58),1,1))/7))*7+IF(YEAR(H58)>YEAR(H58),364,0) -> 140 | I59: =MIN(51,INT((I58 - DATE(YEAR(I58),1,1))/7))*7+IF(YEAR(I58)>YEAR(I58),364,0) -> 140 | J59: =MIN(51,INT((J58 - DATE(YEAR(J58),1,1))/7))*7+IF(YEAR(J58)>YEAR(J58),364,0) -> 140 | K59: =MIN(51,INT((K58 - DATE(YEAR(K58),1,1))/7))*7+IF(YEAR(K58)>YEAR(K58),364,0) -> 140 | L59: =MIN(51,INT((L58 - DATE(YEAR(L58),1,1))/7))*7+IF(YEAR(L58)>YEAR(L58),364,0) -> 161 | M59: =MIN(51,INT((M58 - DATE(YEAR(M58),1,1))/7))*7+IF(YEAR(M58)>YEAR(M58),364,0) -> 161 | N59: =MIN(51,INT((N58 - DATE(YEAR(N58),1,1))/7))*7+IF(YEAR(N58)>YEAR(N58),364,0) -> 161 | ... P59: =MIN(51,INT((P58 - DATE(YEAR(P58),1,1))/7))*7+IF(YEAR(P58)>YEAR(P58),364,0) -> 161
E61: Harvest periods
F62: harv_date | G62: =MIN(Crop!I99:I117) -> 43784 | H62: =MIN(Crop!J99:J117) -> 43784 | I62: =MIN(Crop!K99:K117) -> 43784 | J62: =MIN(Crop!L99:L117) -> 43784 | K62: =MIN(Crop!M99:M117) -> 43784 | L62: =MIN(Crop!N99:N117) -> 43784 | M62: =MIN(Crop!O99:O117) -> 43784 | N62: =MIN(Crop!P99:P117) -> 43784 | ... P62: =MIN(Crop!R99:R117) -> 43784
F63: AFO version | G63: =MIN(51,INT((G62 - DATE(YEAR(G62),1,1))/7))*7 -> 315 | H63: =MIN(51,INT((H62 - DATE(YEAR(H62),1,1))/7))*7 -> 315 | I63: =MIN(51,INT((I62 - DATE(YEAR(I62),1,1))/7))*7 -> 315 | J63: =MIN(51,INT((J62 - DATE(YEAR(J62),1,1))/7))*7 -> 315 | K63: =MIN(51,INT((K62 - DATE(YEAR(K62),1,1))/7))*7 -> 315 | L63: =MIN(51,INT((L62 - DATE(YEAR(L62),1,1))/7))*7 -> 315 | M63: =MIN(51,INT((M62 - DATE(YEAR(M62),1,1))/7))*7 -> 315 | N63: =MIN(51,INT((N62 - DATE(YEAR(N62),1,1))/7))*7 -> 315 | ... P63: =MIN(51,INT((P62 - DATE(YEAR(P62),1,1))/7))*7 -> 315
F65: harv_period_lengths | G65: 14 | H65: 14 | I65: 14 | J65: 14 | K65: 14 | L65: 14 | M65: 14 | N65: 14 | O65: 14 | P65: 14
G66: 37 | H66: 37 | I66: 37 | J66: 37 | K66: 37 | L66: 37 | M66: 37 | N66: 37 | O66: 37 | P66: 37
F67: AFO version | G67: =INT(G65/7)*7 -> 14 | H67: =INT(H65/7)*7 -> 14 | I67: =INT(I65/7)*7 -> 14 | J67: =INT(J65/7)*7 -> 14 | K67: =INT(K65/7)*7 -> 14 | L67: =INT(L65/7)*7 -> 14 | M67: =INT(M65/7)*7 -> 14 | N67: =INT(N65/7)*7 -> 14 | ... P67: =INT(P65/7)*7 -> 14
G68: =INT(G66/7)*7 -> 35 | H68: =INT(H66/7)*7 -> 35 | I68: =INT(I66/7)*7 -> 35 | J68: =INT(J66/7)*7 -> 35 | K68: =INT(K66/7)*7 -> 35 | L68: =INT(L66/7)*7 -> 35 | M68: =INT(M66/7)*7 -> 35 | N68: =INT(N66/7)*7 -> 35 | ... P68: =INT(P66/7)*7 -> 35
E72: =E40 -> Static Labour Periods | AL72: »
E77: Stocashtic Labour Periods
G98: early | K98: medium | M98: late | U98: Day of yr - input for AFO
F100: typ | G100: season0 | H100: season1 | I100: season2 | J100: season3 | K100: season4 | L100: season5 | M100: season6 | N100: season7 | O100: season8 | U100: =F100 -> typ | V100: =G100 -> season0 | W100: =H100 -> season1 | X100: =I100 -> season2 | Y100: =J100 -> season3 | Z100: =K100 -> season4 | AA100: =L100 -> season5 | AB100: =M100 -> season6 | ... AD100: =O100 -> season8
E101: P00 | F101: =F21 -> 43560 | G101: =G21 -> 43560 | H101: =H21 -> 43560 | I101: =I21 -> 43560 | J101: =J21 -> 43560 | K101: =K21 -> 43560 | L101: =L21 -> 43560 | M101: =M21 -> 43560 | ... O101: =O21 -> 43560 | P101: start of year | T101: P00 | U101: =MIN(51,INT((F101 - DATE(YEAR(F101),1,1))/7))*7+IF(YEAR(F101)>YEAR(F$101),364,0) -> 91 | V101: =MIN(51,INT((G101 - DATE(YEAR(G101),1,1))/7))*7+IF(YEAR(G101)>YEAR(G$101),364,0) -> 91 | W101: =MIN(51,INT((H101 - DATE(YEAR(H101),1,1))/7))*7+IF(YEAR(H101)>YEAR(H$101),364,0) -> 91 | X101: =MIN(51,INT((I101 - DATE(YEAR(I101),1,1))/7))*7+IF(YEAR(I101)>YEAR(I$101),364,0) -> 91 | Y101: =MIN(51,INT((J101 - DATE(YEAR(J101),1,1))/7))*7+IF(YEAR(J101)>YEAR(J$101),364,0) -> 91 | Z101: =MIN(51,INT((K101 - DATE(YEAR(K101),1,1))/7))*7+IF(YEAR(K101)>YEAR(K$101),364,0) -> 91 | AA101: =MIN(51,INT((L101 - DATE(YEAR(L101),1,1))/7))*7+IF(YEAR(L101)>YEAR(L$101),364,0) -> 91 | AB101: =MIN(51,INT((M101 - DATE(YEAR(M101),1,1))/7))*7+IF(YEAR(M101)>YEAR(M$101),364,0) -> 91 | ... AD101: =MIN(51,INT((O101 - DATE(YEAR(O101),1,1))/7))*7+IF(YEAR(O101)>YEAR(O$101),364,0) -> 91
E102: P01 | F102: =F22 -> 43600 | G102: =G22 -> 43589 | H102: =H22 -> 43589 | I102: =I22 -> 43589 | J102: =J22 -> 43589 | K102: =K22 -> 43606 | L102: =L22 -> 43606 | M102: =M22 -> 43606 | ... O102: =O22 -> 43606 | T102: P01 | U102: =MIN(51,INT((F102 - DATE(YEAR(F102),1,1))/7))*7+IF(YEAR(F102)>YEAR(F$101),364,0) -> 133 | V102: =MIN(51,INT((G102 - DATE(YEAR(G102),1,1))/7))*7+IF(YEAR(G102)>YEAR(G$101),364,0) -> 119 | W102: =MIN(51,INT((H102 - DATE(YEAR(H102),1,1))/7))*7+IF(YEAR(H102)>YEAR(H$101),364,0) -> 119 | X102: =MIN(51,INT((I102 - DATE(YEAR(I102),1,1))/7))*7+IF(YEAR(I102)>YEAR(I$101),364,0) -> 119 | Y102: =MIN(51,INT((J102 - DATE(YEAR(J102),1,1))/7))*7+IF(YEAR(J102)>YEAR(J$101),364,0) -> 119 | Z102: =MIN(51,INT((K102 - DATE(YEAR(K102),1,1))/7))*7+IF(YEAR(K102)>YEAR(K$101),364,0) -> 140 | AA102: =MIN(51,INT((L102 - DATE(YEAR(L102),1,1))/7))*7+IF(YEAR(L102)>YEAR(L$101),364,0) -> 140 | AB102: =MIN(51,INT((M102 - DATE(YEAR(M102),1,1))/7))*7+IF(YEAR(M102)>YEAR(M$101),364,0) -> 140 | ... AD102: =MIN(51,INT((O102 - DATE(YEAR(O102),1,1))/7))*7+IF(YEAR(O102)>YEAR(O$101),364,0) -> 140
E103: P02 | F103: =F102+7 -> 43607 | G103: =G102+7 -> 43596 | H103: =H102+7 -> 43596 | I103: =I102+7 -> 43596 | J103: =J102+7 -> 43596 | K103: =K102+7 -> 43613 | L103: =L102+7 -> 43613 | M103: =M102+7 -> 43613 | ... O103: =O102+7 -> 43613 | T103: P02 | U103: =MIN(51,INT((F103 - DATE(YEAR(F103),1,1))/7))*7+IF(YEAR(F103)>YEAR(F$101),364,0) -> 140 | V103: =MIN(51,INT((G103 - DATE(YEAR(G103),1,1))/7))*7+IF(YEAR(G103)>YEAR(G$101),364,0) -> 126 | W103: =MIN(51,INT((H103 - DATE(YEAR(H103),1,1))/7))*7+IF(YEAR(H103)>YEAR(H$101),364,0) -> 126 | X103: =MIN(51,INT((I103 - DATE(YEAR(I103),1,1))/7))*7+IF(YEAR(I103)>YEAR(I$101),364,0) -> 126 | Y103: =MIN(51,INT((J103 - DATE(YEAR(J103),1,1))/7))*7+IF(YEAR(J103)>YEAR(J$101),364,0) -> 126 | Z103: =MIN(51,INT((K103 - DATE(YEAR(K103),1,1))/7))*7+IF(YEAR(K103)>YEAR(K$101),364,0) -> 147 | AA103: =MIN(51,INT((L103 - DATE(YEAR(L103),1,1))/7))*7+IF(YEAR(L103)>YEAR(L$101),364,0) -> 147 | AB103: =MIN(51,INT((M103 - DATE(YEAR(M103),1,1))/7))*7+IF(YEAR(M103)>YEAR(M$101),364,0) -> 147 | ... AD103: =MIN(51,INT((O103 - DATE(YEAR(O103),1,1))/7))*7+IF(YEAR(O103)>YEAR(O$101),364,0) -> 147
E104: P03 | F104: =F103+7 -> 43614 | G104: =G103+7 -> 43603 | H104: =H103+7 -> 43603 | I104: =I103+7 -> 43603 | J104: =J103+7 -> 43603 | K104: =K103+7 -> 43620 | L104: =L103+7 -> 43620 | M104: =M103+7 -> 43620 | ... O104: =O103+7 -> 43620 | T104: P03 | U104: =MIN(51,INT((F104 - DATE(YEAR(F104),1,1))/7))*7+IF(YEAR(F104)>YEAR(F$101),364,0) -> 147 | V104: =MIN(51,INT((G104 - DATE(YEAR(G104),1,1))/7))*7+IF(YEAR(G104)>YEAR(G$101),364,0) -> 133 | W104: =MIN(51,INT((H104 - DATE(YEAR(H104),1,1))/7))*7+IF(YEAR(H104)>YEAR(H$101),364,0) -> 133 | X104: =MIN(51,INT((I104 - DATE(YEAR(I104),1,1))/7))*7+IF(YEAR(I104)>YEAR(I$101),364,0) -> 133 | Y104: =MIN(51,INT((J104 - DATE(YEAR(J104),1,1))/7))*7+IF(YEAR(J104)>YEAR(J$101),364,0) -> 133 | Z104: =MIN(51,INT((K104 - DATE(YEAR(K104),1,1))/7))*7+IF(YEAR(K104)>YEAR(K$101),364,0) -> 154 | AA104: =MIN(51,INT((L104 - DATE(YEAR(L104),1,1))/7))*7+IF(YEAR(L104)>YEAR(L$101),364,0) -> 154 | AB104: =MIN(51,INT((M104 - DATE(YEAR(M104),1,1))/7))*7+IF(YEAR(M104)>YEAR(M$101),364,0) -> 154 | ... AD104: =MIN(51,INT((O104 - DATE(YEAR(O104),1,1))/7))*7+IF(YEAR(O104)>YEAR(O$101),364,0) -> 154
E105: P04 | F105: =F104+7 -> 43621 | G105: =G104+7 -> 43610 | H105: =H104+7 -> 43610 | I105: =I104+7 -> 43610 | J105: =J104+7 -> 43610 | K105: =K104+7 -> 43627 | L105: =L104+7 -> 43627 | M105: =M104+7 -> 43627 | ... O105: =O104+7 -> 43627 | Q105: Season Node dates | T105: P04 | U105: =MIN(51,INT((F105 - DATE(YEAR(F105),1,1))/7))*7+IF(YEAR(F105)>YEAR(F$101),364,0) -> 154 | V105: =MIN(51,INT((G105 - DATE(YEAR(G105),1,1))/7))*7+IF(YEAR(G105)>YEAR(G$101),364,0) -> 140 | W105: =MIN(51,INT((H105 - DATE(YEAR(H105),1,1))/7))*7+IF(YEAR(H105)>YEAR(H$101),364,0) -> 140 | X105: =MIN(51,INT((I105 - DATE(YEAR(I105),1,1))/7))*7+IF(YEAR(I105)>YEAR(I$101),364,0) -> 140 | Y105: =MIN(51,INT((J105 - DATE(YEAR(J105),1,1))/7))*7+IF(YEAR(J105)>YEAR(J$101),364,0) -> 140 | Z105: =MIN(51,INT((K105 - DATE(YEAR(K105),1,1))/7))*7+IF(YEAR(K105)>YEAR(K$101),364,0) -> 161 | AA105: =MIN(51,INT((L105 - DATE(YEAR(L105),1,1))/7))*7+IF(YEAR(L105)>YEAR(L$101),364,0) -> 161 | AB105: =MIN(51,INT((M105 - DATE(YEAR(M105),1,1))/7))*7+IF(YEAR(M105)>YEAR(M$101),364,0) -> 161 | ... AD105: =MIN(51,INT((O105 - DATE(YEAR(O105),1,1))/7))*7+IF(YEAR(O105)>YEAR(O$101),364,0) -> 161
E106: P05 | F106: =F23 -> 43631 | G106: =G23 -> 43631 | H106: =H23 -> 43631 | I106: =I23 -> 43631 | J106: =J23 -> 43631 | K106: =K23 -> 43631 | L106: =L23 -> 43631 | M106: =M23 -> 43631 | ... O106: =O23 -> 43631 | Q106: start of wet seeding | T106: P05 | U106: =MIN(51,INT((F106 - DATE(YEAR(F106),1,1))/7))*7+IF(YEAR(F106)>YEAR(F$101),364,0) -> 161 | V106: =MIN(51,INT((G106 - DATE(YEAR(G106),1,1))/7))*7+IF(YEAR(G106)>YEAR(G$101),364,0) -> 161 | W106: =MIN(51,INT((H106 - DATE(YEAR(H106),1,1))/7))*7+IF(YEAR(H106)>YEAR(H$101),364,0) -> 161 | X106: =MIN(51,INT((I106 - DATE(YEAR(I106),1,1))/7))*7+IF(YEAR(I106)>YEAR(I$101),364,0) -> 161 | Y106: =MIN(51,INT((J106 - DATE(YEAR(J106),1,1))/7))*7+IF(YEAR(J106)>YEAR(J$101),364,0) -> 161 | Z106: =MIN(51,INT((K106 - DATE(YEAR(K106),1,1))/7))*7+IF(YEAR(K106)>YEAR(K$101),364,0) -> 161 | AA106: =MIN(51,INT((L106 - DATE(YEAR(L106),1,1))/7))*7+IF(YEAR(L106)>YEAR(L$101),364,0) -> 161 | AB106: =MIN(51,INT((M106 - DATE(YEAR(M106),1,1))/7))*7+IF(YEAR(M106)>YEAR(M$101),364,0) -> 161 | ... AD106: =MIN(51,INT((O106 - DATE(YEAR(O106),1,1))/7))*7+IF(YEAR(O106)>YEAR(O$101),364,0) -> 161
E107: P06 | F107: 43678 | G107: 43678 | H107: 43678 | I107: 43678 | J107: 43678 | K107: 43678 | L107: 43678 | M107: 43678 | N107: 43678 | O107: 43678 | T107: P06 | U107: =MIN(51,INT((F107 - DATE(YEAR(F107),1,1))/7))*7+IF(YEAR(F107)>YEAR(F$101),364,0) -> 210 | V107: =MIN(51,INT((G107 - DATE(YEAR(G107),1,1))/7))*7+IF(YEAR(G107)>YEAR(G$101),364,0) -> 210 | W107: =MIN(51,INT((H107 - DATE(YEAR(H107),1,1))/7))*7+IF(YEAR(H107)>YEAR(H$101),364,0) -> 210 | X107: =MIN(51,INT((I107 - DATE(YEAR(I107),1,1))/7))*7+IF(YEAR(I107)>YEAR(I$101),364,0) -> 210 | Y107: =MIN(51,INT((J107 - DATE(YEAR(J107),1,1))/7))*7+IF(YEAR(J107)>YEAR(J$101),364,0) -> 210 | Z107: =MIN(51,INT((K107 - DATE(YEAR(K107),1,1))/7))*7+IF(YEAR(K107)>YEAR(K$101),364,0) -> 210 | AA107: =MIN(51,INT((L107 - DATE(YEAR(L107),1,1))/7))*7+IF(YEAR(L107)>YEAR(L$101),364,0) -> 210 | AB107: =MIN(51,INT((M107 - DATE(YEAR(M107),1,1))/7))*7+IF(YEAR(M107)>YEAR(M$101),364,0) -> 210 | ... AD107: =MIN(51,INT((O107 - DATE(YEAR(O107),1,1))/7))*7+IF(YEAR(O107)>YEAR(O$101),364,0) -> 210
E108: P07 | F108: =F25 -> 43709 | G108: =G25 -> 43709 | H108: =H25 -> 43709 | I108: =I25 -> 43709 | J108: =J25 -> 43709 | K108: =K25 -> 43709 | L108: =L25 -> 43709 | M108: =M25 -> 43709 | ... O108: =O25 -> 43709 | T108: P07 | U108: =MIN(51,INT((F108 - DATE(YEAR(F108),1,1))/7))*7+IF(YEAR(F108)>YEAR(F$101),364,0) -> 238 | V108: =MIN(51,INT((G108 - DATE(YEAR(G108),1,1))/7))*7+IF(YEAR(G108)>YEAR(G$101),364,0) -> 238 | W108: =MIN(51,INT((H108 - DATE(YEAR(H108),1,1))/7))*7+IF(YEAR(H108)>YEAR(H$101),364,0) -> 238 | X108: =MIN(51,INT((I108 - DATE(YEAR(I108),1,1))/7))*7+IF(YEAR(I108)>YEAR(I$101),364,0) -> 238 | Y108: =MIN(51,INT((J108 - DATE(YEAR(J108),1,1))/7))*7+IF(YEAR(J108)>YEAR(J$101),364,0) -> 238 | Z108: =MIN(51,INT((K108 - DATE(YEAR(K108),1,1))/7))*7+IF(YEAR(K108)>YEAR(K$101),364,0) -> 238 | AA108: =MIN(51,INT((L108 - DATE(YEAR(L108),1,1))/7))*7+IF(YEAR(L108)>YEAR(L$101),364,0) -> 238 | AB108: =MIN(51,INT((M108 - DATE(YEAR(M108),1,1))/7))*7+IF(YEAR(M108)>YEAR(M$101),364,0) -> 238 | ... AD108: =MIN(51,INT((O108 - DATE(YEAR(O108),1,1))/7))*7+IF(YEAR(O108)>YEAR(O$101),364,0) -> 238
E109: P08 | F109: 43739 | G109: 43739 | H109: 43739 | I109: 43739 | J109: 43739 | K109: 43739 | L109: 43739 | M109: 43739 | N109: 43739 | O109: 43739 | T109: P08 | U109: =MIN(51,INT((F109 - DATE(YEAR(F109),1,1))/7))*7+IF(YEAR(F109)>YEAR(F$101),364,0) -> 273 | V109: =MIN(51,INT((G109 - DATE(YEAR(G109),1,1))/7))*7+IF(YEAR(G109)>YEAR(G$101),364,0) -> 273 | W109: =MIN(51,INT((H109 - DATE(YEAR(H109),1,1))/7))*7+IF(YEAR(H109)>YEAR(H$101),364,0) -> 273 | X109: =MIN(51,INT((I109 - DATE(YEAR(I109),1,1))/7))*7+IF(YEAR(I109)>YEAR(I$101),364,0) -> 273 | Y109: =MIN(51,INT((J109 - DATE(YEAR(J109),1,1))/7))*7+IF(YEAR(J109)>YEAR(J$101),364,0) -> 273 | Z109: =MIN(51,INT((K109 - DATE(YEAR(K109),1,1))/7))*7+IF(YEAR(K109)>YEAR(K$101),364,0) -> 273 | AA109: =MIN(51,INT((L109 - DATE(YEAR(L109),1,1))/7))*7+IF(YEAR(L109)>YEAR(L$101),364,0) -> 273 | AB109: =MIN(51,INT((M109 - DATE(YEAR(M109),1,1))/7))*7+IF(YEAR(M109)>YEAR(M$101),364,0) -> 273 | ... AD109: =MIN(51,INT((O109 - DATE(YEAR(O109),1,1))/7))*7+IF(YEAR(O109)>YEAR(O$101),364,0) -> 273
E110: P09 | F110: =G62 -> 43784 | G110: =H62 -> 43784 | H110: =I62 -> 43784 | I110: =J62 -> 43784 | J110: =K62 -> 43784 | K110: =L62 -> 43784 | L110: =M62 -> 43784 | M110: =N62 -> 43784 | ... O110: =P62 -> 43784 | P110: start of early harvest | T110: P09 | U110: =MIN(51,INT((F110 - DATE(YEAR(F110),1,1))/7))*7+IF(YEAR(F110)>YEAR(F$101),364,0) -> 315 | V110: =MIN(51,INT((G110 - DATE(YEAR(G110),1,1))/7))*7+IF(YEAR(G110)>YEAR(G$101),364,0) -> 315 | W110: =MIN(51,INT((H110 - DATE(YEAR(H110),1,1))/7))*7+IF(YEAR(H110)>YEAR(H$101),364,0) -> 315 | X110: =MIN(51,INT((I110 - DATE(YEAR(I110),1,1))/7))*7+IF(YEAR(I110)>YEAR(I$101),364,0) -> 315 | Y110: =MIN(51,INT((J110 - DATE(YEAR(J110),1,1))/7))*7+IF(YEAR(J110)>YEAR(J$101),364,0) -> 315 | Z110: =MIN(51,INT((K110 - DATE(YEAR(K110),1,1))/7))*7+IF(YEAR(K110)>YEAR(K$101),364,0) -> 315 | AA110: =MIN(51,INT((L110 - DATE(YEAR(L110),1,1))/7))*7+IF(YEAR(L110)>YEAR(L$101),364,0) -> 315 | AB110: =MIN(51,INT((M110 - DATE(YEAR(M110),1,1))/7))*7+IF(YEAR(M110)>YEAR(M$101),364,0) -> 315 | ... AD110: =MIN(51,INT((O110 - DATE(YEAR(O110),1,1))/7))*7+IF(YEAR(O110)>YEAR(O$101),364,0) -> 315
E111: P10 | F111: =F110+G67 -> 43798 | G111: =G110+H67 -> 43798 | H111: =H110+I67 -> 43798 | I111: =I110+J67 -> 43798 | J111: =J110+K67 -> 43798 | K111: =K110+L67 -> 43798 | L111: =L110+M67 -> 43798 | M111: =M110+N67 -> 43798 | ... O111: =O110+P67 -> 43798 | P111: start of late harvest | T111: P10 | U111: =MIN(51,INT((F111 - DATE(YEAR(F111),1,1))/7))*7+IF(YEAR(F111)>YEAR(F$101),364,0) -> 329 | V111: =MIN(51,INT((G111 - DATE(YEAR(G111),1,1))/7))*7+IF(YEAR(G111)>YEAR(G$101),364,0) -> 329 | W111: =MIN(51,INT((H111 - DATE(YEAR(H111),1,1))/7))*7+IF(YEAR(H111)>YEAR(H$101),364,0) -> 329 | X111: =MIN(51,INT((I111 - DATE(YEAR(I111),1,1))/7))*7+IF(YEAR(I111)>YEAR(I$101),364,0) -> 329 | Y111: =MIN(51,INT((J111 - DATE(YEAR(J111),1,1))/7))*7+IF(YEAR(J111)>YEAR(J$101),364,0) -> 329 | Z111: =MIN(51,INT((K111 - DATE(YEAR(K111),1,1))/7))*7+IF(YEAR(K111)>YEAR(K$101),364,0) -> 329 | AA111: =MIN(51,INT((L111 - DATE(YEAR(L111),1,1))/7))*7+IF(YEAR(L111)>YEAR(L$101),364,0) -> 329 | AB111: =MIN(51,INT((M111 - DATE(YEAR(M111),1,1))/7))*7+IF(YEAR(M111)>YEAR(M$101),364,0) -> 329 | ... AD111: =MIN(51,INT((O111 - DATE(YEAR(O111),1,1))/7))*7+IF(YEAR(O111)>YEAR(O$101),364,0) -> 329
E112: P11 | F112: =F111+G68 -> 43833 | G112: =G111+H68 -> 43833 | H112: =H111+I68 -> 43833 | I112: =I111+J68 -> 43833 | J112: =J111+K68 -> 43833 | K112: =K111+L68 -> 43833 | L112: =L111+M68 -> 43833 | M112: =M111+N68 -> 43833 | ... O112: =O111+P68 -> 43833 | P112: end of harvest/year | T112: P11 | U112: =MIN(51,INT((F112 - DATE(YEAR(F112),1,1))/7))*7+IF(YEAR(F112)>YEAR(F$101),364,0) -> 364 | V112: =MIN(51,INT((G112 - DATE(YEAR(G112),1,1))/7))*7+IF(YEAR(G112)>YEAR(G$101),364,0) -> 364 | W112: =MIN(51,INT((H112 - DATE(YEAR(H112),1,1))/7))*7+IF(YEAR(H112)>YEAR(H$101),364,0) -> 364 | X112: =MIN(51,INT((I112 - DATE(YEAR(I112),1,1))/7))*7+IF(YEAR(I112)>YEAR(I$101),364,0) -> 364 | Y112: =MIN(51,INT((J112 - DATE(YEAR(J112),1,1))/7))*7+IF(YEAR(J112)>YEAR(J$101),364,0) -> 364 | Z112: =MIN(51,INT((K112 - DATE(YEAR(K112),1,1))/7))*7+IF(YEAR(K112)>YEAR(K$101),364,0) -> 364 | AA112: =MIN(51,INT((L112 - DATE(YEAR(L112),1,1))/7))*7+IF(YEAR(L112)>YEAR(L$101),364,0) -> 364 | AB112: =MIN(51,INT((M112 - DATE(YEAR(M112),1,1))/7))*7+IF(YEAR(M112)>YEAR(M$101),364,0) -> 364 | ... AD112: =MIN(51,INT((O112 - DATE(YEAR(O112),1,1))/7))*7+IF(YEAR(O112)>YEAR(O$101),364,0) -> 364
E113: P12 | F113: 43862 | G113: 43862 | H113: 43862 | I113: 43862 | J113: 43862 | K113: 43862 | L113: 43862 | M113: 43862 | N113: 43862 | O113: 43862 | T113: P12 | U113: =MIN(51,INT((F113 - DATE(YEAR(F113),1,1))/7))*7+IF(YEAR(F113)>YEAR(F$101),364,0) -> 392 | V113: =MIN(51,INT((G113 - DATE(YEAR(G113),1,1))/7))*7+IF(YEAR(G113)>YEAR(G$101),364,0) -> 392 | W113: =MIN(51,INT((H113 - DATE(YEAR(H113),1,1))/7))*7+IF(YEAR(H113)>YEAR(H$101),364,0) -> 392 | X113: =MIN(51,INT((I113 - DATE(YEAR(I113),1,1))/7))*7+IF(YEAR(I113)>YEAR(I$101),364,0) -> 392 | Y113: =MIN(51,INT((J113 - DATE(YEAR(J113),1,1))/7))*7+IF(YEAR(J113)>YEAR(J$101),364,0) -> 392 | Z113: =MIN(51,INT((K113 - DATE(YEAR(K113),1,1))/7))*7+IF(YEAR(K113)>YEAR(K$101),364,0) -> 392 | AA113: =MIN(51,INT((L113 - DATE(YEAR(L113),1,1))/7))*7+IF(YEAR(L113)>YEAR(L$101),364,0) -> 392 | AB113: =MIN(51,INT((M113 - DATE(YEAR(M113),1,1))/7))*7+IF(YEAR(M113)>YEAR(M$101),364,0) -> 392 | ... AD113: =MIN(51,INT((O113 - DATE(YEAR(O113),1,1))/7))*7+IF(YEAR(O113)>YEAR(O$101),364,0) -> 392
E114: P13 | F114: 43891 | G114: 43891 | H114: 43891 | I114: 43891 | J114: 43891 | K114: 43891 | L114: 43891 | M114: 43891 | N114: 43891 | O114: 43891 | T114: P13 | U114: =MIN(51,INT((F114 - DATE(YEAR(F114),1,1))/7))*7+IF(YEAR(F114)>YEAR(F$101),364,0) -> 420 | V114: =MIN(51,INT((G114 - DATE(YEAR(G114),1,1))/7))*7+IF(YEAR(G114)>YEAR(G$101),364,0) -> 420 | W114: =MIN(51,INT((H114 - DATE(YEAR(H114),1,1))/7))*7+IF(YEAR(H114)>YEAR(H$101),364,0) -> 420 | X114: =MIN(51,INT((I114 - DATE(YEAR(I114),1,1))/7))*7+IF(YEAR(I114)>YEAR(I$101),364,0) -> 420 | Y114: =MIN(51,INT((J114 - DATE(YEAR(J114),1,1))/7))*7+IF(YEAR(J114)>YEAR(J$101),364,0) -> 420 | Z114: =MIN(51,INT((K114 - DATE(YEAR(K114),1,1))/7))*7+IF(YEAR(K114)>YEAR(K$101),364,0) -> 420 | AA114: =MIN(51,INT((L114 - DATE(YEAR(L114),1,1))/7))*7+IF(YEAR(L114)>YEAR(L$101),364,0) -> 420 | AB114: =MIN(51,INT((M114 - DATE(YEAR(M114),1,1))/7))*7+IF(YEAR(M114)>YEAR(M$101),364,0) -> 420 | ... AD114: =MIN(51,INT((O114 - DATE(YEAR(O114),1,1))/7))*7+IF(YEAR(O114)>YEAR(O$101),364,0) -> 420
E115: P14 | F115: =F101+365 -> 43925 | G115: =G101+365 -> 43925 | H115: =H101+365 -> 43925 | I115: =I101+365 -> 43925 | J115: =J101+365 -> 43925 | K115: =K101+365 -> 43925 | L115: =L101+365 -> 43925 | M115: =M101+365 -> 43925 | ... O115: =O101+365 -> 43925 | P115: end date last period | T115: P14 | U115: =MIN(51,INT((F115 - DATE(YEAR(F115),1,1))/7))*7+IF(YEAR(F115)>YEAR(F$101),364,0) -> 455 | V115: =MIN(51,INT((G115 - DATE(YEAR(G115),1,1))/7))*7+IF(YEAR(G115)>YEAR(G$101),364,0) -> 455 | W115: =MIN(51,INT((H115 - DATE(YEAR(H115),1,1))/7))*7+IF(YEAR(H115)>YEAR(H$101),364,0) -> 455 | X115: =MIN(51,INT((I115 - DATE(YEAR(I115),1,1))/7))*7+IF(YEAR(I115)>YEAR(I$101),364,0) -> 455 | Y115: =MIN(51,INT((J115 - DATE(YEAR(J115),1,1))/7))*7+IF(YEAR(J115)>YEAR(J$101),364,0) -> 455 | Z115: =MIN(51,INT((K115 - DATE(YEAR(K115),1,1))/7))*7+IF(YEAR(K115)>YEAR(K$101),364,0) -> 455 | AA115: =MIN(51,INT((L115 - DATE(YEAR(L115),1,1))/7))*7+IF(YEAR(L115)>YEAR(L$101),364,0) -> 455 | AB115: =MIN(51,INT((M115 - DATE(YEAR(M115),1,1))/7))*7+IF(YEAR(M115)>YEAR(M$101),364,0) -> 455 | ... AD115: =MIN(51,INT((O115 - DATE(YEAR(O115),1,1))/7))*7+IF(YEAR(O115)>YEAR(O$101),364,0) -> 455
E119: =E77 -> Stocashtic Labour Periods | AL119: »

Sheet Saltbush
C4: « | D4: 661.25
D5: 661.25 | E5: Däta | G5: AREA OF SALTBUSH
G7: 39336.602
C8: 0
G15: Proportion of understorey | J15: 0.9
G16: Saltbush stems/ha | J16: 660
G17: Landuse | J17: sp
G19: =G5 -> AREA OF SALTBUSH | X19: »
C23: « | D23: 417.58461
D24: 417.58461 | E24: Däta | G24: COST OF ESTABLISHING SALTBUSH
G26: 44719.602
C27: 0
J31: Saltbush | K31: Understory
G34: Cost of establishment | I34: /ha | J34: 453.5 | K34: 80
G35: Probability of success | J35: 0.8 | K35: 0.8
G36: Productive Life of stand | I36: yrs | J36: 20 | K36: 10
G37: Expected estab date | J37: 43466 | K37: =MIN(364,INT((J37 - DATE(YEAR(J37),1,1)))) -> 0
I39: PMT | J39: =PMT(5%,i_saltbush_life,-i_saltbush_estab_cost/i_saltbush_success) -> 45.487517 | K39: =PMT(5%,i_understory_life,-i_understory_estab_cost/i_understory_success) -> 12.950457
G41: =G24 -> COST OF ESTABLISHING SALTBUSH | X41: »
C45: « | D45: 4408.925
D46: 4408.925 | E46: Däta | G46: SALTBUSH PRODUCTIVITY & FEED VALUE & SELECTIVITY
G48: 38530.673 | J48: *Jun22: z axis still needs to be calibrated
C49: 0
J50: Growth
K51: Loss in prodn of saltbush
I52: Typical FOO | J52: Typical growth rate | K52: when ungrazed | M52: DM total ash | P52: Diet selection | R52: Expected propn | T52: Crude
I53: g/stem | J53: g/stem/day | K53: %/day | M53: % | N53: SB OMD% | P53: Ratio SB vol / Total vol | R53: SLP in diet | T53: Protein
G56: Typ | H56: P0 | I56: 50 | J56: 4.5 | K56: 0.01 | M56: 0.237 | N56: 0.64 | P56: 0.42 | R56: 1 | T56: =MAX(12%,MIN(20%,20%-(P56-30%)*0.8)) -> 0.12
H57: P1 | I57: 100 | J57: 2.2 | K57: 0.01 | M57: 0.237 | P57: 0.42 | R57: 1 | T57: =MAX(12%,MIN(20%,20%-(P57-30%)*0.8)) -> 0.12
H58: P2 | I58: 100 | J58: 2.2 | K58: 0.01 | M58: 0.237 | P58: 0.32 | R58: 1 | T58: =MAX(12%,MIN(20%,20%-(P58-30%)*0.8)) -> 0.184
H59: P3 | I59: 150 | J59: 1.8 | K59: 0.01 | M59: 0.237 | P59: 0.14 | R59: 1 | T59: =MAX(12%,MIN(20%,20%-(P59-30%)*0.8)) -> 0.2
H60: P4 | I60: 300 | J60: 0.75 | K60: 0.01 | M60: 0.237 | P60: 0.12 | R60: 1 | T60: =MAX(12%,MIN(20%,20%-(P60-30%)*0.8)) -> 0.2
H61: P5 | I61: 300 | J61: 0.75 | K61: 0.01 | M61: 0.237 | P61: 0.23 | R61: 1 | T61: =MAX(12%,MIN(20%,20%-(P61-30%)*0.8)) -> 0.2
H62: P6 | I62: 325 | J62: 1 | K62: 0.01 | M62: 0.237 | P62: 0.32 | R62: 1 | T62: =MAX(12%,MIN(20%,20%-(P62-30%)*0.8)) -> 0.184
H63: P7 | I63: 350 | J63: 1.5 | K63: 0.01 | M63: 0.237 | P63: 0.42 | R63: 1 | T63: =MAX(12%,MIN(20%,20%-(P63-30%)*0.8)) -> 0.12
H64: P8 | I64: 50 | J64: 4.5 | K64: 0.01 | M64: 0.237 | P64: 0.51 | R64: 1 | T64: =MAX(12%,MIN(20%,20%-(P64-30%)*0.8)) -> 0.12
H65: P9 | I65: 50 | J65: 4.5 | K65: 0.01 | M65: 0.237 | P65: 0.6 | R65: 1 | T65: =MAX(12%,MIN(20%,20%-(P65-30%)*0.8)) -> 0.12
G66: Z0 | H66: P0 | I66: 50 | J66: 4.5 | K66: 0.01 | M66: =M65 -> 0.237 | P66: 0.42 | R66: 1 | T66: =MAX(12%,MIN(20%,20%-(P66-30%)*0.8)) -> 0.12
H67: P1 | I67: 100 | J67: 2.2 | K67: 0.01 | M67: =M66 -> 0.237 | P67: 0.42 | R67: 1 | T67: =MAX(12%,MIN(20%,20%-(P67-30%)*0.8)) -> 0.12
H68: P2 | I68: 100 | J68: 2.2 | K68: 0.01 | M68: =M67 -> 0.237 | P68: 0.32 | R68: 1 | T68: =MAX(12%,MIN(20%,20%-(P68-30%)*0.8)) -> 0.184
H69: P3 | I69: 150 | J69: 1.8 | K69: 0.01 | M69: =M68 -> 0.237 | P69: 0.14 | R69: 1 | T69: =MAX(12%,MIN(20%,20%-(P69-30%)*0.8)) -> 0.2
H70: P4 | I70: 300 | J70: 0.75 | K70: 0.01 | M70: =M69 -> 0.237 | P70: 0.12 | R70: 1 | T70: =MAX(12%,MIN(20%,20%-(P70-30%)*0.8)) -> 0.2
H71: P5 | I71: 300 | J71: 0.75 | K71: 0.01 | M71: =M70 -> 0.237 | P71: 0.23 | R71: 1 | T71: =MAX(12%,MIN(20%,20%-(P71-30%)*0.8)) -> 0.2
H72: P6 | I72: 325 | J72: 1 | K72: 0.01 | M72: =M71 -> 0.237 | P72: 0.32 | R72: 1 | T72: =MAX(12%,MIN(20%,20%-(P72-30%)*0.8)) -> 0.184
H73: P7 | I73: 350 | J73: 1.5 | K73: 0.01 | M73: =M72 -> 0.237 | P73: 0.42 | R73: 1 | T73: =MAX(12%,MIN(20%,20%-(P73-30%)*0.8)) -> 0.12
H74: P8 | I74: 50 | J74: 4.5 | K74: 0.01 | M74: =M73 -> 0.237 | P74: 0.51 | R74: 1 | T74: =MAX(12%,MIN(20%,20%-(P74-30%)*0.8)) -> 0.12
H75: P9 | I75: 50 | J75: 4.5 | K75: 0.01 | M75: =M74 -> 0.237 | P75: 0.6 | R75: 1 | T75: =MAX(12%,MIN(20%,20%-(P75-30%)*0.8)) -> 0.12
G76: Z1 | H76: P0 | I76: 50 | J76: 4.5 | K76: 0.01 | M76: =M75 -> 0.237 | P76: 0.42 | R76: 1 | T76: =MAX(12%,MIN(20%,20%-(P76-30%)*0.8)) -> 0.12
H77: P1 | I77: 100 | J77: 2.2 | K77: 0.01 | M77: =M76 -> 0.237 | P77: 0.42 | R77: 1 | T77: =MAX(12%,MIN(20%,20%-(P77-30%)*0.8)) -> 0.12
H78: P2 | I78: 100 | J78: 2.2 | K78: 0.01 | M78: =M77 -> 0.237 | P78: 0.32 | R78: 1 | T78: =MAX(12%,MIN(20%,20%-(P78-30%)*0.8)) -> 0.184
H79: P3 | I79: 150 | J79: 1.8 | K79: 0.01 | M79: =M78 -> 0.237 | P79: 0.14 | R79: 1 | T79: =MAX(12%,MIN(20%,20%-(P79-30%)*0.8)) -> 0.2
H80: P4 | I80: 300 | J80: 0.75 | K80: 0.01 | M80: =M79 -> 0.237 | P80: 0.12 | R80: 1 | T80: =MAX(12%,MIN(20%,20%-(P80-30%)*0.8)) -> 0.2
H81: P5 | I81: 300 | J81: 0.75 | K81: 0.01 | M81: =M80 -> 0.237 | P81: 0.23 | R81: 1 | T81: =MAX(12%,MIN(20%,20%-(P81-30%)*0.8)) -> 0.2
H82: P6 | I82: 325 | J82: 1 | K82: 0.01 | M82: =M81 -> 0.237 | P82: 0.32 | R82: 1 | T82: =MAX(12%,MIN(20%,20%-(P82-30%)*0.8)) -> 0.184
H83: P7 | I83: 350 | J83: 1.5 | K83: 0.01 | M83: =M82 -> 0.237 | P83: 0.42 | R83: 1 | T83: =MAX(12%,MIN(20%,20%-(P83-30%)*0.8)) -> 0.12
H84: P8 | I84: 50 | J84: 4.5 | K84: 0.01 | M84: =M83 -> 0.237 | P84: 0.51 | R84: 1 | T84: =MAX(12%,MIN(20%,20%-(P84-30%)*0.8)) -> 0.12
H85: P9 | I85: 50 | J85: 4.5 | K85: 0.01 | M85: =M84 -> 0.237 | P85: 0.6 | R85: 1 | T85: =MAX(12%,MIN(20%,20%-(P85-30%)*0.8)) -> 0.12
G86: Z2 | H86: P0 | I86: 50 | J86: 4.5 | K86: 0.01 | M86: =M85 -> 0.237 | P86: 0.42 | R86: 1 | T86: =MAX(12%,MIN(20%,20%-(P86-30%)*0.8)) -> 0.12
H87: P1 | I87: 100 | J87: 2.2 | K87: 0.01 | M87: =M86 -> 0.237 | P87: 0.42 | R87: 1 | T87: =MAX(12%,MIN(20%,20%-(P87-30%)*0.8)) -> 0.12
H88: P2 | I88: 100 | J88: 2.2 | K88: 0.01 | M88: =M87 -> 0.237 | P88: 0.32 | R88: 1 | T88: =MAX(12%,MIN(20%,20%-(P88-30%)*0.8)) -> 0.184
H89: P3 | I89: 150 | J89: 1.8 | K89: 0.01 | M89: =M88 -> 0.237 | P89: 0.14 | R89: 1 | T89: =MAX(12%,MIN(20%,20%-(P89-30%)*0.8)) -> 0.2
H90: P4 | I90: 300 | J90: 0.75 | K90: 0.01 | M90: =M89 -> 0.237 | P90: 0.12 | R90: 1 | T90: =MAX(12%,MIN(20%,20%-(P90-30%)*0.8)) -> 0.2
H91: P5 | I91: 300 | J91: 0.75 | K91: 0.01 | M91: =M90 -> 0.237 | P91: 0.23 | R91: 1 | T91: =MAX(12%,MIN(20%,20%-(P91-30%)*0.8)) -> 0.2
H92: P6 | I92: 325 | J92: 1 | K92: 0.01 | M92: =M91 -> 0.237 | P92: 0.32 | R92: 1 | T92: =MAX(12%,MIN(20%,20%-(P92-30%)*0.8)) -> 0.184
H93: P7 | I93: 350 | J93: 1.5 | K93: 0.01 | M93: =M92 -> 0.237 | P93: 0.42 | R93: 1 | T93: =MAX(12%,MIN(20%,20%-(P93-30%)*0.8)) -> 0.12
H94: P8 | I94: 50 | J94: 4.5 | K94: 0.01 | M94: =M93 -> 0.237 | P94: 0.51 | R94: 1 | T94: =MAX(12%,MIN(20%,20%-(P94-30%)*0.8)) -> 0.12
H95: P9 | I95: 50 | J95: 4.5 | K95: 0.01 | M95: =M94 -> 0.237 | P95: 0.6 | R95: 1 | T95: =MAX(12%,MIN(20%,20%-(P95-30%)*0.8)) -> 0.12
G96: Z3 | H96: P0 | I96: 50 | J96: 4.5 | K96: 0.01 | M96: =M95 -> 0.237 | P96: 0.42 | R96: 1 | T96: =MAX(12%,MIN(20%,20%-(P96-30%)*0.8)) -> 0.12
H97: P1 | I97: 100 | J97: 2.2 | K97: 0.01 | M97: =M96 -> 0.237 | P97: 0.42 | R97: 1 | T97: =MAX(12%,MIN(20%,20%-(P97-30%)*0.8)) -> 0.12
H98: P2 | I98: 100 | J98: 2.2 | K98: 0.01 | M98: =M97 -> 0.237 | P98: 0.32 | R98: 1 | T98: =MAX(12%,MIN(20%,20%-(P98-30%)*0.8)) -> 0.184
H99: P3 | I99: 150 | J99: 1.8 | K99: 0.01 | M99: =M98 -> 0.237 | P99: 0.14 | R99: 1 | T99: =MAX(12%,MIN(20%,20%-(P99-30%)*0.8)) -> 0.2
H100: P4 | I100: 300 | J100: 0.75 | K100: 0.01 | M100: =M99 -> 0.237 | P100: 0.12 | R100: 1 | T100: =MAX(12%,MIN(20%,20%-(P100-30%)*0.8)) -> 0.2
H101: P5 | I101: 300 | J101: 0.75 | K101: 0.01 | M101: =M100 -> 0.237 | P101: 0.23 | R101: 1 | T101: =MAX(12%,MIN(20%,20%-(P101-30%)*0.8)) -> 0.2
H102: P6 | I102: 325 | J102: 1 | K102: 0.01 | M102: =M101 -> 0.237 | P102: 0.32 | R102: 1 | T102: =MAX(12%,MIN(20%,20%-(P102-30%)*0.8)) -> 0.184
H103: P7 | I103: 350 | J103: 1.5 | K103: 0.01 | M103: =M102 -> 0.237 | P103: 0.42 | R103: 1 | T103: =MAX(12%,MIN(20%,20%-(P103-30%)*0.8)) -> 0.12
H104: P8 | I104: 50 | J104: 4.5 | K104: 0.01 | M104: =M103 -> 0.237 | P104: 0.51 | R104: 1 | T104: =MAX(12%,MIN(20%,20%-(P104-30%)*0.8)) -> 0.12
H105: P9 | I105: 50 | J105: 4.5 | K105: 0.01 | M105: =M104 -> 0.237 | P105: 0.6 | R105: 1 | T105: =MAX(12%,MIN(20%,20%-(P105-30%)*0.8)) -> 0.12
G106: Z4 | H106: P0 | I106: 50 | J106: 4.5 | K106: 0.01 | M106: =M105 -> 0.237 | P106: 0.42 | R106: 1 | T106: =MAX(12%,MIN(20%,20%-(P106-30%)*0.8)) -> 0.12
H107: P1 | I107: 100 | J107: 2.2 | K107: 0.01 | M107: =M106 -> 0.237 | P107: 0.42 | R107: 1 | T107: =MAX(12%,MIN(20%,20%-(P107-30%)*0.8)) -> 0.12
H108: P2 | I108: 100 | J108: 2.2 | K108: 0.01 | M108: =M107 -> 0.237 | P108: 0.32 | R108: 1 | T108: =MAX(12%,MIN(20%,20%-(P108-30%)*0.8)) -> 0.184
H109: P3 | I109: 150 | J109: 1.8 | K109: 0.01 | M109: =M108 -> 0.237 | P109: 0.14 | R109: 1 | T109: =MAX(12%,MIN(20%,20%-(P109-30%)*0.8)) -> 0.2
H110: P4 | I110: 300 | J110: 0.75 | K110: 0.01 | M110: =M109 -> 0.237 | P110: 0.12 | R110: 1 | T110: =MAX(12%,MIN(20%,20%-(P110-30%)*0.8)) -> 0.2
H111: P5 | I111: 300 | J111: 0.75 | K111: 0.01 | M111: =M110 -> 0.237 | P111: 0.23 | R111: 1 | T111: =MAX(12%,MIN(20%,20%-(P111-30%)*0.8)) -> 0.2
H112: P6 | I112: 325 | J112: 1 | K112: 0.01 | M112: =M111 -> 0.237 | P112: 0.32 | R112: 1 | T112: =MAX(12%,MIN(20%,20%-(P112-30%)*0.8)) -> 0.184
H113: P7 | I113: 350 | J113: 1.5 | K113: 0.01 | M113: =M112 -> 0.237 | P113: 0.42 | R113: 1 | T113: =MAX(12%,MIN(20%,20%-(P113-30%)*0.8)) -> 0.12
H114: P8 | I114: 50 | J114: 4.5 | K114: 0.01 | M114: =M113 -> 0.237 | P114: 0.51 | R114: 1 | T114: =MAX(12%,MIN(20%,20%-(P114-30%)*0.8)) -> 0.12
H115: P9 | I115: 50 | J115: 4.5 | K115: 0.01 | M115: =M114 -> 0.237 | P115: 0.6 | R115: 1 | T115: =MAX(12%,MIN(20%,20%-(P115-30%)*0.8)) -> 0.12
G116: Z5 | H116: P0 | I116: 50 | J116: 4.5 | K116: 0.01 | M116: =M115 -> 0.237 | P116: 0.42 | R116: 1 | T116: =MAX(12%,MIN(20%,20%-(P116-30%)*0.8)) -> 0.12
H117: P1 | I117: 100 | J117: 2.2 | K117: 0.01 | M117: =M116 -> 0.237 | P117: 0.42 | R117: 1 | T117: =MAX(12%,MIN(20%,20%-(P117-30%)*0.8)) -> 0.12
H118: P2 | I118: 100 | J118: 2.2 | K118: 0.01 | M118: =M117 -> 0.237 | P118: 0.32 | R118: 1 | T118: =MAX(12%,MIN(20%,20%-(P118-30%)*0.8)) -> 0.184
H119: P3 | I119: 150 | J119: 1.8 | K119: 0.01 | M119: =M118 -> 0.237 | P119: 0.14 | R119: 1 | T119: =MAX(12%,MIN(20%,20%-(P119-30%)*0.8)) -> 0.2
H120: P4 | I120: 300 | J120: 0.75 | K120: 0.01 | M120: =M119 -> 0.237 | P120: 0.12 | R120: 1 | T120: =MAX(12%,MIN(20%,20%-(P120-30%)*0.8)) -> 0.2
H121: P5 | I121: 300 | J121: 0.75 | K121: 0.01 | M121: =M120 -> 0.237 | P121: 0.23 | R121: 1 | T121: =MAX(12%,MIN(20%,20%-(P121-30%)*0.8)) -> 0.2
H122: P6 | I122: 325 | J122: 1 | K122: 0.01 | M122: =M121 -> 0.237 | P122: 0.32 | R122: 1 | T122: =MAX(12%,MIN(20%,20%-(P122-30%)*0.8)) -> 0.184
H123: P7 | I123: 350 | J123: 1.5 | K123: 0.01 | M123: =M122 -> 0.237 | P123: 0.42 | R123: 1 | T123: =MAX(12%,MIN(20%,20%-(P123-30%)*0.8)) -> 0.12
H124: P8 | I124: 50 | J124: 4.5 | K124: 0.01 | M124: =M123 -> 0.237 | P124: 0.51 | R124: 1 | T124: =MAX(12%,MIN(20%,20%-(P124-30%)*0.8)) -> 0.12
H125: P9 | I125: 50 | J125: 4.5 | K125: 0.01 | M125: =M124 -> 0.237 | P125: 0.6 | R125: 1 | T125: =MAX(12%,MIN(20%,20%-(P125-30%)*0.8)) -> 0.12
G126: Z6 | H126: P0 | I126: 50 | J126: 4.5 | K126: 0.01 | M126: =M125 -> 0.237 | P126: 0.42 | R126: 1 | T126: =MAX(12%,MIN(20%,20%-(P126-30%)*0.8)) -> 0.12
H127: P1 | I127: 100 | J127: 2.2 | K127: 0.01 | M127: =M126 -> 0.237 | P127: 0.42 | R127: 1 | T127: =MAX(12%,MIN(20%,20%-(P127-30%)*0.8)) -> 0.12
H128: P2 | I128: 100 | J128: 2.2 | K128: 0.01 | M128: =M127 -> 0.237 | P128: 0.32 | R128: 1 | T128: =MAX(12%,MIN(20%,20%-(P128-30%)*0.8)) -> 0.184
...

Sheet Labour
E3: 10Aug21: Added a time period for txed jobs and the Seeding & harvest Prepartion and packing away 4 Aug21: Spread the fixed jobs across more dates so that it didn't cause problems in short labour periods. Probably better to be coded as a length of the task so that it is more universal.
E9: Labour Bounds
H10: note
H14: Manager | J14: Permanent | L14: Casual
G16: Min | H16: 1 | J16: 0 | L16: 0
G17: Max | H17: 1 | J17: 1 | L17: 999
G19: Min Seeding/Harv | L19: 0
G20: Max Seeding/Harv | L20: 999
E24: =E9 -> Labour Bounds | Z24: »
E29: Leave
H34: Manager | J34: Permanent | L34: Casual
G36: Sick | J36: 10
G38: Leave Length | H38: 28 | J38: 28
E41: =E29 -> Leave | Z41: »
E46: Daily hours and efficiency
H51: Manager | I51: Permanent | J51: Casual
G52: weekdays | H52: 9 | I52: 8 | J52: 8
G53: weekends | H53: 4.5 | I53: 0 | J53: 0
G54: seeding | H54: 10 | I54: 9 | J54: 8
G55: harvest | H55: 9 | I55: 9 | J55: 8
G57: Supervision required
I58: Permanent | J58: Casual
H59: normal | I59: 0.07 | J59: 0.15
H60: seedingharv | I60: 0.02 | J60: 0.1
E62: =E46 -> Daily hours and efficiency | Z62: »
E67: Fixed Labour
I68: Note
F71: Tax | J71: Planning | N71: BAS | R71: Super & WC | V71: Learn
F72: date | G72: days | H72: hours | J72: date | K72: days | L72: hours | N72: date | O72: days | P72: hours | R72: date | S72: days | T72: hours | V72: hours
E73: 43525 | F73: =MIN(364,INT((E73 - DATE(YEAR(E73),1,1)))) -> 59 | G73: 15 | H73: 6 | I73: 43466 | J73: =MIN(364,INT((I73 - DATE(YEAR(I73),1,1)))) -> 0 | K73: 10 | L73: 4 | M73: 43497 | N73: =MIN(364,INT((M73 - DATE(YEAR(M73),1,1)))) -> 31 | O73: 21 | P73: 20 | Q73: 43525 | R73: =MIN(364,INT((Q73 - DATE(YEAR(Q73),1,1)))) -> 59 | S73: 21 | T73: 10 | V73: 66
E74: 43556 | F74: =MIN(364,INT((E74 - DATE(YEAR(E74),1,1)))) -> 90 | G74: 30 | H74: 10 | I74: 43497 | J74: =MIN(364,INT((I74 - DATE(YEAR(I74),1,1)))) -> 31 | K74: 10 | L74: 4 | M74: 43556 | N74: =MIN(364,INT((M74 - DATE(YEAR(M74),1,1)))) -> 90 | O74: 21 | P74: 20 | Q74: 43631 | R74: =MIN(364,INT((Q74 - DATE(YEAR(Q74),1,1)))) -> 165 | S74: 21 | T74: 10
E75: 43631 | F75: =MIN(364,INT((E75 - DATE(YEAR(E75),1,1)))) -> 165 | G75: 15 | H75: 5 | I75: 43525 | J75: =MIN(364,INT((I75 - DATE(YEAR(I75),1,1)))) -> 59 | K75: 10 | L75: 4 | M75: 43647 | N75: =MIN(364,INT((M75 - DATE(YEAR(M75),1,1)))) -> 181 | O75: 21 | P75: 20 | Q75: 43709 | R75: =MIN(364,INT((Q75 - DATE(YEAR(Q75),1,1)))) -> 243 | S75: 21 | T75: 10
I76: 43556 | J76: =MIN(364,INT((I76 - DATE(YEAR(I76),1,1)))) -> 90 | K76: 10 | L76: 4 | M76: 43739 | N76: =MIN(364,INT((M76 - DATE(YEAR(M76),1,1)))) -> 273 | O76: 21 | P76: 20 | Q76: 43814 | R76: =MIN(364,INT((Q76 - DATE(YEAR(Q76),1,1)))) -> 348 | S76: 21 | T76: 10
I77: 43586 | J77: =MIN(364,INT((I77 - DATE(YEAR(I77),1,1)))) -> 120 | K77: 10 | L77: 4
I78: 43631 | J78: =MIN(364,INT((I78 - DATE(YEAR(I78),1,1)))) -> 165 | K78: 10 | L78: 4
I79: 43647 | J79: =MIN(364,INT((I79 - DATE(YEAR(I79),1,1)))) -> 181 | K79: 10 | L79: 4
I80: 43678 | J80: =MIN(364,INT((I80 - DATE(YEAR(I80),1,1)))) -> 212 | K80: 10 | L80: 4
I81: 43709 | J81: =MIN(364,INT((I81 - DATE(YEAR(I81),1,1)))) -> 243 | K81: 10 | L81: 4
I82: 43739 | J82: =MIN(364,INT((I82 - DATE(YEAR(I82),1,1)))) -> 273 | K82: 10 | L82: 4
I83: 43770 | J83: =MIN(364,INT((I83 - DATE(YEAR(I83),1,1)))) -> 304 | K83: 10 | L83: 4
E90: =E67 -> Fixed Labour | Z90: »
E95: Labour Phases
F97: Helper | O97: Preparation & Pack away
G99: Harvest | J99: Harvest preparation | N99: Fertilizer preparation | R99: Spray preparation | V99: Seeding preparation
E100: seeding | G100: crop | H100: time | J100: date | K100: days | L100: hours | N100: date | O100: days | P100: hours | R100: date | S100: days | T100: hours | V100: date | W100: days | X100: hours
E101: 0.5 | G101: =General!G17 -> b | H101: 1.2 | I101: 43743 | J101: =MIN(364,INT((I101 - DATE(YEAR(I101),1,1)))) -> 277 | K101: 20 | L101: 20 | M101: 43560 | N101: =MIN(364,INT((M101 - DATE(YEAR(M101),1,1)))) -> 94 | O101: 14 | P101: 13 | Q101: 43560 | R101: =MIN(364,INT((Q101 - DATE(YEAR(Q101),1,1)))) -> 94 | S101: 14 | T101: 13 | U101: 43529 | V101: =MIN(364,INT((U101 - DATE(YEAR(U101),1,1)))) -> 63 | W101: 30 | X101: 40
G102: =General!G18 -> bd | H102: 1.2 | I102: 43774 | J102: =MIN(364,INT((I102 - DATE(YEAR(I102),1,1)))) -> 308 | K102: 20 | L102: 20 | M102: 43590 | N102: =MIN(364,INT((M102 - DATE(YEAR(M102),1,1)))) -> 124 | O102: 5 | P102: 3 | Q102: 43590 | R102: =MIN(364,INT((Q102 - DATE(YEAR(Q102),1,1)))) -> 124 | S102: 5 | T102: 3 | U102: 43560 | V102: =MIN(364,INT((U102 - DATE(YEAR(U102),1,1)))) -> 94 | W102: 30 | X102: 40
G103: =General!G19 -> f | H103: 1.2 | M103: 43682 | N103: =MIN(364,INT((M103 - DATE(YEAR(M103),1,1)))) -> 216 | O103: 5 | P103: 3 | Q103: 43713 | R103: =MIN(364,INT((Q103 - DATE(YEAR(Q103),1,1)))) -> 247 | S103: 5 | T103: 3 | U103: 43632 | V103: =MIN(364,INT((U103 - DATE(YEAR(U103),1,1)))) -> 166 | W103: 14 | X103: 5
G104: =General!G20 -> h | H104: 1.2
G105: =General!G21 -> i | H105: 1.2
G106: =General!G22 -> k | H106: 1.2
G107: =General!G23 -> l | H107: 1.2
G108: =General!G24 -> lf | H108: 1.2
G109: =General!G25 -> ms | H109: 1.2
G110: =General!G26 -> o | H110: 1.2
G111: =General!G27 -> od | H111: 1.2
G112: =General!G28 -> of | H112: 1.2
G113: =General!G29 -> r | H113: 1.2
G114: =General!G30 -> rd | H114: 1.2
G115: =General!G31 -> v | H115: 1.2
... G119: =General!G35 -> zd | H119: 1.2
E125: Weekly crop monitoring (fixed)
F126: 43466 | G126: 43497 | H126: 43525 | I126: 43556 | J126: 43586 | K126: 43617 | L126: 43647 | M126: 43678 | N126: 43709 | O126: 43739 | P126: 43770 | Q126: 43800
E127: date | F127: =MIN(364,INT((F126 - DATE(YEAR(F126),1,1)))) -> 0 | G127: =MIN(364,INT((G126 - DATE(YEAR(G126),1,1)))) -> 31 | H127: =MIN(364,INT((H126 - DATE(YEAR(H126),1,1)))) -> 59 | I127: =MIN(364,INT((I126 - DATE(YEAR(I126),1,1)))) -> 90 | J127: =MIN(364,INT((J126 - DATE(YEAR(J126),1,1)))) -> 120 | K127: =MIN(364,INT((K126 - DATE(YEAR(K126),1,1)))) -> 151 | L127: =MIN(364,INT((L126 - DATE(YEAR(L126),1,1)))) -> 181 | M127: =MIN(364,INT((M126 - DATE(YEAR(M126),1,1)))) -> 212 | ... Q127: =MIN(364,INT((Q126 - DATE(YEAR(Q126),1,1)))) -> 334
E128: hrs | F128: 0 | G128: 0 | H128: 0 | I128: 0 | J128: 0 | K128: 0.5 | L128: 0.5 | M128: 0.3 | N128: 0.3 | O128: 0 | P128: 0 | Q128: 0
E132: Weekly crop monitoring (variable)
F133: =F127 -> 0 | G133: =G127 -> 31 | H133: =H127 -> 59 | I133: =I127 -> 90 | J133: =J127 -> 120 | K133: =K127 -> 151 | L133: =L127 -> 181 | M133: =M127 -> 212 | ... Q133: =Q127 -> 334
E134: =General!G17 -> b | F134: 0 | G134: 0 | H134: 0 | I134: 0 | J134: 0 | K134: 0.1 | L134: 0.1 | M134: 0.1 | N134: 0.1 | O134: 0 | P134: 0 | Q134: 0
E135: =General!G18 -> bd | F135: 0 | G135: 0 | H135: 0 | I135: 0 | J135: 0 | K135: 0.1 | L135: 0.1 | M135: 0.1 | N135: 0.1 | O135: 0 | P135: 0 | Q135: 0
E136: =General!G19 -> f | F136: 0 | G136: 0 | H136: 0 | I136: 0 | J136: 0 | K136: 0.1 | L136: 0.1 | M136: 0.1 | N136: 0.1 | O136: 0 | P136: 0 | Q136: 0
E137: =General!G20 -> h | F137: 0 | G137: 0 | H137: 0 | I137: 0 | J137: 0 | K137: 0.1 | L137: 0.1 | M137: 0.1 | N137: 0.1 | O137: 0 | P137: 0 | Q137: 0
E138: =General!G21 -> i | F138: 0 | G138: 0 | H138: 0 | I138: 0 | J138: 0 | K138: 0.1 | L138: 0.1 | M138: 0.1 | N138: 0.1 | O138: 0 | P138: 0 | Q138: 0
E139: =General!G22 -> k | F139: 0 | G139: 0 | H139: 0 | I139: 0 | J139: 0 | K139: 0.1 | L139: 0.1 | M139: 0.1 | N139: 0.1 | O139: 0 | P139: 0 | Q139: 0
E140: =General!G23 -> l | F140: 0 | G140: 0 | H140: 0 | I140: 0 | J140: 0 | K140: 0.1 | L140: 0.1 | M140: 0.1 | N140: 0.1 | O140: 0 | P140: 0 | Q140: 0
E141: =General!G24 -> lf | F141: 0 | G141: 0 | H141: 0 | I141: 0 | J141: 0 | K141: 0.1 | L141: 0.1 | M141: 0.1 | N141: 0.1 | O141: 0 | P141: 0 | Q141: 0
E142: =General!G25 -> ms | F142: 0 | G142: 0 | H142: 0 | I142: 0 | J142: 0 | K142: 0.1 | L142: 0.1 | M142: 0.1 | N142: 0.1 | O142: 0 | P142: 0 | Q142: 0
E143: =General!G26 -> o | F143: 0 | G143: 0 | H143: 0 | I143: 0 | J143: 0 | K143: 0.1 | L143: 0.1 | M143: 0.1 | N143: 0.1 | O143: 0 | P143: 0 | Q143: 0
E144: =General!G27 -> od | F144: 0 | G144: 0 | H144: 0 | I144: 0 | J144: 0 | K144: 0.1 | L144: 0.1 | M144: 0.1 | N144: 0.1 | O144: 0 | P144: 0 | Q144: 0
E145: =General!G28 -> of | F145: 0 | G145: 0 | H145: 0 | I145: 0 | J145: 0 | K145: 0.1 | L145: 0.1 | M145: 0.1 | N145: 0.1 | O145: 0 | P145: 0 | Q145: 0
... E152: =General!G35 -> zd | F152: 0 | G152: 0 | H152: 0 | I152: 0 | J152: 0 | K152: 0.1 | L152: 0.1 | M152: 0.1 | N152: 0.1 | O152: 0 | P152: 0 | Q152: 0
E154: =E95 -> Labour Phases | Z154: »

Sheet Annual
C4: « | AD4: ïnsertcolumnstart
D5: 0 | E5: Däta | G5: Data Sharing for Annual Pasture sheet (P1a)
G6: Standard format for all data transferred between modules
G7: 37998.514 | H7: 37998.514
C8: 1
C13: FïlterStart | J13: frëeze
G16: Relative Intake Coefficients | K16: =J75 -> typ | L16: =K75 -> z0 | M16: =L75 -> z1 | N16: =M75 -> z2 | O16: =N75 -> z3 | P16: =O75 -> z4 | Q16: =P75 -> z5 | R16: =Q75 -> z6 | ... T16: =S75 -> z8
H17: Proportion of clover in the sward | K17: 0.2 | L17: 0.2 | M17: 0.2 | N17: 0.2 | O17: 0.2 | P17: 0.2 | Q17: 0.2 | R17: 0.2 | S17: 0.2 | T17: 0.2
H18: Height ratio scalar | K18: 2 | L18: 2 | M18: 2 | N18: 2 | O18: 2 | P18: 2 | Q18: 2 | R18: 2 | S18: 2 | T18: 2
H20: Length of establishment phase (days) | K20: 30 | L20: =K20 -> 30 | M20: =L20 -> 30 | N20: =M20 -> 30 | O20: =N20 -> 30 | P20: =O20 -> 30 | Q20: =P20 -> 30 | R20: =Q20 -> 30 | S20: =R20 -> 30 | T20: =S20 -> 30
H21: Break of season (doy) | K21: {=TRANSPOSE(General!i_break)} -> 133 | L21: 119 | M21: 119 | N21: 119 | O21: 119 | P21: 140 | Q21: 140 | R21: 140 | S21: 140 | T21: 140
H23: Note: The calculation in the tble below could be done in the pre-calcs and then the input above could be defined as a sensitivity variable.
H24: Pasture stage | J24: FP0 | K24: =MIN(1,(MAX(0, Periods!U22-(K$21+K$20))+MAX(0,K$21-Periods!U21))/(Periods!U22-Periods!U21)) -> 1 | L24: =MIN(1,(MAX(0, Periods!V22-(L$21+L$20))+MAX(0,L$21-Periods!V21))/(Periods!V22-Periods!V21)) -> 1 | M24: =MIN(1,(MAX(0, Periods!W22-(M$21+M$20))+MAX(0,M$21-Periods!W21))/(Periods!W22-Periods!W21)) -> 1 | N24: =MIN(1,(MAX(0, Periods!X22-(N$21+N$20))+MAX(0,N$21-Periods!X21))/(Periods!X22-Periods!X21)) -> 1 | O24: =MIN(1,(MAX(0, Periods!Y22-(O$21+O$20))+MAX(0,O$21-Periods!Y21))/(Periods!Y22-Periods!Y21)) -> 1 | P24: =MIN(1,(MAX(0, Periods!Z22-(P$21+P$20))+MAX(0,P$21-Periods!Z21))/(Periods!Z22-Periods!Z21)) -> 1 | Q24: =MIN(1,(MAX(0, Periods!AA22-(Q$21+Q$20))+MAX(0,Q$21-Periods!AA21))/(Periods!AA22-Periods!AA21)) -> 1 | R24: =MIN(1,(MAX(0, Periods!AB22-(R$21+R$20))+MAX(0,R$21-Periods!AB21))/(Periods!AB22-Periods!AB21)) -> 1 | ... T24: =MIN(1,(MAX(0, Periods!AD22-(T$21+T$20))+MAX(0,T$21-Periods!AD21))/(Periods!AD22-Periods!AD21)) -> 1
J25: FP1 | K25: =MIN(1,(MAX(0, Periods!U23-(K$21+K$20))+MAX(0,K$21-Periods!U22))/(Periods!U23-Periods!U22)) -> 0 | L25: =MIN(1,(MAX(0, Periods!V23-(L$21+L$20))+MAX(0,L$21-Periods!V22))/(Periods!V23-Periods!V22)) -> 0.28571429 | M25: =MIN(1,(MAX(0, Periods!W23-(M$21+M$20))+MAX(0,M$21-Periods!W22))/(Periods!W23-Periods!W22)) -> 0.28571429 | N25: =MIN(1,(MAX(0, Periods!X23-(N$21+N$20))+MAX(0,N$21-Periods!X22))/(Periods!X23-Periods!X22)) -> 0.28571429 | O25: =MIN(1,(MAX(0, Periods!Y23-(O$21+O$20))+MAX(0,O$21-Periods!Y22))/(Periods!Y23-Periods!Y22)) -> 0.28571429 | P25: =MIN(1,(MAX(0, Periods!Z23-(P$21+P$20))+MAX(0,P$21-Periods!Z22))/(Periods!Z23-Periods!Z22)) -> 0 | Q25: =MIN(1,(MAX(0, Periods!AA23-(Q$21+Q$20))+MAX(0,Q$21-Periods!AA22))/(Periods!AA23-Periods!AA22)) -> 0 | R25: =MIN(1,(MAX(0, Periods!AB23-(R$21+R$20))+MAX(0,R$21-Periods!AB22))/(Periods!AB23-Periods!AB22)) -> 0 | ... T25: =MIN(1,(MAX(0, Periods!AD23-(T$21+T$20))+MAX(0,T$21-Periods!AD22))/(Periods!AD23-Periods!AD22)) -> 0
J26: FP2 | K26: =MIN(1,(MAX(0, Periods!U24-(K$21+K$20))+MAX(0,K$21-Periods!U23))/(Periods!U24-Periods!U23)) -> 0.96428571 | L26: =MIN(1,(MAX(0, Periods!V24-(L$21+L$20))+MAX(0,L$21-Periods!V23))/(Periods!V24-Periods!V23)) -> 1 | M26: =MIN(1,(MAX(0, Periods!W24-(M$21+M$20))+MAX(0,M$21-Periods!W23))/(Periods!W24-Periods!W23)) -> 1 | N26: =MIN(1,(MAX(0, Periods!X24-(N$21+N$20))+MAX(0,N$21-Periods!X23))/(Periods!X24-Periods!X23)) -> 1 | O26: =MIN(1,(MAX(0, Periods!Y24-(O$21+O$20))+MAX(0,O$21-Periods!Y23))/(Periods!Y24-Periods!Y23)) -> 1 | P26: =MIN(1,(MAX(0, Periods!Z24-(P$21+P$20))+MAX(0,P$21-Periods!Z23))/(Periods!Z24-Periods!Z23)) -> 0.83928571 | Q26: =MIN(1,(MAX(0, Periods!AA24-(Q$21+Q$20))+MAX(0,Q$21-Periods!AA23))/(Periods!AA24-Periods!AA23)) -> 0.83928571 | R26: =MIN(1,(MAX(0, Periods!AB24-(R$21+R$20))+MAX(0,R$21-Periods!AB23))/(Periods!AB24-Periods!AB23)) -> 0.83928571 | ... T26: =MIN(1,(MAX(0, Periods!AD24-(T$21+T$20))+MAX(0,T$21-Periods!AD23))/(Periods!AD24-Periods!AD23)) -> 0.83928571
J27: FP3 | K27: =MIN(1,(MAX(0, Periods!U25-(K$21+K$20))+MAX(0,K$21-Periods!U24))/(Periods!U25-Periods!U24)) -> 1 | L27: =MIN(1,(MAX(0, Periods!V25-(L$21+L$20))+MAX(0,L$21-Periods!V24))/(Periods!V25-Periods!V24)) -> 1 | M27: =MIN(1,(MAX(0, Periods!W25-(M$21+M$20))+MAX(0,M$21-Periods!W24))/(Periods!W25-Periods!W24)) -> 1 | N27: =MIN(1,(MAX(0, Periods!X25-(N$21+N$20))+MAX(0,N$21-Periods!X24))/(Periods!X25-Periods!X24)) -> 1 | O27: =MIN(1,(MAX(0, Periods!Y25-(O$21+O$20))+MAX(0,O$21-Periods!Y24))/(Periods!Y25-Periods!Y24)) -> 1 | P27: =MIN(1,(MAX(0, Periods!Z25-(P$21+P$20))+MAX(0,P$21-Periods!Z24))/(Periods!Z25-Periods!Z24)) -> 1 | Q27: =MIN(1,(MAX(0, Periods!AA25-(Q$21+Q$20))+MAX(0,Q$21-Periods!AA24))/(Periods!AA25-Periods!AA24)) -> 1 | R27: =MIN(1,(MAX(0, Periods!AB25-(R$21+R$20))+MAX(0,R$21-Periods!AB24))/(Periods!AB25-Periods!AB24)) -> 1 | ... T27: =MIN(1,(MAX(0, Periods!AD25-(T$21+T$20))+MAX(0,T$21-Periods!AD24))/(Periods!AD25-Periods!AD24)) -> 1
J28: FP4 | K28: =MIN(1,(MAX(0, Periods!U26-(K$21+K$20))+MAX(0,K$21-Periods!U25))/(Periods!U26-Periods!U25)) -> 1 | L28: =MIN(1,(MAX(0, Periods!V26-(L$21+L$20))+MAX(0,L$21-Periods!V25))/(Periods!V26-Periods!V25)) -> 1 | M28: =MIN(1,(MAX(0, Periods!W26-(M$21+M$20))+MAX(0,M$21-Periods!W25))/(Periods!W26-Periods!W25)) -> 1 | N28: =MIN(1,(MAX(0, Periods!X26-(N$21+N$20))+MAX(0,N$21-Periods!X25))/(Periods!X26-Periods!X25)) -> 1 | O28: =MIN(1,(MAX(0, Periods!Y26-(O$21+O$20))+MAX(0,O$21-Periods!Y25))/(Periods!Y26-Periods!Y25)) -> 1 | P28: =MIN(1,(MAX(0, Periods!Z26-(P$21+P$20))+MAX(0,P$21-Periods!Z25))/(Periods!Z26-Periods!Z25)) -> 1 | Q28: =MIN(1,(MAX(0, Periods!AA26-(Q$21+Q$20))+MAX(0,Q$21-Periods!AA25))/(Periods!AA26-Periods!AA25)) -> 1 | R28: =MIN(1,(MAX(0, Periods!AB26-(R$21+R$20))+MAX(0,R$21-Periods!AB25))/(Periods!AB26-Periods!AB25)) -> 1 | ... T28: =MIN(1,(MAX(0, Periods!AD26-(T$21+T$20))+MAX(0,T$21-Periods!AD25))/(Periods!AD26-Periods!AD25)) -> 1
J29: FP5 | K29: =MIN(1,(MAX(0, Periods!U27-(K$21+K$20))+MAX(0,K$21-Periods!U26))/(Periods!U27-Periods!U26)) -> 1 | L29: =MIN(1,(MAX(0, Periods!V27-(L$21+L$20))+MAX(0,L$21-Periods!V26))/(Periods!V27-Periods!V26)) -> 1 | M29: =MIN(1,(MAX(0, Periods!W27-(M$21+M$20))+MAX(0,M$21-Periods!W26))/(Periods!W27-Periods!W26)) -> 1 | N29: =MIN(1,(MAX(0, Periods!X27-(N$21+N$20))+MAX(0,N$21-Periods!X26))/(Periods!X27-Periods!X26)) -> 1 | O29: =MIN(1,(MAX(0, Periods!Y27-(O$21+O$20))+MAX(0,O$21-Periods!Y26))/(Periods!Y27-Periods!Y26)) -> 1 | P29: =MIN(1,(MAX(0, Periods!Z27-(P$21+P$20))+MAX(0,P$21-Periods!Z26))/(Periods!Z27-Periods!Z26)) -> 1 | Q29: =MIN(1,(MAX(0, Periods!AA27-(Q$21+Q$20))+MAX(0,Q$21-Periods!AA26))/(Periods!AA27-Periods!AA26)) -> 1 | R29: =MIN(1,(MAX(0, Periods!AB27-(R$21+R$20))+MAX(0,R$21-Periods!AB26))/(Periods!AB27-Periods!AB26)) -> 1 | ... T29: =MIN(1,(MAX(0, Periods!AD27-(T$21+T$20))+MAX(0,T$21-Periods!AD26))/(Periods!AD27-Periods!AD26)) -> 1
J30: FP6 | K30: =MIN(1,(MAX(0, Periods!U28-(K$21+K$20))+MAX(0,K$21-Periods!U27))/(Periods!U28-Periods!U27)) -> 1 | L30: =MIN(1,(MAX(0, Periods!V28-(L$21+L$20))+MAX(0,L$21-Periods!V27))/(Periods!V28-Periods!V27)) -> 1 | M30: =MIN(1,(MAX(0, Periods!W28-(M$21+M$20))+MAX(0,M$21-Periods!W27))/(Periods!W28-Periods!W27)) -> 1 | N30: =MIN(1,(MAX(0, Periods!X28-(N$21+N$20))+MAX(0,N$21-Periods!X27))/(Periods!X28-Periods!X27)) -> 1 | O30: =MIN(1,(MAX(0, Periods!Y28-(O$21+O$20))+MAX(0,O$21-Periods!Y27))/(Periods!Y28-Periods!Y27)) -> 1 | P30: =MIN(1,(MAX(0, Periods!Z28-(P$21+P$20))+MAX(0,P$21-Periods!Z27))/(Periods!Z28-Periods!Z27)) -> 1 | Q30: =MIN(1,(MAX(0, Periods!AA28-(Q$21+Q$20))+MAX(0,Q$21-Periods!AA27))/(Periods!AA28-Periods!AA27)) -> 1 | R30: =MIN(1,(MAX(0, Periods!AB28-(R$21+R$20))+MAX(0,R$21-Periods!AB27))/(Periods!AB28-Periods!AB27)) -> 1 | ... T30: =MIN(1,(MAX(0, Periods!AD28-(T$21+T$20))+MAX(0,T$21-Periods!AD27))/(Periods!AD28-Periods!AD27)) -> 1
J31: FP7 | K31: =MIN(1,(MAX(0, Periods!U29-(K$21+K$20))+MAX(0,K$21-Periods!U28))/(Periods!U29-Periods!U28)) -> 1 | L31: =MIN(1,(MAX(0, Periods!V29-(L$21+L$20))+MAX(0,L$21-Periods!V28))/(Periods!V29-Periods!V28)) -> 1 | M31: =MIN(1,(MAX(0, Periods!W29-(M$21+M$20))+MAX(0,M$21-Periods!W28))/(Periods!W29-Periods!W28)) -> 1 | N31: =MIN(1,(MAX(0, Periods!X29-(N$21+N$20))+MAX(0,N$21-Periods!X28))/(Periods!X29-Periods!X28)) -> 1 | O31: =MIN(1,(MAX(0, Periods!Y29-(O$21+O$20))+MAX(0,O$21-Periods!Y28))/(Periods!Y29-Periods!Y28)) -> 1 | P31: =MIN(1,(MAX(0, Periods!Z29-(P$21+P$20))+MAX(0,P$21-Periods!Z28))/(Periods!Z29-Periods!Z28)) -> 1 | Q31: =MIN(1,(MAX(0, Periods!AA29-(Q$21+Q$20))+MAX(0,Q$21-Periods!AA28))/(Periods!AA29-Periods!AA28)) -> 1 | R31: =MIN(1,(MAX(0, Periods!AB29-(R$21+R$20))+MAX(0,R$21-Periods!AB28))/(Periods!AB29-Periods!AB28)) -> 1 | ... T31: =MIN(1,(MAX(0, Periods!AD29-(T$21+T$20))+MAX(0,T$21-Periods!AD28))/(Periods!AD29-Periods!AD28)) -> 1
J32: FP8 | K32: =MIN(1,(MAX(0, Periods!U30-(K$21+K$20))+MAX(0,K$21-Periods!U29))/(Periods!U30-Periods!U29)) -> 1 | L32: =MIN(1,(MAX(0, Periods!V30-(L$21+L$20))+MAX(0,L$21-Periods!V29))/(Periods!V30-Periods!V29)) -> 1 | M32: =MIN(1,(MAX(0, Periods!W30-(M$21+M$20))+MAX(0,M$21-Periods!W29))/(Periods!W30-Periods!W29)) -> 1 | N32: =MIN(1,(MAX(0, Periods!X30-(N$21+N$20))+MAX(0,N$21-Periods!X29))/(Periods!X30-Periods!X29)) -> 1 | O32: =MIN(1,(MAX(0, Periods!Y30-(O$21+O$20))+MAX(0,O$21-Periods!Y29))/(Periods!Y30-Periods!Y29)) -> 1 | P32: =MIN(1,(MAX(0, Periods!Z30-(P$21+P$20))+MAX(0,P$21-Periods!Z29))/(Periods!Z30-Periods!Z29)) -> 1 | Q32: =MIN(1,(MAX(0, Periods!AA30-(Q$21+Q$20))+MAX(0,Q$21-Periods!AA29))/(Periods!AA30-Periods!AA29)) -> 1 | R32: =MIN(1,(MAX(0, Periods!AB30-(R$21+R$20))+MAX(0,R$21-Periods!AB29))/(Periods!AB30-Periods!AB29)) -> 1 | ... T32: =MIN(1,(MAX(0, Periods!AD30-(T$21+T$20))+MAX(0,T$21-Periods!AD29))/(Periods!AD30-Periods!AD29)) -> 1
J33: FP9 | K33: =MIN(1,(MAX(0, Periods!U31-(K$21+K$20))+MAX(0,K$21-Periods!U30))/(Periods!U31-Periods!U30)) -> 1 | L33: =MIN(1,(MAX(0, Periods!V31-(L$21+L$20))+MAX(0,L$21-Periods!V30))/(Periods!V31-Periods!V30)) -> 1 | M33: =MIN(1,(MAX(0, Periods!W31-(M$21+M$20))+MAX(0,M$21-Periods!W30))/(Periods!W31-Periods!W30)) -> 1 | N33: =MIN(1,(MAX(0, Periods!X31-(N$21+N$20))+MAX(0,N$21-Periods!X30))/(Periods!X31-Periods!X30)) -> 1 | O33: =MIN(1,(MAX(0, Periods!Y31-(O$21+O$20))+MAX(0,O$21-Periods!Y30))/(Periods!Y31-Periods!Y30)) -> 1 | P33: =MIN(1,(MAX(0, Periods!Z31-(P$21+P$20))+MAX(0,P$21-Periods!Z30))/(Periods!Z31-Periods!Z30)) -> 1 | Q33: =MIN(1,(MAX(0, Periods!AA31-(Q$21+Q$20))+MAX(0,Q$21-Periods!AA30))/(Periods!AA31-Periods!AA30)) -> 1 | R33: =MIN(1,(MAX(0, Periods!AB31-(R$21+R$20))+MAX(0,R$21-Periods!AB30))/(Periods!AB31-Periods!AB30)) -> 1 | ... T33: =MIN(1,(MAX(0, Periods!AD31-(T$21+T$20))+MAX(0,T$21-Periods!AD30))/(Periods!AD31-Periods!AD30)) -> 1
C34: ïnsertline
G35: Data Sharing for Annual Pasture sheet (P1a) | AD35: ïnsertcolumnfinish | AE35: «»
C40: « | AD40: ïnsertcolumnstart
D41: 0 | E41: Däta | G41: ABOUT Annual Pasture structure & data (P1a)
G42: Background details
G43: 37998.527 | H43: 37998.527
C44: 1
C49: FïlterStart | J49: frëeze
H51: This sheet contains pasture production, quality and rates of decline. Pasture growth rates were calculated from results
H52: of the GrassGro model run by Paul Sanford.
H53: Note: FOO is entered in the units as measured in the locality. It is later converted to the units required for the prediction of intake that is used in the Sheep Generator.
H55: Key people for EWW data: | K55: Michael Young
H56: Data sources: | K56: AusFarm model
H57: Module version | K57: P1-1a
H58: Last major review of this sheet: | K58: 45292
H60: Recent changes
C62: ïnsertline
G63: ABOUT Annual Pasture structure & data (P1a) | AD63: ïnsertcolumnfinish | AE63: «»
C67: « | AD67: ïnsertcolumnstart
D68: 0 | E68: Däta | G68: Module Definition Table - Pasture (P1a)
G69: Defines where this module fits
G70: 37998.729 | H70: 37998.729
C71: 1
G75: Related to | H75: This module | J75: typ | K75: z0 | L75: z1 | M75: z2 | N75: z3 | O75: z4 | P75: z5 | Q75: z6 | R75: z7 | S75: z8
C76: FïlterStart | J76: frëeze
G78: Loss of pasture due to trampling (green & dry) | J78: 0.1
G79: End of growing season (period) | J79: 5 | K79: 5 | L79: 5 | M79: 5 | N79: 5 | O79: 5 | P79: 5 | Q79: 5 | R79: 5 | S79: 5
G80: Period when dry feed becomes available to livestock | J80: 6 | K80: 6 | L80: 6 | M80: 6 | N80: 6 | O80: 6 | P80: 6 | Q80: 6 | R80: 6 | S80: 6
G81: Decay of dry pasture in summer/autumn (%/d) | J81: 0.002
C85: ïnsertline
G86: =G68 -> Module Definition Table - Pasture (P1a) | AD86: ïnsertcolumnfinish | AE86: «»
C90: « | AD90: ïnsertcolumnstart
D91: 0 | E91: Däta | G91: Pasture coverage
G92: What propn of the LMU can pasture grow on?
G93: 44718.38
C94: 1
J98: LMU0 | K98: LMU1 | L98: LMU2 | M98: LMU3 | N98: LMU4 | O98: LMU5 | P98: LMU6 | Q98: LMU7 | R98: LMU8
C99: FïlterStart | J99: frëeze
I101: Pasture Coverage | J101: 1 | K101: 1 | L101: 1 | M101: 1 | N101: 1 | O101: 1 | P101: 1 | Q101: 1 | R101: 1
C104: ïnsertline
G105: =G91 -> Pasture coverage | AD105: ïnsertcolumnfinish | AE105: «»
C110: «
D111: 410 | E111: Däta | G111: Mobilise below ground reserves (germination) of continuous annual pasture (P1a)
G112: Input quantity mobilised on the standard soil & proportion of this achieved on other soils
G113: 37951.66
C114: 1
I117: Std LMU (LMU2) | J117: Mobilisation on other LMUs | T117: Proportion of Mobilisation in each Feed Period
H118: Season type | I118: kg/ha | J118: LMU0 | K118: LMU1 | L118: LMU2 | M118: LMU3 | N118: LMU4 | O118: LMU5 | P118: LMU6 | Q118: LMU7 | R118: LMU8 | T118: P0 | U118: P1 | V118: P2 | W118: P3 | X118: P4 | Y118: P5 | Z118: P6 | AA118: P7 | AB118: P8 | AC118: P9
I119: frëeze
H121: typ | I121: 119.56818 | J121: =V$229 -> 0.72387914 | K121: =W$229 -> 0.90116959 | L121: =X$229 -> 1.0243665 | M121: =Y$229 -> 1 | N121: =Z$229 -> 1.0750487 | O121: =AA$229 -> 0.98684211 | P121: =AB$229 -> 0.89122807 | Q121: =AC$229 -> 0.56 | R121: =AD$229 -> 0 | T121: 0 | U121: 1 | V121: 0 | W121: 0 | X121: 0 | Y121: 0 | Z121: 0 | AA121: 0 | AB121: 0 | AC121: 0
H122: z0 | I122: 146.34697 | J122: =V$229 -> 0.72387914 | K122: =W$229 -> 0.90116959 | L122: =X$229 -> 1.0243665 | M122: =Y$229 -> 1 | N122: =Z$229 -> 1.0750487 | O122: =AA$229 -> 0.98684211 | P122: =AB$229 -> 0.89122807 | Q122: =AC$229 -> 0.56 | R122: =AD$229 -> 0 | T122: 0 | U122: 1 | V122: 0 | W122: 0 | X122: 0 | Y122: 0 | Z122: 0 | AA122: 0 | AB122: 0 | AC122: 0
H123: z1 | I123: 146.34697 | J123: =V$229 -> 0.72387914 | K123: =W$229 -> 0.90116959 | L123: =X$229 -> 1.0243665 | M123: =Y$229 -> 1 | N123: =Z$229 -> 1.0750487 | O123: =AA$229 -> 0.98684211 | P123: =AB$229 -> 0.89122807 | Q123: =AC$229 -> 0.56 | R123: =AD$229 -> 0 | T123: 0 | U123: 1 | V123: 0 | W123: 0 | X123: 0 | Y123: 0 | Z123: 0 | AA123: 0 | AB123: 0 | AC123: 0
H124: z2 | I124: 146.34697 | J124: =V$229 -> 0.72387914 | K124: =W$229 -> 0.90116959 | L124: =X$229 -> 1.0243665 | M124: =Y$229 -> 1 | N124: =Z$229 -> 1.0750487 | O124: =AA$229 -> 0.98684211 | P124: =AB$229 -> 0.89122807 | Q124: =AC$229 -> 0.56 | R124: =AD$229 -> 0 | T124: 0 | U124: 1 | V124: 0 | W124: 0 | X124: 0 | Y124: 0 | Z124: 0 | AA124: 0 | AB124: 0 | AC124: 0
H125: z3 | I125: 146.34697 | J125: =V$229 -> 0.72387914 | K125: =W$229 -> 0.90116959 | L125: =X$229 -> 1.0243665 | M125: =Y$229 -> 1 | N125: =Z$229 -> 1.0750487 | O125: =AA$229 -> 0.98684211 | P125: =AB$229 -> 0.89122807 | Q125: =AC$229 -> 0.56 | R125: =AD$229 -> 0 | T125: 0 | U125: 1 | V125: 0 | W125: 0 | X125: 0 | Y125: 0 | Z125: 0 | AA125: 0 | AB125: 0 | AC125: 0
H126: z4 | I126: 102.40384 | J126: =V$229 -> 0.72387914 | K126: =W$229 -> 0.90116959 | L126: =X$229 -> 1.0243665 | M126: =Y$229 -> 1 | N126: =Z$229 -> 1.0750487 | O126: =AA$229 -> 0.98684211 | P126: =AB$229 -> 0.89122807 | Q126: =AC$229 -> 0.56 | R126: =AD$229 -> 0 | T126: 0 | U126: 1 | V126: 0 | W126: 0 | X126: 0 | Y126: 0 | Z126: 0 | AA126: 0 | AB126: 0 | AC126: 0
H127: z5 | I127: 102.40384 | J127: =V$229 -> 0.72387914 | K127: =W$229 -> 0.90116959 | L127: =X$229 -> 1.0243665 | M127: =Y$229 -> 1 | N127: =Z$229 -> 1.0750487 | O127: =AA$229 -> 0.98684211 | P127: =AB$229 -> 0.89122807 | Q127: =AC$229 -> 0.56 | R127: =AD$229 -> 0 | T127: 0 | U127: 1 | V127: 0 | W127: 0 | X127: 0 | Y127: 0 | Z127: 0 | AA127: 0 | AB127: 0 | AC127: 0
H128: z6 | I128: 102.40384 | J128: =V$229 -> 0.72387914 | K128: =W$229 -> 0.90116959 | L128: =X$229 -> 1.0243665 | M128: =Y$229 -> 1 | N128: =Z$229 -> 1.0750487 | O128: =AA$229 -> 0.98684211 | P128: =AB$229 -> 0.89122807 | Q128: =AC$229 -> 0.56 | R128: =AD$229 -> 0 | T128: 0 | U128: 1 | V128: 0 | W128: 0 | X128: 0 | Y128: 0 | Z128: 0 | AA128: 0 | AB128: 0 | AC128: 0
H129: z7 | I129: 102.40384 | J129: =V$229 -> 0.72387914 | K129: =W$229 -> 0.90116959 | L129: =X$229 -> 1.0243665 | M129: =Y$229 -> 1 | N129: =Z$229 -> 1.0750487 | O129: =AA$229 -> 0.98684211 | P129: =AB$229 -> 0.89122807 | Q129: =AC$229 -> 0.56 | R129: =AD$229 -> 0 | T129: 0 | U129: 1 | V129: 0 | W129: 0 | X129: 0 | Y129: 0 | Z129: 0 | AA129: 0 | AB129: 0 | AC129: 0
H130: z8 | I130: 100.87323 | J130: =V$229 -> 0.72387914 | K130: =W$229 -> 0.90116959 | L130: =X$229 -> 1.0243665 | M130: =Y$229 -> 1 | N130: =Z$229 -> 1.0750487 | O130: =AA$229 -> 0.98684211 | P130: =AB$229 -> 0.89122807 | Q130: =AC$229 -> 0.56 | R130: =AD$229 -> 0 | T130: 0 | U130: 1 | V130: 0 | W130: 0 | X130: 0 | Y130: 0 | Z130: 0 | AA130: 0 | AB130: 0 | AC130: 0
G133: =G111 -> Mobilise below ground reserves (germination) of continuous annual pasture (P1a) | AE133: «»
C137: « | AD137: ïnsertcolumnstart
D138: 0 | E138: Däta | G138: Reseeding pasture: Production & timing (annual pasture) (P1a)
G139: Input details of seeding date & first grazing date & quantity available.
G140: 38000.38 | H140: 38000.38
C141: 1
J145: {=TRANSPOSE(H121:H130)} -> typ | K145: z0 | L145: z1 | M145: z2 | N145: z3 | O145: z4 | P145: z5 | Q145: z6 | R145: z7 | S145: z8
C146: FïlterStart | J146: frëeze
H148: Date destocked | J148: 43570 | K148: 43570 | L148: 43570 | M148: 43570 | N148: 43570 | O148: 43570 | P148: 43570 | Q148: 43570 | R148: 43570 | S148: 43570
I149: day of yr | J149: =MIN(51,INT((J148 - DATE(YEAR(J148),1,1))/7))*7 -> 98 | K149: =MIN(51,INT((K148 - DATE(YEAR(K148),1,1))/7))*7 -> 98 | L149: =MIN(51,INT((L148 - DATE(YEAR(L148),1,1))/7))*7 -> 98 | M149: =MIN(51,INT((M148 - DATE(YEAR(M148),1,1))/7))*7 -> 98 | N149: =MIN(51,INT((N148 - DATE(YEAR(N148),1,1))/7))*7 -> 98 | O149: =MIN(51,INT((O148 - DATE(YEAR(O148),1,1))/7))*7 -> 98 | P149: =MIN(51,INT((P148 - DATE(YEAR(P148),1,1))/7))*7 -> 98 | Q149: =MIN(51,INT((Q148 - DATE(YEAR(Q148),1,1))/7))*7 -> 98 | ... S149: =MIN(51,INT((S148 - DATE(YEAR(S148),1,1))/7))*7 -> 98
H150: Date of sowing pasture | J150: 43580 | K150: 43580 | L150: 43580 | M150: 43580 | N150: 43610 | O150: 43580 | P150: 43580 | Q150: 43580 | R150: 43580 | S150: 43580
I151: day of yr | J151: =MIN(51,INT((J150 - DATE(YEAR(J150),1,1))/7))*7 -> 112 | K151: =MIN(51,INT((K150 - DATE(YEAR(K150),1,1))/7))*7 -> 112 | L151: =MIN(51,INT((L150 - DATE(YEAR(L150),1,1))/7))*7 -> 112 | M151: =MIN(51,INT((M150 - DATE(YEAR(M150),1,1))/7))*7 -> 112 | N151: =MIN(51,INT((N150 - DATE(YEAR(N150),1,1))/7))*7 -> 140 | O151: =MIN(51,INT((O150 - DATE(YEAR(O150),1,1))/7))*7 -> 112 | P151: =MIN(51,INT((P150 - DATE(YEAR(P150),1,1))/7))*7 -> 112 | Q151: =MIN(51,INT((Q150 - DATE(YEAR(Q150),1,1))/7))*7 -> 112 | ... S151: =MIN(51,INT((S150 - DATE(YEAR(S150),1,1))/7))*7 -> 112
H152: End of pasture sowing window | J152: 43603 | K152: 43603 | L152: 43603 | M152: 43603 | N152: 43603 | O152: 43603 | P152: 43603 | Q152: 43603 | R152: 43603 | S152: 43603
I153: day of yr | J153: =MIN(51,INT((J152 - DATE(YEAR(J152),1,1))/7))*7 -> 133 | K153: =MIN(51,INT((K152 - DATE(YEAR(K152),1,1))/7))*7 -> 133 | L153: =MIN(51,INT((L152 - DATE(YEAR(L152),1,1))/7))*7 -> 133 | M153: =MIN(51,INT((M152 - DATE(YEAR(M152),1,1))/7))*7 -> 133 | N153: =MIN(51,INT((N152 - DATE(YEAR(N152),1,1))/7))*7 -> 133 | O153: =MIN(51,INT((O152 - DATE(YEAR(O152),1,1))/7))*7 -> 133 | P153: =MIN(51,INT((P152 - DATE(YEAR(P152),1,1))/7))*7 -> 133 | Q153: =MIN(51,INT((Q152 - DATE(YEAR(Q152),1,1))/7))*7 -> 133 | ... S153: =MIN(51,INT((S152 - DATE(YEAR(S152),1,1))/7))*7 -> 133
H154: Date of first grazing | J154: 43631 | K154: 43631 | L154: 43631 | M154: =K154+15 -> 43646 | N154: =L154+15 -> 43646 | O154: 43636 | P154: 43636 | Q154: =O154+15 -> 43651 | R154: =P154+15 -> 43651 | S154: 43631
I155: day of yr | J155: =MIN(51,INT((J154 - DATE(YEAR(J154),1,1))/7))*7 -> 161 | K155: =MIN(51,INT((K154 - DATE(YEAR(K154),1,1))/7))*7 -> 161 | L155: =MIN(51,INT((L154 - DATE(YEAR(L154),1,1))/7))*7 -> 161 | M155: =MIN(51,INT((M154 - DATE(YEAR(M154),1,1))/7))*7 -> 175 | N155: =MIN(51,INT((N154 - DATE(YEAR(N154),1,1))/7))*7 -> 175 | O155: =MIN(51,INT((O154 - DATE(YEAR(O154),1,1))/7))*7 -> 168 | P155: =MIN(51,INT((P154 - DATE(YEAR(P154),1,1))/7))*7 -> 168 | Q155: =MIN(51,INT((Q154 - DATE(YEAR(Q154),1,1))/7))*7 -> 182 | ... S155: =MIN(51,INT((S154 - DATE(YEAR(S154),1,1))/7))*7 -> 161
H156: FOO when destocked (wasted) | J156: 500 | K156: 500 | L156: 500 | M156: 500 | N156: 500 | O156: 500 | P156: 500 | Q156: 500 | R156: 500 | S156: 500
H157: with date check | J157: =IF(Date_Destocking<=INDEX(i_break_date,MATCH(J145,General!i_z_idx,0),1),0,J156) -> 0 | K157: =IF(Date_Destocking<=INDEX(i_break_date,MATCH(K145,General!i_z_idx,0),1),0,K156) -> 0 | L157: =IF(Date_Destocking<=INDEX(i_break_date,MATCH(L145,General!i_z_idx,0),1),0,L156) -> 0 | M157: =IF(Date_Destocking<=INDEX(i_break_date,MATCH(M145,General!i_z_idx,0),1),0,M156) -> 0 | N157: =IF(Date_Destocking<=INDEX(i_break_date,MATCH(N145,General!i_z_idx,0),1),0,N156) -> 0 | O157: =IF(Date_Destocking<=INDEX(i_break_date,MATCH(O145,General!i_z_idx,0),1),0,O156) -> 0 | P157: =IF(Date_Destocking<=INDEX(i_break_date,MATCH(P145,General!i_z_idx,0),1),0,P156) -> 0 | Q157: =IF(Date_Destocking<=INDEX(i_break_date,MATCH(Q145,General!i_z_idx,0),1),0,Q156) -> 0 | ... S157: =IF(Date_Destocking<=INDEX(i_break_date,MATCH(S145,General!i_z_idx,0),1),0,S156) -> 0
G159: Note: | H159: 1. The year entered in the dates above needs to be consistent with the date used to defiine the feed periods.
...

Sheet Understory
C4: « | AD4: ïnsertcolumnstart
D5: 0 | E5: Däta | G5: Data Sharing for Annual Pasture sheet (P1a)
G6: Standard format for all data transferred between modules
G7: 37998.514 | H7: 37998.514
C8: 1
C13: FïlterStart | J13: frëeze
G16: Relative Intake Coefficients | K16: =J71 -> typ | L16: =K71 -> z0 | M16: =L71 -> z1 | N16: =M71 -> z2 | O16: =N71 -> z3 | P16: =O71 -> z4 | Q16: =P71 -> z5 | R16: =Q71 -> z6 | ... T16: =S71 -> z8
H17: Proportion of clover in the sward | K17: 0.2 | L17: 0.2 | M17: 0.2 | N17: 0.2 | O17: 0.2 | P17: 0.2 | Q17: 0.2 | R17: 0.2 | S17: 0.2 | T17: 0.2
H18: Height ratio scalar | K18: 2 | L18: 2 | M18: 2 | N18: 2 | O18: 2 | P18: 2 | Q18: 2 | R18: 2 | S18: 2 | T18: 2
H20: Pasture stage | J20: FP0 | K20: =Annual!K24 -> 1 | L20: =Annual!L24 -> 1 | M20: =Annual!M24 -> 1 | N20: =Annual!N24 -> 1 | O20: =Annual!O24 -> 1 | P20: =Annual!P24 -> 1 | Q20: =Annual!Q24 -> 1 | R20: =Annual!R24 -> 1 | ... T20: =Annual!T24 -> 1
J21: FP1 | K21: =Annual!K25 -> 0 | L21: =Annual!L25 -> 0.28571429 | M21: =Annual!M25 -> 0.28571429 | N21: =Annual!N25 -> 0.28571429 | O21: =Annual!O25 -> 0.28571429 | P21: =Annual!P25 -> 0 | Q21: =Annual!Q25 -> 0 | R21: =Annual!R25 -> 0 | ... T21: =Annual!T25 -> 0
J22: FP2 | K22: =Annual!K26 -> 0.96428571 | L22: =Annual!L26 -> 1 | M22: =Annual!M26 -> 1 | N22: =Annual!N26 -> 1 | O22: =Annual!O26 -> 1 | P22: =Annual!P26 -> 0.83928571 | Q22: =Annual!Q26 -> 0.83928571 | R22: =Annual!R26 -> 0.83928571 | ... T22: =Annual!T26 -> 0.83928571
J23: FP3 | K23: =Annual!K27 -> 1 | L23: =Annual!L27 -> 1 | M23: =Annual!M27 -> 1 | N23: =Annual!N27 -> 1 | O23: =Annual!O27 -> 1 | P23: =Annual!P27 -> 1 | Q23: =Annual!Q27 -> 1 | R23: =Annual!R27 -> 1 | ... T23: =Annual!T27 -> 1
J24: FP4 | K24: =Annual!K28 -> 1 | L24: =Annual!L28 -> 1 | M24: =Annual!M28 -> 1 | N24: =Annual!N28 -> 1 | O24: =Annual!O28 -> 1 | P24: =Annual!P28 -> 1 | Q24: =Annual!Q28 -> 1 | R24: =Annual!R28 -> 1 | ... T24: =Annual!T28 -> 1
J25: FP5 | K25: =Annual!K29 -> 1 | L25: =Annual!L29 -> 1 | M25: =Annual!M29 -> 1 | N25: =Annual!N29 -> 1 | O25: =Annual!O29 -> 1 | P25: =Annual!P29 -> 1 | Q25: =Annual!Q29 -> 1 | R25: =Annual!R29 -> 1 | ... T25: =Annual!T29 -> 1
J26: FP6 | K26: =Annual!K30 -> 1 | L26: =Annual!L30 -> 1 | M26: =Annual!M30 -> 1 | N26: =Annual!N30 -> 1 | O26: =Annual!O30 -> 1 | P26: =Annual!P30 -> 1 | Q26: =Annual!Q30 -> 1 | R26: =Annual!R30 -> 1 | ... T26: =Annual!T30 -> 1
J27: FP7 | K27: =Annual!K31 -> 1 | L27: =Annual!L31 -> 1 | M27: =Annual!M31 -> 1 | N27: =Annual!N31 -> 1 | O27: =Annual!O31 -> 1 | P27: =Annual!P31 -> 1 | Q27: =Annual!Q31 -> 1 | R27: =Annual!R31 -> 1 | ... T27: =Annual!T31 -> 1
J28: FP8 | K28: =Annual!K32 -> 1 | L28: =Annual!L32 -> 1 | M28: =Annual!M32 -> 1 | N28: =Annual!N32 -> 1 | O28: =Annual!O32 -> 1 | P28: =Annual!P32 -> 1 | Q28: =Annual!Q32 -> 1 | R28: =Annual!R32 -> 1 | ... T28: =Annual!T32 -> 1
J29: FP9 | K29: =Annual!K33 -> 1 | L29: =Annual!L33 -> 1 | M29: =Annual!M33 -> 1 | N29: =Annual!N33 -> 1 | O29: =Annual!O33 -> 1 | P29: =Annual!P33 -> 1 | Q29: =Annual!Q33 -> 1 | R29: =Annual!R33 -> 1 | ... T29: =Annual!T33 -> 1
C30: ïnsertline
G31: Data Sharing for Annual Pasture sheet (P1a) | AD31: ïnsertcolumnfinish | AE31: «»
C36: « | AD36: ïnsertcolumnstart
D37: 0 | E37: Däta | G37: ABOUT Annual Pasture structure & data (P1a)
G38: Background details
G39: 37998.527 | H39: 37998.527
C40: 1
C45: FïlterStart | J45: frëeze
H47: This sheet contains pasture production, quality and rates of decline. Pasture growth rates were calculated from results
H48: of the GrassGro model run by Paul Sanford.
H49: Note: FOO is entered in the units as measured in the locality. It is later converted to the units required for the prediction of intake that is used in the Sheep Generator.
H51: Key people for CWW data: | K51: John Young, Paul Sanford
H52: Data sources: | K52: GrassGro model
H53: Module version | K53: P1-1a
H54: Last major review of this sheet: | K54: 44197
H56: Recent changes
H57: 27Dec23 update PGR based on PfS and remove SAM from exp 4Apr22: Add HR scalar with z axis. Change the base level FOO to 400kg/ha. Add pasture stage (for foo conversion) with p6z axes. 12Dec21: Changed germination to mobilisation of below ground reserves. Adjust inputs for the period of mobilisation (to periods 1 or 2 depending on time of break - may need more changing) 11Jul21: Remove digdeclinefoo input. Set mainteff back to 50% after the error had been removed. 1Jul21: Change FEC to NV 20Jun21: ALter ME efficiency input to 100% to mask a calculation error (revert when error is fixed) 3Jun21: Tweak inputs for PGR with GrazeH. Edit comment on restocking FOO. 23May21: Adjust quality of the dry feed pool to improve the range of the senescing feed (& alter table design slightly) 29Apr21: Tweaked pasture quality values 28Apr21: Altered DMD of green pasture to reflect the new DMD calculations that work from the best quality and a reduction 27Apr21: Altered the base level to 300kg/ha Added outlining for the season types, so that the typical season values could be viewed without the full detail GSM data: added 1.5 & 1.5% decline in dmd per month to P4 & P5
C58: ïnsertline
G59: ABOUT Annual Pasture structure & data (P1a) | AD59: ïnsertcolumnfinish | AE59: «»
C63: « | AD63: ïnsertcolumnstart
D64: 0 | E64: Däta | G64: Module Definition Table - Pasture (P1a)
G65: Defines where this module fits
G66: 37998.729 | H66: 37998.729
C67: 1
G71: Related to | H71: This module | J71: typ | K71: z0 | L71: z1 | M71: z2 | N71: z3 | O71: z4 | P71: z5 | Q71: z6 | R71: z7 | S71: z8
C72: FïlterStart | J72: frëeze
G74: Loss of pasture due to trampling (green & dry) | J74: 0.1
G75: End of growing season (period) | J75: =Annual!J79 -> 5 | K75: =Annual!K79 -> 5 | L75: =Annual!L79 -> 5 | M75: =Annual!M79 -> 5 | N75: =Annual!N79 -> 5 | O75: =Annual!O79 -> 5 | P75: =Annual!P79 -> 5 | Q75: =Annual!Q79 -> 5 | ... S75: =Annual!S79 -> 5
G76: Period when dry feed becomes available to livestock | J76: =Annual!J80 -> 6 | K76: =Annual!K80 -> 6 | L76: =Annual!L80 -> 6 | M76: =Annual!M80 -> 6 | N76: =Annual!N80 -> 6 | O76: =Annual!O80 -> 6 | P76: =Annual!P80 -> 6 | Q76: =Annual!Q80 -> 6 | ... S76: =Annual!S80 -> 6
G77: Decay of dry pasture in summer/autumn (%/d) | J77: =Annual!J81 -> 0.002
C81: ïnsertline
G82: =G64 -> Module Definition Table - Pasture (P1a) | AD82: ïnsertcolumnfinish | AE82: «»
C86: « | AD86: ïnsertcolumnstart
D87: 0 | E87: Däta | G87: Pasture coverage
G88: What propn of the LMU can pasture grow on?
G89: 44718.38
C90: 1
J94: LMU0 | K94: LMU1 | L94: LMU2 | M94: LMU3 | N94: LMU4 | O94: LMU5 | P94: LMU6 | Q94: LMU7 | R94: LMU8
C95: FïlterStart | J95: frëeze
I97: Pasture Coverage | J97: 0.9 | K97: 0.9 | L97: 0.9 | M97: 0.9 | N97: 0.9 | O97: 0.9 | P97: 0.9 | Q97: 0.9 | R97: 0.9
C100: ïnsertline
G101: =G87 -> Pasture coverage | AD101: ïnsertcolumnfinish | AE101: «»
C106: «
D107: 410 | E107: Däta | G107: Mobilise below ground reserves (germination) of continuous annual pasture (P1a)
G108: Input quantity mobilised on the standard soil & proportion of this achieved on other soils
G109: 37951.66
C110: 1
I113: Std LMU (LMU2) | J113: Mobilisation on other LMUs | T113: Proportion of Mobilisation in each Feed Period
H114: Season type | I114: kg/ha | J114: LMU0 | K114: LMU1 | L114: LMU2 | M114: LMU3 | N114: LMU4 | O114: LMU5 | P114: LMU6 | Q114: LMU7 | R114: LMU8 | T114: P0 | U114: P1 | V114: P2 | W114: P3 | X114: P4 | Y114: P5 | Z114: P6 | AA114: P7 | AB114: P8 | AC114: P9
I115: frëeze
H117: typ | I117: =Annual!I121 -> 119.56818 | J117: =Annual!J121 -> 0.72387914 | K117: =Annual!K121 -> 0.90116959 | L117: =Annual!L121 -> 1.0243665 | M117: =Annual!M121 -> 1 | N117: =Annual!N121 -> 1.0750487 | O117: =Annual!O121 -> 0.98684211 | P117: =Annual!P121 -> 0.89122807 | ... R117: =Annual!R121 -> 0 | T117: =Annual!T121 -> 0 | U117: =Annual!U121 -> 1 | V117: =Annual!V121 -> 0 | W117: =Annual!W121 -> 0 | X117: =Annual!X121 -> 0 | Y117: =Annual!Y121 -> 0 | Z117: =Annual!Z121 -> 0 | AA117: =Annual!AA121 -> 0 | ... AC117: =Annual!AC121 -> 0
H118: z0 | I118: =Annual!I122 -> 146.34697 | J118: =Annual!J122 -> 0.72387914 | K118: =Annual!K122 -> 0.90116959 | L118: =Annual!L122 -> 1.0243665 | M118: =Annual!M122 -> 1 | N118: =Annual!N122 -> 1.0750487 | O118: =Annual!O122 -> 0.98684211 | P118: =Annual!P122 -> 0.89122807 | ... R118: =Annual!R122 -> 0 | T118: =Annual!T122 -> 0 | U118: =Annual!U122 -> 1 | V118: =Annual!V122 -> 0 | W118: =Annual!W122 -> 0 | X118: =Annual!X122 -> 0 | Y118: =Annual!Y122 -> 0 | Z118: =Annual!Z122 -> 0 | AA118: =Annual!AA122 -> 0 | ... AC118: =Annual!AC122 -> 0
H119: z1 | I119: =Annual!I123 -> 146.34697 | J119: =Annual!J123 -> 0.72387914 | K119: =Annual!K123 -> 0.90116959 | L119: =Annual!L123 -> 1.0243665 | M119: =Annual!M123 -> 1 | N119: =Annual!N123 -> 1.0750487 | O119: =Annual!O123 -> 0.98684211 | P119: =Annual!P123 -> 0.89122807 | ... R119: =Annual!R123 -> 0 | T119: =Annual!T123 -> 0 | U119: =Annual!U123 -> 1 | V119: =Annual!V123 -> 0 | W119: =Annual!W123 -> 0 | X119: =Annual!X123 -> 0 | Y119: =Annual!Y123 -> 0 | Z119: =Annual!Z123 -> 0 | AA119: =Annual!AA123 -> 0 | ... AC119: =Annual!AC123 -> 0
H120: z2 | I120: =Annual!I124 -> 146.34697 | J120: =Annual!J124 -> 0.72387914 | K120: =Annual!K124 -> 0.90116959 | L120: =Annual!L124 -> 1.0243665 | M120: =Annual!M124 -> 1 | N120: =Annual!N124 -> 1.0750487 | O120: =Annual!O124 -> 0.98684211 | P120: =Annual!P124 -> 0.89122807 | ... R120: =Annual!R124 -> 0 | T120: =Annual!T124 -> 0 | U120: =Annual!U124 -> 1 | V120: =Annual!V124 -> 0 | W120: =Annual!W124 -> 0 | X120: =Annual!X124 -> 0 | Y120: =Annual!Y124 -> 0 | Z120: =Annual!Z124 -> 0 | AA120: =Annual!AA124 -> 0 | ... AC120: =Annual!AC124 -> 0
H121: z3 | I121: =Annual!I125 -> 146.34697 | J121: =Annual!J125 -> 0.72387914 | K121: =Annual!K125 -> 0.90116959 | L121: =Annual!L125 -> 1.0243665 | M121: =Annual!M125 -> 1 | N121: =Annual!N125 -> 1.0750487 | O121: =Annual!O125 -> 0.98684211 | P121: =Annual!P125 -> 0.89122807 | ... R121: =Annual!R125 -> 0 | T121: =Annual!T125 -> 0 | U121: =Annual!U125 -> 1 | V121: =Annual!V125 -> 0 | W121: =Annual!W125 -> 0 | X121: =Annual!X125 -> 0 | Y121: =Annual!Y125 -> 0 | Z121: =Annual!Z125 -> 0 | AA121: =Annual!AA125 -> 0 | ... AC121: =Annual!AC125 -> 0
H122: z4 | I122: =Annual!I126 -> 102.40384 | J122: =Annual!J126 -> 0.72387914 | K122: =Annual!K126 -> 0.90116959 | L122: =Annual!L126 -> 1.0243665 | M122: =Annual!M126 -> 1 | N122: =Annual!N126 -> 1.0750487 | O122: =Annual!O126 -> 0.98684211 | P122: =Annual!P126 -> 0.89122807 | ... R122: =Annual!R126 -> 0 | T122: =Annual!T126 -> 0 | U122: =Annual!U126 -> 1 | V122: =Annual!V126 -> 0 | W122: =Annual!W126 -> 0 | X122: =Annual!X126 -> 0 | Y122: =Annual!Y126 -> 0 | Z122: =Annual!Z126 -> 0 | AA122: =Annual!AA126 -> 0 | ... AC122: =Annual!AC126 -> 0
H123: z5 | I123: =Annual!I127 -> 102.40384 | J123: =Annual!J127 -> 0.72387914 | K123: =Annual!K127 -> 0.90116959 | L123: =Annual!L127 -> 1.0243665 | M123: =Annual!M127 -> 1 | N123: =Annual!N127 -> 1.0750487 | O123: =Annual!O127 -> 0.98684211 | P123: =Annual!P127 -> 0.89122807 | ... R123: =Annual!R127 -> 0 | T123: =Annual!T127 -> 0 | U123: =Annual!U127 -> 1 | V123: =Annual!V127 -> 0 | W123: =Annual!W127 -> 0 | X123: =Annual!X127 -> 0 | Y123: =Annual!Y127 -> 0 | Z123: =Annual!Z127 -> 0 | AA123: =Annual!AA127 -> 0 | ... AC123: =Annual!AC127 -> 0
H124: z6 | I124: =Annual!I128 -> 102.40384 | J124: =Annual!J128 -> 0.72387914 | K124: =Annual!K128 -> 0.90116959 | L124: =Annual!L128 -> 1.0243665 | M124: =Annual!M128 -> 1 | N124: =Annual!N128 -> 1.0750487 | O124: =Annual!O128 -> 0.98684211 | P124: =Annual!P128 -> 0.89122807 | ... R124: =Annual!R128 -> 0 | T124: =Annual!T128 -> 0 | U124: =Annual!U128 -> 1 | V124: =Annual!V128 -> 0 | W124: =Annual!W128 -> 0 | X124: =Annual!X128 -> 0 | Y124: =Annual!Y128 -> 0 | Z124: =Annual!Z128 -> 0 | AA124: =Annual!AA128 -> 0 | ... AC124: =Annual!AC128 -> 0
H125: z7 | I125: =Annual!I129 -> 102.40384 | J125: =Annual!J129 -> 0.72387914 | K125: =Annual!K129 -> 0.90116959 | L125: =Annual!L129 -> 1.0243665 | M125: =Annual!M129 -> 1 | N125: =Annual!N129 -> 1.0750487 | O125: =Annual!O129 -> 0.98684211 | P125: =Annual!P129 -> 0.89122807 | ... R125: =Annual!R129 -> 0 | T125: =Annual!T129 -> 0 | U125: =Annual!U129 -> 1 | V125: =Annual!V129 -> 0 | W125: =Annual!W129 -> 0 | X125: =Annual!X129 -> 0 | Y125: =Annual!Y129 -> 0 | Z125: =Annual!Z129 -> 0 | AA125: =Annual!AA129 -> 0 | ... AC125: =Annual!AC129 -> 0
H126: z8 | I126: =Annual!I130 -> 100.87323 | J126: =Annual!J130 -> 0.72387914 | K126: =Annual!K130 -> 0.90116959 | L126: =Annual!L130 -> 1.0243665 | M126: =Annual!M130 -> 1 | N126: =Annual!N130 -> 1.0750487 | O126: =Annual!O130 -> 0.98684211 | P126: =Annual!P130 -> 0.89122807 | ... R126: =Annual!R130 -> 0 | T126: =Annual!T130 -> 0 | U126: =Annual!U130 -> 1 | V126: =Annual!V130 -> 0 | W126: =Annual!W130 -> 0 | X126: =Annual!X130 -> 0 | Y126: =Annual!Y130 -> 0 | Z126: =Annual!Z130 -> 0 | AA126: =Annual!AA130 -> 0 | ... AC126: =Annual!AC130 -> 0
G129: =G107 -> Mobilise below ground reserves (germination) of continuous annual pasture (P1a) | AE129: «»
C133: « | AD133: ïnsertcolumnstart
D134: 0 | E134: Däta | G134: Reseeding pasture: Production & timing (annual pasture) (P1a)
G135: Input details of seeding date & first grazing date & quantity available.
G136: 38000.38 | H136: 38000.38
C137: 1
J141: {=TRANSPOSE(H117:H126)} -> typ | K141: z0 | L141: z1 | M141: z2 | N141: z3 | O141: z4 | P141: z5 | Q141: z6 | R141: z7 | S141: z8
C142: FïlterStart | J142: frëeze
H144: Date destocked | J144: 43570 | K144: 43570 | L144: 43570 | M144: 43570 | N144: 43570 | O144: 43570 | P144: 43570 | Q144: 43570 | R144: 43570 | S144: 43570
I145: day of yr | J145: =MIN(51,INT((J144 - DATE(YEAR(J144),1,1))/7))*7 -> 98 | K145: =MIN(51,INT((K144 - DATE(YEAR(K144),1,1))/7))*7 -> 98 | L145: =MIN(51,INT((L144 - DATE(YEAR(L144),1,1))/7))*7 -> 98 | M145: =MIN(51,INT((M144 - DATE(YEAR(M144),1,1))/7))*7 -> 98 | N145: =MIN(51,INT((N144 - DATE(YEAR(N144),1,1))/7))*7 -> 98 | O145: =MIN(51,INT((O144 - DATE(YEAR(O144),1,1))/7))*7 -> 98 | P145: =MIN(51,INT((P144 - DATE(YEAR(P144),1,1))/7))*7 -> 98 | Q145: =MIN(51,INT((Q144 - DATE(YEAR(Q144),1,1))/7))*7 -> 98 | ... S145: =MIN(51,INT((S144 - DATE(YEAR(S144),1,1))/7))*7 -> 98
H146: Date of sowing pasture | J146: 43580 | K146: 43580 | L146: 43580 | M146: 43580 | N146: 43610 | O146: 43580 | P146: 43580 | Q146: 43580 | R146: 43580 | S146: 43580
I147: day of yr | J147: =MIN(51,INT((J146 - DATE(YEAR(J146),1,1))/7))*7 -> 112 | K147: =MIN(51,INT((K146 - DATE(YEAR(K146),1,1))/7))*7 -> 112 | L147: =MIN(51,INT((L146 - DATE(YEAR(L146),1,1))/7))*7 -> 112 | M147: =MIN(51,INT((M146 - DATE(YEAR(M146),1,1))/7))*7 -> 112 | N147: =MIN(51,INT((N146 - DATE(YEAR(N146),1,1))/7))*7 -> 140 | O147: =MIN(51,INT((O146 - DATE(YEAR(O146),1,1))/7))*7 -> 112 | P147: =MIN(51,INT((P146 - DATE(YEAR(P146),1,1))/7))*7 -> 112 | Q147: =MIN(51,INT((Q146 - DATE(YEAR(Q146),1,1))/7))*7 -> 112 | ... S147: =MIN(51,INT((S146 - DATE(YEAR(S146),1,1))/7))*7 -> 112
H148: End of pasture sowing window | J148: 43603 | K148: 43603 | L148: 43603 | M148: 43603 | N148: 43603 | O148: 43603 | P148: 43603 | Q148: 43603 | R148: 43603 | S148: 43603
I149: day of yr | J149: =MIN(51,INT((J148 - DATE(YEAR(J148),1,1))/7))*7 -> 133 | K149: =MIN(51,INT((K148 - DATE(YEAR(K148),1,1))/7))*7 -> 133 | L149: =MIN(51,INT((L148 - DATE(YEAR(L148),1,1))/7))*7 -> 133 | M149: =MIN(51,INT((M148 - DATE(YEAR(M148),1,1))/7))*7 -> 133 | N149: =MIN(51,INT((N148 - DATE(YEAR(N148),1,1))/7))*7 -> 133 | O149: =MIN(51,INT((O148 - DATE(YEAR(O148),1,1))/7))*7 -> 133 | P149: =MIN(51,INT((P148 - DATE(YEAR(P148),1,1))/7))*7 -> 133 | Q149: =MIN(51,INT((Q148 - DATE(YEAR(Q148),1,1))/7))*7 -> 133 | ... S149: =MIN(51,INT((S148 - DATE(YEAR(S148),1,1))/7))*7 -> 133
H150: Date of first grazing | J150: 43631 | K150: 43631 | L150: 43631 | M150: =K150+15 -> 43646 | N150: =L150+15 -> 43646 | O150: 43636 | P150: 43636 | Q150: =O150+15 -> 43651 | R150: =P150+15 -> 43651 | S150: 43631
I151: day of yr | J151: =MIN(51,INT((J150 - DATE(YEAR(J150),1,1))/7))*7 -> 161 | K151: =MIN(51,INT((K150 - DATE(YEAR(K150),1,1))/7))*7 -> 161 | L151: =MIN(51,INT((L150 - DATE(YEAR(L150),1,1))/7))*7 -> 161 | M151: =MIN(51,INT((M150 - DATE(YEAR(M150),1,1))/7))*7 -> 175 | N151: =MIN(51,INT((N150 - DATE(YEAR(N150),1,1))/7))*7 -> 175 | O151: =MIN(51,INT((O150 - DATE(YEAR(O150),1,1))/7))*7 -> 168 | P151: =MIN(51,INT((P150 - DATE(YEAR(P150),1,1))/7))*7 -> 168 | Q151: =MIN(51,INT((Q150 - DATE(YEAR(Q150),1,1))/7))*7 -> 182 | ... S151: =MIN(51,INT((S150 - DATE(YEAR(S150),1,1))/7))*7 -> 161
H152: FOO when destocked (wasted) | J152: 500 | K152: 500 | L152: 500 | M152: 500 | N152: 500 | O152: 500 | P152: 500 | Q152: 500 | R152: 500 | S152: 500
H153: with date check | J153: =IF(Date_Destocking<=INDEX(i_break_date,MATCH(J141,General!i_z_idx,0),1),0,J152) -> 0 | K153: =IF(Date_Destocking<=INDEX(i_break_date,MATCH(K141,General!i_z_idx,0),1),0,K152) -> 0 | L153: =IF(Date_Destocking<=INDEX(i_break_date,MATCH(L141,General!i_z_idx,0),1),0,L152) -> 0 | M153: =IF(Date_Destocking<=INDEX(i_break_date,MATCH(M141,General!i_z_idx,0),1),0,M152) -> 0 | N153: =IF(Date_Destocking<=INDEX(i_break_date,MATCH(N141,General!i_z_idx,0),1),0,N152) -> 0 | O153: =IF(Date_Destocking<=INDEX(i_break_date,MATCH(O141,General!i_z_idx,0),1),0,O152) -> 0 | P153: =IF(Date_Destocking<=INDEX(i_break_date,MATCH(P141,General!i_z_idx,0),1),0,P152) -> 0 | Q153: =IF(Date_Destocking<=INDEX(i_break_date,MATCH(Q141,General!i_z_idx,0),1),0,Q152) -> 0 | ... S153: =IF(Date_Destocking<=INDEX(i_break_date,MATCH(S141,General!i_z_idx,0),1),0,S152) -> 0
G155: Note: | H155: 1. The year entered in the dates above needs to be consistent with the date used to defiine the feed periods.
H156: 2. Calculations are based on feed period, so the actual day specified above doesn't affect the calculations.
H158: Note | L158: Std LMU (LMU2) | M158: Proportion available on other LMUs
...

Sheet Sheep
C2: =INT($C$6)+2 -> 3
C3: =INT($C$6)+0.005 -> 1.005
B4: « | C4: =INT($C$6)+1.005 -> 2.005
C5: =INT(MAX($C$9:$C$20))+1 -> 5 | E5: 2 | F5: 2 | G5: 2.001 | H5: 1.015 | I5: 1 | J5: 1 | K5: 1 | L5: 1 | M5: 1 | N5: 1 | O5: 1 | P5: 1 | Q5: 1 | R5: 1 | S5: 1 | T5: 1 | U5: 1 | V5: 1 | W5: 1 | X5: 1 | Y5: 1 | Z5: 1 | AA5: 1
C6: 1.02 | E6: #Inputs | F6: 2 | H6: Property: Version Control for the worksheet & Sheet controls
C7: =INT($C$6)+1.02 -> 2.02 | E7: Table Zoom: | F7: 1 | H7: Controls for this worksheet
C8: =INT($C$6)+2.005 -> 3.005
C9: =INT($C$6)+1.005 -> 2.005 | D9: ›
C10: =INT($C$6)+1 -> 2 | H10: Worksheet Version:
C11: =INT($C$6)+1.045 -> 2.045 | H11: Structure: | I11: 46054.44 | J11: 1Feb26: 31Jan26: Move the min & max NV levels from Structural. Includes a z axis here. Change the minimum value to 3.5 15Dec22: Altered formulas for period dates to calculate from the day of year in Periods rather than the input dates (changes all periods to 7 days) 4Oct22: Altered formulas for the equivalent FOO & DMD (old XMATCH) because the old method led to different feed across seasons at the season start. 1Oct22: Add calculation of chill index for the information of the user. 26Sep22: Fix error in calculation of propn_x. Was pointing to a blank cell, but input value was 0 anyway so no change. 19Jun22: Copied in the Chill index adjust from GSM 23Apr22: Added a shearing trigger for sires, dams & Offs so that animals are sold prior to sale if cfw >= trigger value. Offs: changed the the sales offset to a sale age. Removed the pffset from shearing to sale (or sale to shearing). 27Jan22: Change range name for date_born1st from oig2 to iog2 to be in the order as entered (rather than order as required) Improve the names for the scanning inputs (to differentiate drys at scanning from drys at birth) 22Jan22: Change range names for ia_r2_k to be in the order as entered (rather than order as required) 19Jan22: Add o axis to inputs on i_dry_retain_forced_o 26Nov21: Reduce j0 axis to 2 slices for paststd_foo & _dmd (altered name to reflect the new naming convention). Added i_supplement_zp6 24Sep21: alter the cashflow dates to be the maximum of the shearing dates plus 21 days (was minimum) Sep21: Add table with cashflow & peak debt dates for the stock enterprise 19Jul21: Edit the message about the Analysis Controls 16Jul21: Add an o axis to i_dry_sales_forced 14Jul21: Swap names for ia_r2_k4 & k5 which were wrong way around 30Jun21: Change all range names from m4 to p4 for month axis and m1 to p1 for daily axis. 11Jun21: Add Trigger level for 'Scan option' so that cost of the different scanning options is not charged to all scanned dams 9Jun21: Outlined the feed supply table to collapse the z axis (at level 5) 8Jun21: Add a 'Not Mated' slice to the 'k2 input cluster' so that NM can have differential nutrition from Drys (can be managed separately from pregnants prior to scanning) Fix error in i_k2_len formula Alter table shape for ia_r2_sk2ig1 to include a scan axis (and update values to point to the new feedoptions_var table) 26May21: Delete z axis from mobsize input and offs FVP input which is not used anymore 16May21: Add winter lambing inputs for all necessary tables Move the title that descibes the inclusion/exclusion of nutritional management (had got dsiplaced above sale/retention of drys) 27Apr21: remove name ranges for inputs moved to structure. 25Apr21: Moved the nut_spread table to StructuralSA sheet 8Apr21: Expanded i_nutspread_n1 range for the nutrition experiment 22Mar21: added table of inputs for variables that were in Structural but are actually Feed supply and initial values. 7Jan21: deleted paddock size input (now in Property because required for pasture labour & for crop labour) 15Dec20 & 3Jan21: Altered formulas for handling of default input for sale time of offspring 5Nov20: Deleted pre-joining sire check & Joining (adding the sires to the dams) 14Apr19: Created the workbook
C12: =INT($C$6)+1.045 -> 2.045 | H12: Data: | I12: 46053.53 | J12: 31Jan26: Changed the FOO & DMD for the back calculation from NV. Values in P0 were for green feed so they changed a lot. Changed the HR scalar in Sheep! to 2 (was 1.25) to align with the values in Annual!. Change i_dse_type to 1 (DSE based on MEI) 14Jul23: Change latitude to -31.5 (was -33 which is Kojonup) 4Jun23: Update mob size to 100hd for the period of lambing. Needs to cover the period of birth for all cycles of birth. 30Sep22: Set Chill to 0 - see GSM for more detail Change the date of spring (for the old XMATCH formula replacements) 28Sep22: Change the chill adjustment for single/twins to 20 (from 50). Scan2 impact of survival was too extreme. 10Jun22: Change the offspring sale table to days. Tidy up comments for t1 & t2. 3Apr22: Changed the Height ratio scalar to 1.25 to represent a moderate density clover pasture (c.f. the WA (region 3) standard. Change FP1 to be establishing pasture along with FP0 29Mar22: Add CWW input values to latest Property template 23Mar22: Add comment on alternate day monitoring of mated dams. Add +2 to the timing of scanning - to get the scanning costs to be incurred in the scanning DVP. 16Mar22: Change shearing date for Aut to Nov (from Oct) so that shearing is similar relative timing to Spring. Change shearing date for Win to Dec (from Jan) so that shearing is prior to joining and similar relative timing to Spring. Change the offspring lamb selling rules. Change t[1] DVP1 to a max sale offset of 250days which corrsponds to teeth eruption and no longer being a lamb. 27Jan22: Change the mating date of Yearlings to be 12 month interval 26Nov21: Altered the slope of the LWC and feedsupply to reflect value for NV definition of feedsupply. 15Jun21: Fix headings for mob size 11Jun21: Change 'Force retention of drys' to False. To remove potential clash when 'force sale of drys' is selected with the default to force retention. 3Jun21: Tweak the FS0-FS3 FOO & DMD. Change yearlilng TOL for Aut to 1 Jul 2Jun21: Tweak the FS0 FOO levels to allow for the region3 FOO adjustment 27May21: Make Aut TOL date the same for all genotypes Calibrate FS0-2 FOO and DMD. 26May21: calibrate weekly rain dist and windspeed 21May21: Change the feed supply options and the feed variation option to align with the new table (BBM & BBT point to BBT, BMT points to Maternal) 18May21: Change feed supply inputs to reflect the new feed supply with sires as 0 (and no effect of TOL) 17May21: Alter weaning age for BBM, BBT & BMT because original values were test values Alter the TOL association for progeny with dams. 16May21: Adjust feed variation options for the spring pattern to point to the expanded table in FeedSupply. Adjust the Spring FeedSupply to point to existing table. Revert to May lambing information rather than GEPEP calibration (TOL & TOS). Revert Scan to 1. 5May21: GEPEP calibration. Altered May management to fit with the GEPEP MLP management 2May21: Altered the offspring t1 & t2 definitions so that offspring can be sold at shearing in t[2]. t[1] is finished lamb for DVP0 & 1 and mid year for later DVPs Altered dates of off spring FVPs so FVP1 aligns near the break and FVP2 near peak spring 29Apr21: Altered the standard feed supply values to align with the custom region & the annual inputs 27Apr21: Change region to 3 (Custom region to set FOO conversion to -200kg/ha as per Old MIDAS GSM) 17Apr21: Adjust initial weight & CFW at weaning for dams & offspring to better match the range of progeny weights. (Increased the downside for the offspring weights) Altered the nut spread comment re:LTW 13Apr21: Force retention of drys 10Apr21: Changed scanning to 0 (fixed problem) 8Apr21: Changed scanning to 1 for all classes (0 was infeasible) Reset the May lambing shearing dates to original (had been MLP experiment dates) Altered the nutspread for 6N experiments. Dams more detail on the down side, offspring more detail on the upside Altered comment about alignment of Generator FOO and 'Pasture' FOO 4Apr21: Change TOL & TOS back to standard values. Set scan = 0 (to simplify the LW patterns) Fix positioning of some comments 29Mar21:Set nutrition to 0, 1 , -1. 18Mar21: Change the standard TOL to both included, so FeedTest will report both TOL. 27: Alter dam age index to 3 letters 26:Altered sale inputs for offspring to align with the code and altered the default formulas for t1 & t2 Finetuned the husbandry wrt crutching & mulesing BBT. Altered Husbandry number to be python 0 based (when cross checking) 25: Altered set name for weaning. Fixed ia_i_idg2 TOL to 0 & 1 24: Altered the FOO & digestibility of dry feed to align with the new values in Annuals 1: 2Apr19-Added blank Standard Single Table
C13: =INT($C$6)+3.005 -> 4.005 | AQ13: ‹›
C14: =INT($C$6)+3.005 -> 4.005 | D14: ›
C15: =INT($C$6)+3 -> 4 | H15: Standards: | I15: Row H: | J15: 15 | K15: Col W: | L15: 8.43 | M15: Sheet Zoom: | O15: 1
C16: =INT($C$6)+3 -> 4 | H16: User can unprotect sheet using macros | L16: TRUE
C17: =INT($C$6)+3 -> 4 | H17: User can access protected cells | L17: TRUE
C18: =INT($C$6)+3 -> 4 | H18: View gridlines on this sheet | L18: TRUE
C19: =INT($C$6)+3 -> 4 | H19: View row & column headers on this sheet | L19: TRUE
C20: =INT($C$6)+3.005 -> 4.005 | AQ20: ‹›
C21: =INT($C$6)+2.005 -> 3.005
C22: =INT($C$6)+1.005 -> 2.005 | AR22: «»
C23: =INT($C$6)+0.005 -> 1.005
C24: =INT($C$6)+2 -> 3
C25: =INT($C$29)+2 -> 3
C26: =INT($C$29)+0.005 -> 1.005
B27: « | C27: =INT($C$29)+1.005 -> 2.005
C28: =INT(MAX($C$40:$C$172))+1 -> 5
C29: 1.02 | E29: #Inputs | H29: =COUNTIFS($B$1:$B29, "«")&" Property: Region definition inputs" -> 2 Property: Region definition inputs
C30: =INT($C$29)+1.02 -> 2.02 | E30: Table Zoom: | F30: 1 | H30: General info, FOO & DMD in each feed period, Monthly environmental data, DSE/hd
C31: =INT($C$29)+2.005 -> 3.005
C32: =INT($C$29)+2 -> 3
C33: =INT($C$29)+2 -> 3
C34: =INT($C$29)+2 -> 3
C35: =INT($C$29)+2 -> 3
B36: Ғilter | C36: =INT($C$29)+2.01 -> 3.01
C37: =INT(MAX($C$40:$C$172))+1 -> 5
B38: 07Ғreeze | C38: =INT(MAX($C$40:$C$172))+1 -> 5
C39: =INT($C$29)+1 -> 2 | H39: General info:
C40: =INT($C$29)+3.005 -> 4.005 | D40: ›
C41: =INT($C$29)+2 -> 3 | H41: Region (for FOO conversion) | J41: 0 | L41: 0 is no conversion (NSW), 1 = Victoria cut to ground level, 2 = WA cut with a scalpel, 3 = custom region (-200kg/ha), 4 = custom region (-100kg/ha)
C42: =INT($C$29)+2 -> 3 | H42: Pasture type (for FOO conversion) | J42: 0 | L42: 0 is generic pasture
C43: =INT($C$29)+2 -> 3 | H43: Latitude (-ve for south) | I43: degrees | J43: -31.5
C44: =INT($C$29)+2 -> 3 | H44: Steepness | I44: degrees | J44: 10 | L44: Average slope of the ground (defined as per Sheep Explorer. Scalar of energy requirement cf flat ground = 1 + tan(slope))
C45: =INT($C$29)+3 -> 4 | H45: Species factor | J45: 0 | L45: Species factor for intake: C3 plants 0, C4 plants 0.16
C46: =INT($C$29)+3 -> 4 | H46: Proportion of Legume | I46: (%) | J46: 0.2
C47: =INT($C$29)+3 -> 4 | H47: Height ratio scalar | J47: 2 | K47: =Annual!$H$18 -> Height ratio scalar | L47: Higher value for taller (sparse) pastures a lower value for shorter (dense) pastures
C48: =INT($C$29)+3 -> 4 | H48: Grain Quality | I48: (MJ/kg) | J48: 13.3
C49: 4 | H49: Slope of LWC and feedsupply | J49: 35 | L49: g/hd/d per unit of feedsupply (MJ/kg)
C50: 4 | H50: Standard dressing percentage | I50: (%) | J50: 0.475
C51: =INT($C$29)+3 -> 4
H53: Relative stocking rate | J53: Normal | K53: Trees
J54: 1 | K54: 1
C56: =INT($C$29)+3 -> 4 | H56: Equation system dates (see Universal for the equation system selected and the change made at the change date)
C57: =INT($C$29)+3 -> 4 | I57: Start date & date of change for equation system
C58: =INT($C$29)+3 -> 4 | I58: Sires | K58: Dams | M58: Young at foot | O58: Offspring
H59: Date: | I59: =DATE(i_startyear,1,1) -> 43466 | J59: 43466 | K59: =I59 -> 43466 | L59: 43466 | M59: =K59 -> 43466 | N59: 43466 | O59: =M59 -> 43466 | P59: 43466
C60: 3 | H60: Date: | I60: =MIN(363,INT((I59 - DATE(YEAR(I59),1,1))))+364*(YEAR(I59)-i_startyear) -> 0 | J60: =MIN(363,INT((J59 - DATE(YEAR(J59),1,1))))+364*(YEAR(J59)-i_startyear) -> 0 | K60: =MIN(363,INT((K59 - DATE(YEAR(K59),1,1))))+364*(YEAR(K59)-i_startyear) -> 0 | L60: =MIN(363,INT((L59 - DATE(YEAR(L59),1,1))))+364*(YEAR(L59)-i_startyear) -> 0 | M60: =MIN(363,INT((M59 - DATE(YEAR(M59),1,1))))+364*(YEAR(M59)-i_startyear) -> 0 | N60: =MIN(363,INT((N59 - DATE(YEAR(N59),1,1))))+364*(YEAR(N59)-i_startyear) -> 0 | O60: =MIN(363,INT((O59 - DATE(YEAR(O59),1,1))))+364*(YEAR(O59)-i_startyear) -> 0 | P60: =MIN(363,INT((P59 - DATE(YEAR(P59),1,1))))+364*(YEAR(P59)-i_startyear) -> 0
C61: =INT($C$29)+2.005 -> 3.005 | AQ61: ‹›
C62: =INT($C$29)+1 -> 2 | H62: Feed Pool Periods: | K62: Start Date | L62: Length | O62: FOO | Q62: DMD | S62: Pasture | U62: Stock density | V62: Supp level | X62: Propn paddocks | Y62: Average mob size (hd)
C63: =INT($C$29)+1 -> 2 | H63: Feed pool periods (p6) | I63: Season type | L63: (days) | O63: FS0 | P63: FS1 | Q63: FS0 | R63: FS1 | S63: stage | T63: Legume | U63: hd/ha | V63: % of ad lib | X63: stocked | Y63: Sires | AB63: Dams | AE63: Offspring
C64: =INT($C$29)+3.005 -> 4.005 | D64: ›
C65: =INT($C$29)+3 -> 4 | X65: Note: this table doesn't require a z axis when 'z' is added | AH65: Helpers for formula | AJ65: =COUNT($J$68:$J$77) -> 10
C66: =INT($C$29)+2 -> 3 | M66: Cutoff level between pools | Y66: Time of Lambing | AI66: Equivalent period in typ | AN66: For this weather-year
C67: =INT($C$29)+2 -> 3 | E67: Weather year # | F67: Adjusted date | H67: Number of feed periods | I67: Season type | J67: Period | K67: Date | L67: Length | M67: Lowest value | N67: Highest value | O67: These values are selected as typical FOO & DMD combinations and are used in the back calculation from NV to FOO & DMD They are not exact copies of the values from the Pasture data. Values are in the units of the local pasture calibration (converted to GrazFeed FOO in the Generator) | Y67: =INDEX(i_i_idx,1,1) -> Aut | Z67: =INDEX(i_i_idx,2,1) -> Win | AA67: =INDEX(i_i_idx,3,1) -> Spr | AB67: =INDEX(i_i_idx,1,1) -> Aut | AC67: =INDEX(i_i_idx,2,1) -> Win | AD67: =INDEX(i_i_idx,3,1) -> Spr | AE67: =INDEX(i_i_idx,1,1) -> Aut | AF67: =INDEX(i_i_idx,2,1) -> Win | AG67: =INDEX(i_i_idx,3,1) -> Spr | AH67: Proportion of equivalent 'typ' feed period | AI67: Lower period | AJ67: Upper period | AK67: Period type | AL67: day of period type | AM67: row MATCH | AN67: Break date | AO67: Spring date | AP67: Senesce date
C68: =INT($C$29)+2 -> 3 | E68: -1 | F68: =$K68+364*($K68<$AN68) -> 43924 | H68: =COUNT(J68:J77) -> 10 | I68: typ | J68: 0 | K68: =INDEX(Periods!$F$21:$O$30,J68+1,$E68+2) -> 43560 | L68: =IF(K69-K68>0,K69-K68,OFFSET(K69,-i_p6_len,0)+365-K68) -> 40 | M68: 3.5 | N68: 13.3 | O68: 400 | P68: 800 | Q68: 0.5 | R68: 0.54 | S68: {=INDEX([0]!i_pasture_stage_p6z,$J68+1,ROUNDDOWN((ROW($J68)-ROW($J$68))/i_p6_len,0)+1)} -> 1 | T68: 0.3 | U68: 5 | V68: 0.1 | X68: 1 | Y68: 50 | Z68: 50 | AA68: 50 | AB68: 100 | AC68: 400 | AD68: 400 | AE68: 400 | AF68: 400 | AG68: 400 | AK68: =IF($K68<$AN68,"Dry",IF($K68<$AO68,"Early",IF($K68<$AP68,"Late","Dry"))) -> Dry | AL68: =IF($AK68="Early",$F68-$AN68,IF($AK68="Late",$F68-$AO68,$F68-$AP68)) -> 171 | AM68: =1+$J68*($AK68<>$AK67) -> 1 | AN68: =INDEX(i_break_date,$E68+2,1) -> 43600 | AO68: =Periods!$F$24 -> 43684 | AP68: =INDEX(Periods!$F$21:$O$31,INDEX(Annual!EndGS,1,$E68+2)+2,$E68+2) -> 43753
C69: =INT($C$29)+2 -> 3 | E69: -1 | F69: =$K69+364*($K69<$AN69) -> 43600 | J69: 1 | K69: =INDEX(Periods!$F$21:$O$30,J69+1,$E69+2) -> 43600 | L69: =IF(K70-K69>0,K70-K69,OFFSET(K70,-i_p6_len,0)+365-K69) -> 31 | M69: 4 | N69: 13.3 | O69: 125 | P69: 350 | Q69: 0.81 | R69: 0.81 | S69: {=INDEX([0]!i_pasture_stage_p6z,$J69+1,ROUNDDOWN((ROW($J69)-ROW($J$68))/i_p6_len,0)+1)} -> 0 | T69: 0.3 | U69: 5 | V69: 0 | X69: 1 | Y69: 50 | Z69: 50 | AA69: 50 | AB69: 100 | AC69: 150 | AD69: 150 | AE69: 400 | AF69: 400 | AG69: 400 | AK69: =IF($K69<$AN69,"Dry",IF($K69<$AO69,"Early",IF($K69<$AP69,"Late","Dry"))) -> Early | AL69: =IF($AK69="Early",$F69-$AN69,IF($AK69="Late",$F69-$AO69,$F69-$AP69)) -> 0 | AM69: =1+$J69*($AK69<>$AK68) -> 2 | AN69: =INDEX(i_break_date,$E69+2,1) -> 43600 | AO69: =AO68 -> 43684 | AP69: =INDEX(Periods!$F$21:$O$31,INDEX(Annual!EndGS,1,$E69+2)+2,$E69+2) -> 43753
C70: =INT($C$29)+2 -> 3 | E70: -1 | F70: =$K70+364*($K70<$AN70) -> 43631 | J70: 2 | K70: =INDEX(Periods!$F$21:$O$30,J70+1,$E70+2) -> 43631 | L70: =IF(K71-K70>0,K71-K70,OFFSET(K71,-i_p6_len,0)+365-K70) -> 53 | M70: 6 | N70: 13.3 | O70: 450 | P70: 550 | Q70: 0.81 | R70: 0.81 | S70: {=INDEX([0]!i_pasture_stage_p6z,$J70+1,ROUNDDOWN((ROW($J70)-ROW($J$68))/i_p6_len,0)+1)} -> 0.96428571 | T70: 0.3 | U70: 5 | V70: 0 | X70: 1 | Y70: 50 | Z70: 50 | AA70: 50 | AB70: 150 | AC70: 100 | AD70: 150 | AE70: 400 | AF70: 400 | AG70: 400 | AK70: =IF($K70<$AN70,"Dry",IF($K70<$AO70,"Early",IF($K70<$AP70,"Late","Dry"))) -> Early | AL70: =IF($AK70="Early",$F70-$AN70,IF($AK70="Late",$F70-$AO70,$F70-$AP70)) -> 31 | AM70: =1+$J70*($AK70<>$AK69) -> 1 | AN70: =INDEX(i_break_date,$E70+2,1) -> 43600 | AO70: =AO69 -> 43684 | AP70: =INDEX(Periods!$F$21:$O$31,INDEX(Annual!EndGS,1,$E70+2)+2,$E70+2) -> 43753
C71: =INT($C$29)+2 -> 3 | E71: -1 | F71: =$K71+364*($K71<$AN71) -> 43684 | J71: 3 | K71: =INDEX(Periods!$F$21:$O$30,J71+1,$E71+2) -> 43684 | L71: =IF(K72-K71>0,K72-K71,OFFSET(K72,-i_p6_len,0)+365-K71) -> 25 | M71: 6.5 | N71: 13.3 | O71: 550 | P71: 1200 | Q71: 0.81 | R71: 0.81 | S71: {=INDEX([0]!i_pasture_stage_p6z,$J71+1,ROUNDDOWN((ROW($J71)-ROW($J$68))/i_p6_len,0)+1)} -> 1 | T71: 0.3 | U71: 5 | V71: 0 | X71: 1 | Y71: 50 | Z71: 50 | AA71: 50 | AB71: 150 | AC71: 150 | AD71: 100 | AE71: 400 | AF71: 400 | AG71: 400 | AK71: =IF($K71<$AN71,"Dry",IF($K71<$AO71,"Early",IF($K71<$AP71,"Late","Dry"))) -> Late | AL71: =IF($AK71="Early",$F71-$AN71,IF($AK71="Late",$F71-$AO71,$F71-$AP71)) -> 0 | AM71: =1+$J71*($AK71<>$AK70) -> 4 | AN71: =INDEX(i_break_date,$E71+2,1) -> 43600 | AO71: =AO70 -> 43684 | AP71: =INDEX(Periods!$F$21:$O$31,INDEX(Annual!EndGS,1,$E71+2)+2,$E71+2) -> 43753
C72: =INT($C$29)+2 -> 3 | E72: -1 | F72: =$K72+364*($K72<$AN72) -> 43709 | J72: 4 | K72: =INDEX(Periods!$F$21:$O$30,J72+1,$E72+2) -> 43709 | L72: =IF(K73-K72>0,K73-K72,OFFSET(K73,-i_p6_len,0)+365-K72) -> 29 | M72: 9 | N72: 13.3 | O72: 750 | P72: 2250 | Q72: 0.8 | R72: 0.8 | S72: {=INDEX([0]!i_pasture_stage_p6z,$J72+1,ROUNDDOWN((ROW($J72)-ROW($J$68))/i_p6_len,0)+1)} -> 1 | T72: 0.3 | U72: 5 | V72: 0 | X72: 0.75 | Y72: 50 | Z72: 50 | AA72: 50 | AB72: 150 | AC72: 150 | AD72: 150 | AE72: 400 | AF72: 400 | AG72: 400 | AK72: =IF($K72<$AN72,"Dry",IF($K72<$AO72,"Early",IF($K72<$AP72,"Late","Dry"))) -> Late | AL72: =IF($AK72="Early",$F72-$AN72,IF($AK72="Late",$F72-$AO72,$F72-$AP72)) -> 25 | AM72: =1+$J72*($AK72<>$AK71) -> 1 | AN72: =INDEX(i_break_date,$E72+2,1) -> 43600 | AO72: =AO71 -> 43684 | AP72: =INDEX(Periods!$F$21:$O$31,INDEX(Annual!EndGS,1,$E72+2)+2,$E72+2) -> 43753
C73: =INT($C$29)+2 -> 3 | E73: -1 | F73: =$K73+364*($K73<$AN73) -> 43738 | J73: 5 | K73: =INDEX(Periods!$F$21:$O$30,J73+1,$E73+2) -> 43738 | L73: =IF(K74-K73>0,K74-K73,OFFSET(K74,-i_p6_len,0)+365-K73) -> 15 | M73: 8 | N73: 13.3 | O73: 1000 | P73: 3000 | Q73: 0.76 | R73: 0.78 | S73: {=INDEX([0]!i_pasture_stage_p6z,$J73+1,ROUNDDOWN((ROW($J73)-ROW($J$68))/i_p6_len,0)+1)} -> 1 | T73: 0.3 | U73: 5 | V73: 0 | X73: 0.75 | Y73: 50 | Z73: 50 | AA73: 50 | AB73: 150 | AC73: 150 | AD73: 150 | AE73: 400 | AF73: 400 | AG73: 400 | AK73: =IF($K73<$AN73,"Dry",IF($K73<$AO73,"Early",IF($K73<$AP73,"Late","Dry"))) -> Late | AL73: =IF($AK73="Early",$F73-$AN73,IF($AK73="Late",$F73-$AO73,$F73-$AP73)) -> 54 | AM73: =1+$J73*($AK73<>$AK72) -> 1 | AN73: =INDEX(i_break_date,$E73+2,1) -> 43600 | AO73: =AO72 -> 43684 | AP73: =INDEX(Periods!$F$21:$O$31,INDEX(Annual!EndGS,1,$E73+2)+2,$E73+2) -> 43753
C74: =INT($C$29)+2 -> 3 | E74: -1 | F74: =$K74+364*($K74<$AN74) -> 43753 | J74: 6 | K74: =INDEX(Periods!$F$21:$O$30,J74+1,$E74+2) -> 43753 | L74: =IF(K75-K74>0,K75-K74,OFFSET(K75,-i_p6_len,0)+365-K74) -> 41 | M74: 5 | N74: 13.3 | O74: 800 | P74: 3000 | Q74: 0.6075 | R74: 0.7125 | S74: {=INDEX([0]!i_pasture_stage_p6z,$J74+1,ROUNDDOWN((ROW($J74)-ROW($J$68))/i_p6_len,0)+1)} -> 1 | T74: 0.3 | U74: 5 | V74: 0 | X74: 0.4 | Y74: 50 | Z74: 50 | AA74: 50 | AB74: 150 | AC74: 150 | AD74: 150 | AE74: 400 | AF74: 400 | AG74: 400 | AK74: =IF($K74<$AN74,"Dry",IF($K74<$AO74,"Early",IF($K74<$AP74,"Late","Dry"))) -> Dry | AL74: =IF($AK74="Early",$F74-$AN74,IF($AK74="Late",$F74-$AO74,$F74-$AP74)) -> 0 | AM74: =1+$J74*($AK74<>$AK73) -> 7 | AN74: =INDEX(i_break_date,$E74+2,1) -> 43600 | AO74: =AO73 -> 43684 | AP74: =INDEX(Periods!$F$21:$O$31,INDEX(Annual!EndGS,1,$E74+2)+2,$E74+2) -> 43753
C75: =INT($C$29)+2 -> 3 | E75: -1 | F75: =$K75+364*($K75<$AN75) -> 43794 | J75: 7 | K75: =INDEX(Periods!$F$21:$O$30,J75+1,$E75+2) -> 43794 | L75: =IF(K76-K75>0,K76-K75,OFFSET(K76,-i_p6_len,0)+365-K75) -> 37 | M75: 4 | N75: 13.3 | O75: 700 | P75: 2500 | Q75: 0.5575 | R75: 0.6625 | S75: {=INDEX([0]!i_pasture_stage_p6z,$J75+1,ROUNDDOWN((ROW($J75)-ROW($J$68))/i_p6_len,0)+1)} -> 1 | T75: 0.3 | U75: 5 | V75: 0 | X75: 0.33 | Y75: 50 | Z75: 50 | AA75: 50 | AB75: 400 | AC75: 400 | AD75: 400 | AE75: 400 | AF75: 400 | AG75: 400 | AK75: =IF($K75<$AN75,"Dry",IF($K75<$AO75,"Early",IF($K75<$AP75,"Late","Dry"))) -> Dry | AL75: =IF($AK75="Early",$F75-$AN75,IF($AK75="Late",$F75-$AO75,$F75-$AP75)) -> 41 | AM75: =1+$J75*($AK75<>$AK74) -> 1 | AN75: =INDEX(i_break_date,$E75+2,1) -> 43600 | AO75: =AO74 -> 43684 | AP75: =INDEX(Periods!$F$21:$O$31,INDEX(Annual!EndGS,1,$E75+2)+2,$E75+2) -> 43753
C76: =INT($C$29)+2 -> 3 | E76: -1 | F76: =$K76+364*($K76<$AN76) -> 43831 | J76: 8 | K76: =INDEX(Periods!$F$21:$O$30,J76+1,$E76+2) -> 43831 | L76: =IF(K77-K76>0,K77-K76,OFFSET(K77,-i_p6_len,0)+365-K76) -> 45 | M76: 3.5 | N76: 13.3 | O76: 600 | P76: 2000 | Q76: 0.5275 | R76: 0.6125 | S76: {=INDEX([0]!i_pasture_stage_p6z,$J76+1,ROUNDDOWN((ROW($J76)-ROW($J$68))/i_p6_len,0)+1)} -> 1 | T76: 0.3 | U76: 5 | V76: 0.05 | X76: 0.33 | Y76: 50 | Z76: 50 | AA76: 50 | AB76: 400 | AC76: 400 | AD76: 400 | AE76: 400 | AF76: 400 | AG76: 400 | AK76: =IF($K76<$AN76,"Dry",IF($K76<$AO76,"Early",IF($K76<$AP76,"Late","Dry"))) -> Dry | AL76: =IF($AK76="Early",$F76-$AN76,IF($AK76="Late",$F76-$AO76,$F76-$AP76)) -> 78 | AM76: =1+$J76*($AK76<>$AK75) -> 1 | AN76: =INDEX(i_break_date,$E76+2,1) -> 43600 | AO76: =AO75 -> 43684 | AP76: =INDEX(Periods!$F$21:$O$31,INDEX(Annual!EndGS,1,$E76+2)+2,$E76+2) -> 43753
C77: =INT($C$29)+2 -> 3 | E77: -1 | F77: =$K77+364*($K77<$AN77) -> 43876 | J77: 9 | K77: =INDEX(Periods!$F$21:$O$30,J77+1,$E77+2) -> 43876 | L77: =IF(K78-K77>0,K78-K77,OFFSET(K78,-i_p6_len,0)+365-K77) -> 49 | M77: 3.5 | N77: 13.3 | O77: 550 | P77: 1500 | Q77: 0.51 | R77: 0.57 | S77: {=INDEX([0]!i_pasture_stage_p6z,$J77+1,ROUNDDOWN((ROW($J77)-ROW($J$68))/i_p6_len,0)+1)} -> 1 | T77: 0.3 | U77: 5 | V77: 0.1 | X77: 0.33 | Y77: 50 | Z77: 50 | AA77: 50 | AB77: 400 | AC77: 400 | AD77: 400 | AE77: 400 | AF77: 400 | AG77: 400 | AK77: =IF($K77<$AN77,"Dry",IF($K77<$AO77,"Early",IF($K77<$AP77,"Late","Dry"))) -> Dry | AL77: =IF($AK77="Early",$F77-$AN77,IF($AK77="Late",$F77-$AO77,$F77-$AP77)) -> 123 | AM77: =1+$J77*($AK77<>$AK76) -> 1 | AN77: =INDEX(i_break_date,$E77+2,1) -> 43600 | AO77: =AO76 -> 43684 | AP77: =INDEX(Periods!$F$21:$O$31,INDEX(Annual!EndGS,1,$E77+2)+2,$E77+2) -> 43753
C78: =INT($C$29)+2 -> 3 | E78: 0 | F78: =$K78+364*($K78<$AN78) -> 43924 | I78: season0 | J78: 0 | K78: =INDEX(Periods!$F$21:$O$30,J78+1,$E78+2) -> 43560 | L78: =IF(K79-K78>0,K79-K78,OFFSET(K79,-i_p6_len,0)+365-K78) -> 29 | M78: {=INDEX(M$68:M$77,$AI78,1)*(1-$AH78)+INDEX(M$68:M$77,$AJ78,1)*($AH78)} -> 3.5 | N78: {=INDEX(N$68:N$77,$AI78,1)*(1-$AH78)+INDEX(N$68:N$77,$AJ78,1)*($AH78)} -> 13.3 | O78: {=INDEX(O$68:O$77,$AI78,1)*(1-$AH78)+INDEX(O$68:O$77,$AJ78,1)*($AH78)} -> 418.36735 | P78: {=INDEX(P$68:P$77,$AI78,1)*(1-$AH78)+INDEX(P$68:P$77,$AJ78,1)*($AH78)} -> 885.71429 | Q78: {=INDEX(Q$68:Q$77,$AI78,1)*(1-$AH78)+INDEX(Q$68:Q$77,$AJ78,1)*($AH78)} -> 0.50122449 | R78: {=INDEX(R$68:R$77,$AI78,1)*(1-$AH78)+INDEX(R$68:R$77,$AJ78,1)*($AH78)} -> 0.54367347 | S78: {=INDEX([0]!i_pasture_stage_p6z,$J78+1,ROUNDDOWN((ROW($J78)-ROW($J$68))/i_p6_len,0)+1)} -> 1 | T78: {=INDEX(T$68:T$77,$AI78,1)*(1-$AH78)+INDEX(T$68:T$77,$AJ78,1)*($AH78)} -> 0.3 | U78: {=INDEX(U$68:U$77,$AI78,1)*(1-$AH78)+INDEX(U$68:U$77,$AJ78,1)*($AH78)} -> 5 | V78: {=INDEX(V$68:V$77,$AI78,1)*(1-$AH78)+INDEX(V$68:V$77,$AJ78,1)*($AH78)} -> 0.1 | X78: {=INDEX(X$68:X$77,$AI78,1)*(1-$AH78)+INDEX(X$68:X$77,$AJ78,1)*($AH78)} -> 0.91795918 | Y78: {=INDEX(Y$68:Y$77,$AI78,1)*(1-$AH78)+INDEX(Y$68:Y$77,$AJ78,1)*($AH78)} -> 50 | Z78: {=INDEX(Z$68:Z$77,$AI78,1)*(1-$AH78)+INDEX(Z$68:Z$77,$AJ78,1)*($AH78)} -> 50 | AA78: {=INDEX(AA$68:AA$77,$AI78,1)*(1-$AH78)+INDEX(AA$68:AA$77,$AJ78,1)*($AH78)} -> 50 | AB78: {=INDEX(AB$68:AB$77,$AI78,1)*(1-$AH78)+INDEX(AB$68:AB$77,$AJ78,1)*($AH78)} -> 136.73469 | AC78: {=INDEX(AC$68:AC$77,$AI78,1)*(1-$AH78)+INDEX(AC$68:AC$77,$AJ78,1)*($AH78)} -> 400 | AD78: {=INDEX(AD$68:AD$77,$AI78,1)*(1-$AH78)+INDEX(AD$68:AD$77,$AJ78,1)*($AH78)} -> 400 | AE78: {=INDEX(AE$68:AE$77,$AI78,1)*(1-$AH78)+INDEX(AE$68:AE$77,$AJ78,1)*($AH78)} -> 400 | ... AG78: {=INDEX(AG$68:AG$77,$AI78,1)*(1-$AH78)+INDEX(AG$68:AG$77,$AJ78,1)*($AH78)} -> 400 | AH78: =($AL78-INDEX($AL$68:$AL$77,$AI78,1))/INDEX($L$68:$L$77,$AI78,1) -> 0.87755102 | AI78: =MOD(SUMIFS($AM$68:$AM$77,$AK$68:$AK$77,$AK78,$AL$68:$AL$77,"<="&$AL78)-1,$AJ$65)+1 -> 10 | AJ78: =IF(OR(INDEX($AK$68:$AK$77,$AI78,1)=INDEX($AK$68:$AK$77,MOD($AI78,AJ$65)+1,1),INDEX($AK$68:$AK$77,$AI78,1)="Early"),MOD($AI78,AJ$65)+1,$AI78) -> 1 | AK78: =IF($K78<$AN78,"Dry",IF($K78<$AO78,"Early",IF($K78<$AP78,"Late","Dry"))) -> Dry | AL78: =IF($AK78="Early",$F78-$AN78,IF($AK78="Late",$F78-$AO78,$F78-$AP78)) -> 166 | AN78: =INDEX(i_break_date,$E78+2,1) -> 43589 | AO78: =AO77 -> 43684 | AP78: =INDEX(Periods!$F$21:$O$31,INDEX(Annual!EndGS,1,$E78+2)+2,$E78+2) -> 43758
C79: =INT($C$29)+3 -> 4 | E79: 0 | F79: =$K79+364*($K79<$AN79) -> 43589 | J79: 1 | K79: =INDEX(Periods!$F$21:$O$30,J79+1,$E79+2) -> 43589 | L79: =IF(K80-K79>0,K80-K79,OFFSET(K80,-i_p6_len,0)+365-K79) -> 42 | M79: {=INDEX(M$68:M$77,$AI79,1)*(1-$AH79)+INDEX(M$68:M$77,$AJ79,1)*($AH79)} -> 4 | N79: {=INDEX(N$68:N$77,$AI79,1)*(1-$AH79)+INDEX(N$68:N$77,$AJ79,1)*($AH79)} -> 13.3 | O79: {=INDEX(O$68:O$77,$AI79,1)*(1-$AH79)+INDEX(O$68:O$77,$AJ79,1)*($AH79)} -> 125 | P79: {=INDEX(P$68:P$77,$AI79,1)*(1-$AH79)+INDEX(P$68:P$77,$AJ79,1)*($AH79)} -> 350 | Q79: {=INDEX(Q$68:Q$77,$AI79,1)*(1-$AH79)+INDEX(Q$68:Q$77,$AJ79,1)*($AH79)} -> 0.81 | R79: {=INDEX(R$68:R$77,$AI79,1)*(1-$AH79)+INDEX(R$68:R$77,$AJ79,1)*($AH79)} -> 0.81 | S79: {=INDEX([0]!i_pasture_stage_p6z,$J79+1,ROUNDDOWN((ROW($J79)-ROW($J$68))/i_p6_len,0)+1)} -> 0.28571429 | T79: {=INDEX(T$68:T$77,$AI79,1)*(1-$AH79)+INDEX(T$68:T$77,$AJ79,1)*($AH79)} -> 0.3 | U79: {=INDEX(U$68:U$77,$AI79,1)*(1-$AH79)+INDEX(U$68:U$77,$AJ79,1)*($AH79)} -> 5 | V79: {=INDEX(V$68:V$77,$AI79,1)*(1-$AH79)+INDEX(V$68:V$77,$AJ79,1)*($AH79)} -> 0 | X79: {=INDEX(X$68:X$77,$AI79,1)*(1-$AH79)+INDEX(X$68:X$77,$AJ79,1)*($AH79)} -> 1 | Y79: {=INDEX(Y$68:Y$77,$AI79,1)*(1-$AH79)+INDEX(Y$68:Y$77,$AJ79,1)*($AH79)} -> 50 | Z79: {=INDEX(Z$68:Z$77,$AI79,1)*(1-$AH79)+INDEX(Z$68:Z$77,$AJ79,1)*($AH79)} -> 50 | AA79: {=INDEX(AA$68:AA$77,$AI79,1)*(1-$AH79)+INDEX(AA$68:AA$77,$AJ79,1)*($AH79)} -> 50 | AB79: {=INDEX(AB$68:AB$77,$AI79,1)*(1-$AH79)+INDEX(AB$68:AB$77,$AJ79,1)*($AH79)} -> 100 | AC79: {=INDEX(AC$68:AC$77,$AI79,1)*(1-$AH79)+INDEX(AC$68:AC$77,$AJ79,1)*($AH79)} -> 150 | AD79: {=INDEX(AD$68:AD$77,$AI79,1)*(1-$AH79)+INDEX(AD$68:AD$77,$AJ79,1)*($AH79)} -> 150 | AE79: {=INDEX(AE$68:AE$77,$AI79,1)*(1-$AH79)+INDEX(AE$68:AE$77,$AJ79,1)*($AH79)} -> 400 | ... AG79: {=INDEX(AG$68:AG$77,$AI79,1)*(1-$AH79)+INDEX(AG$68:AG$77,$AJ79,1)*($AH79)} -> 400 | AH79: =($AL79-INDEX($AL$68:$AL$77,$AI79,1))/INDEX($L$68:$L$77,$AI79,1) -> 0 | AI79: =MOD(SUMIFS($AM$68:$AM$77,$AK$68:$AK$77,$AK79,$AL$68:$AL$77,"<="&$AL79)-1,$AJ$65)+1 -> 2 | AJ79: =IF(OR(INDEX($AK$68:$AK$77,$AI79,1)=INDEX($AK$68:$AK$77,MOD($AI79,AJ$65)+1,1),INDEX($AK$68:$AK$77,$AI79,1)="Early"),MOD($AI79,AJ$65)+1,$AI79) -> 3 | AK79: =IF($K79<$AN79,"Dry",IF($K79<$AO79,"Early",IF($K79<$AP79,"Late","Dry"))) -> Early | AL79: =IF($AK79="Early",$F79-$AN79,IF($AK79="Late",$F79-$AO79,$F79-$AP79)) -> 0 | AN79: =INDEX(i_break_date,$E79+2,1) -> 43589 | AO79: =AO78 -> 43684 | AP79: =INDEX(Periods!$F$21:$O$31,INDEX(Annual!EndGS,1,$E79+2)+2,$E79+2) -> 43758
C80: =INT($C$29)+3 -> 4 | E80: 0 | F80: =$K80+364*($K80<$AN80) -> 43631 | J80: 2 | K80: =INDEX(Periods!$F$21:$O$30,J80+1,$E80+2) -> 43631 | L80: =IF(K81-K80>0,K81-K80,OFFSET(K81,-i_p6_len,0)+365-K80) -> 53 | M80: {=INDEX(M$68:M$77,$AI80,1)*(1-$AH80)+INDEX(M$68:M$77,$AJ80,1)*($AH80)} -> 6.1037736 | N80: {=INDEX(N$68:N$77,$AI80,1)*(1-$AH80)+INDEX(N$68:N$77,$AJ80,1)*($AH80)} -> 13.3 | O80: {=INDEX(O$68:O$77,$AI80,1)*(1-$AH80)+INDEX(O$68:O$77,$AJ80,1)*($AH80)} -> 470.75472 | P80: {=INDEX(P$68:P$77,$AI80,1)*(1-$AH80)+INDEX(P$68:P$77,$AJ80,1)*($AH80)} -> 684.90566 | Q80: {=INDEX(Q$68:Q$77,$AI80,1)*(1-$AH80)+INDEX(Q$68:Q$77,$AJ80,1)*($AH80)} -> 0.81 | R80: {=INDEX(R$68:R$77,$AI80,1)*(1-$AH80)+INDEX(R$68:R$77,$AJ80,1)*($AH80)} -> 0.81 | S80: {=INDEX([0]!i_pasture_stage_p6z,$J80+1,ROUNDDOWN((ROW($J80)-ROW($J$68))/i_p6_len,0)+1)} -> 1 | T80: {=INDEX(T$68:T$77,$AI80,1)*(1-$AH80)+INDEX(T$68:T$77,$AJ80,1)*($AH80)} -> 0.3 | U80: {=INDEX(U$68:U$77,$AI80,1)*(1-$AH80)+INDEX(U$68:U$77,$AJ80,1)*($AH80)} -> 5 | V80: {=INDEX(V$68:V$77,$AI80,1)*(1-$AH80)+INDEX(V$68:V$77,$AJ80,1)*($AH80)} -> 0 | X80: {=INDEX(X$68:X$77,$AI80,1)*(1-$AH80)+INDEX(X$68:X$77,$AJ80,1)*($AH80)} -> 1 | Y80: {=INDEX(Y$68:Y$77,$AI80,1)*(1-$AH80)+INDEX(Y$68:Y$77,$AJ80,1)*($AH80)} -> 50 | Z80: {=INDEX(Z$68:Z$77,$AI80,1)*(1-$AH80)+INDEX(Z$68:Z$77,$AJ80,1)*($AH80)} -> 50 | AA80: {=INDEX(AA$68:AA$77,$AI80,1)*(1-$AH80)+INDEX(AA$68:AA$77,$AJ80,1)*($AH80)} -> 50 | AB80: {=INDEX(AB$68:AB$77,$AI80,1)*(1-$AH80)+INDEX(AB$68:AB$77,$AJ80,1)*($AH80)} -> 150 | AC80: {=INDEX(AC$68:AC$77,$AI80,1)*(1-$AH80)+INDEX(AC$68:AC$77,$AJ80,1)*($AH80)} -> 110.37736 | AD80: {=INDEX(AD$68:AD$77,$AI80,1)*(1-$AH80)+INDEX(AD$68:AD$77,$AJ80,1)*($AH80)} -> 139.62264 | AE80: {=INDEX(AE$68:AE$77,$AI80,1)*(1-$AH80)+INDEX(AE$68:AE$77,$AJ80,1)*($AH80)} -> 400 | ... AG80: {=INDEX(AG$68:AG$77,$AI80,1)*(1-$AH80)+INDEX(AG$68:AG$77,$AJ80,1)*($AH80)} -> 400 | AH80: =($AL80-INDEX($AL$68:$AL$77,$AI80,1))/INDEX($L$68:$L$77,$AI80,1) -> 0.20754717 | AI80: =MOD(SUMIFS($AM$68:$AM$77,$AK$68:$AK$77,$AK80,$AL$68:$AL$77,"<="&$AL80)-1,$AJ$65)+1 -> 3 | AJ80: =IF(OR(INDEX($AK$68:$AK$77,$AI80,1)=INDEX($AK$68:$AK$77,MOD($AI80,AJ$65)+1,1),INDEX($AK$68:$AK$77,$AI80,1)="Early"),MOD($AI80,AJ$65)+1,$AI80) -> 4 | AK80: =IF($K80<$AN80,"Dry",IF($K80<$AO80,"Early",IF($K80<$AP80,"Late","Dry"))) -> Early | AL80: =IF($AK80="Early",$F80-$AN80,IF($AK80="Late",$F80-$AO80,$F80-$AP80)) -> 42 | AN80: =INDEX(i_break_date,$E80+2,1) -> 43589 | AO80: =AO79 -> 43684 | AP80: =INDEX(Periods!$F$21:$O$31,INDEX(Annual!EndGS,1,$E80+2)+2,$E80+2) -> 43758
C81: =INT($C$29)+3 -> 4 | E81: 0 | F81: =$K81+364*($K81<$AN81) -> 43684 | J81: 3 | K81: =INDEX(Periods!$F$21:$O$30,J81+1,$E81+2) -> 43684 | L81: =IF(K82-K81>0,K82-K81,OFFSET(K82,-i_p6_len,0)+365-K81) -> 25 | M81: {=INDEX(M$68:M$77,$AI81,1)*(1-$AH81)+INDEX(M$68:M$77,$AJ81,1)*($AH81)} -> 6.5 | N81: {=INDEX(N$68:N$77,$AI81,1)*(1-$AH81)+INDEX(N$68:N$77,$AJ81,1)*($AH81)} -> 13.3 | O81: {=INDEX(O$68:O$77,$AI81,1)*(1-$AH81)+INDEX(O$68:O$77,$AJ81,1)*($AH81)} -> 550 | P81: {=INDEX(P$68:P$77,$AI81,1)*(1-$AH81)+INDEX(P$68:P$77,$AJ81,1)*($AH81)} -> 1200 | Q81: {=INDEX(Q$68:Q$77,$AI81,1)*(1-$AH81)+INDEX(Q$68:Q$77,$AJ81,1)*($AH81)} -> 0.81 | R81: {=INDEX(R$68:R$77,$AI81,1)*(1-$AH81)+INDEX(R$68:R$77,$AJ81,1)*($AH81)} -> 0.81 | S81: {=INDEX([0]!i_pasture_stage_p6z,$J81+1,ROUNDDOWN((ROW($J81)-ROW($J$68))/i_p6_len,0)+1)} -> 1 | T81: {=INDEX(T$68:T$77,$AI81,1)*(1-$AH81)+INDEX(T$68:T$77,$AJ81,1)*($AH81)} -> 0.3 | U81: {=INDEX(U$68:U$77,$AI81,1)*(1-$AH81)+INDEX(U$68:U$77,$AJ81,1)*($AH81)} -> 5 | V81: {=INDEX(V$68:V$77,$AI81,1)*(1-$AH81)+INDEX(V$68:V$77,$AJ81,1)*($AH81)} -> 0 | X81: {=INDEX(X$68:X$77,$AI81,1)*(1-$AH81)+INDEX(X$68:X$77,$AJ81,1)*($AH81)} -> 1 | Y81: {=INDEX(Y$68:Y$77,$AI81,1)*(1-$AH81)+INDEX(Y$68:Y$77,$AJ81,1)*($AH81)} -> 50 | Z81: {=INDEX(Z$68:Z$77,$AI81,1)*(1-$AH81)+INDEX(Z$68:Z$77,$AJ81,1)*($AH81)} -> 50 | AA81: {=INDEX(AA$68:AA$77,$AI81,1)*(1-$AH81)+INDEX(AA$68:AA$77,$AJ81,1)*($AH81)} -> 50 | AB81: {=INDEX(AB$68:AB$77,$AI81,1)*(1-$AH81)+INDEX(AB$68:AB$77,$AJ81,1)*($AH81)} -> 150 | AC81: {=INDEX(AC$68:AC$77,$AI81,1)*(1-$AH81)+INDEX(AC$68:AC$77,$AJ81,1)*($AH81)} -> 150 | AD81: {=INDEX(AD$68:AD$77,$AI81,1)*(1-$AH81)+INDEX(AD$68:AD$77,$AJ81,1)*($AH81)} -> 100 | AE81: {=INDEX(AE$68:AE$77,$AI81,1)*(1-$AH81)+INDEX(AE$68:AE$77,$AJ81,1)*($AH81)} -> 400 | ... AG81: {=INDEX(AG$68:AG$77,$AI81,1)*(1-$AH81)+INDEX(AG$68:AG$77,$AJ81,1)*($AH81)} -> 400 | AH81: =($AL81-INDEX($AL$68:$AL$77,$AI81,1))/INDEX($L$68:$L$77,$AI81,1) -> 0 | AI81: =MOD(SUMIFS($AM$68:$AM$77,$AK$68:$AK$77,$AK81,$AL$68:$AL$77,"<="&$AL81)-1,$AJ$65)+1 -> 4 | AJ81: =IF(OR(INDEX($AK$68:$AK$77,$AI81,1)=INDEX($AK$68:$AK$77,MOD($AI81,AJ$65)+1,1),INDEX($AK$68:$AK$77,$AI81,1)="Early"),MOD($AI81,AJ$65)+1,$AI81) -> 5 | AK81: =IF($K81<$AN81,"Dry",IF($K81<$AO81,"Early",IF($K81<$AP81,"Late","Dry"))) -> Late | AL81: =IF($AK81="Early",$F81-$AN81,IF($AK81="Late",$F81-$AO81,$F81-$AP81)) -> 0 | AN81: =INDEX(i_break_date,$E81+2,1) -> 43589 | AO81: =AO80 -> 43684 | AP81: =INDEX(Periods!$F$21:$O$31,INDEX(Annual!EndGS,1,$E81+2)+2,$E81+2) -> 43758
C82: =INT($C$29)+3 -> 4 | E82: 0 | F82: =$K82+364*($K82<$AN82) -> 43709 | J82: 4 | K82: =INDEX(Periods!$F$21:$O$30,J82+1,$E82+2) -> 43709 | L82: =IF(K83-K82>0,K83-K82,OFFSET(K83,-i_p6_len,0)+365-K82) -> 29 | M82: {=INDEX(M$68:M$77,$AI82,1)*(1-$AH82)+INDEX(M$68:M$77,$AJ82,1)*($AH82)} -> 9 | N82: {=INDEX(N$68:N$77,$AI82,1)*(1-$AH82)+INDEX(N$68:N$77,$AJ82,1)*($AH82)} -> 13.3 | O82: {=INDEX(O$68:O$77,$AI82,1)*(1-$AH82)+INDEX(O$68:O$77,$AJ82,1)*($AH82)} -> 750 | P82: {=INDEX(P$68:P$77,$AI82,1)*(1-$AH82)+INDEX(P$68:P$77,$AJ82,1)*($AH82)} -> 2250 | Q82: {=INDEX(Q$68:Q$77,$AI82,1)*(1-$AH82)+INDEX(Q$68:Q$77,$AJ82,1)*($AH82)} -> 0.8 | R82: {=INDEX(R$68:R$77,$AI82,1)*(1-$AH82)+INDEX(R$68:R$77,$AJ82,1)*($AH82)} -> 0.8 | S82: {=INDEX([0]!i_pasture_stage_p6z,$J82+1,ROUNDDOWN((ROW($J82)-ROW($J$68))/i_p6_len,0)+1)} -> 1 | T82: {=INDEX(T$68:T$77,$AI82,1)*(1-$AH82)+INDEX(T$68:T$77,$AJ82,1)*($AH82)} -> 0.3 | U82: {=INDEX(U$68:U$77,$AI82,1)*(1-$AH82)+INDEX(U$68:U$77,$AJ82,1)*($AH82)} -> 5 | V82: {=INDEX(V$68:V$77,$AI82,1)*(1-$AH82)+INDEX(V$68:V$77,$AJ82,1)*($AH82)} -> 0 | X82: {=INDEX(X$68:X$77,$AI82,1)*(1-$AH82)+INDEX(X$68:X$77,$AJ82,1)*($AH82)} -> 0.75 | Y82: {=INDEX(Y$68:Y$77,$AI82,1)*(1-$AH82)+INDEX(Y$68:Y$77,$AJ82,1)*($AH82)} -> 50 | Z82: {=INDEX(Z$68:Z$77,$AI82,1)*(1-$AH82)+INDEX(Z$68:Z$77,$AJ82,1)*($AH82)} -> 50 | AA82: {=INDEX(AA$68:AA$77,$AI82,1)*(1-$AH82)+INDEX(AA$68:AA$77,$AJ82,1)*($AH82)} -> 50 | AB82: {=INDEX(AB$68:AB$77,$AI82,1)*(1-$AH82)+INDEX(AB$68:AB$77,$AJ82,1)*($AH82)} -> 150 | AC82: {=INDEX(AC$68:AC$77,$AI82,1)*(1-$AH82)+INDEX(AC$68:AC$77,$AJ82,1)*($AH82)} -> 150 | AD82: {=INDEX(AD$68:AD$77,$AI82,1)*(1-$AH82)+INDEX(AD$68:AD$77,$AJ82,1)*($AH82)} -> 150 | AE82: {=INDEX(AE$68:AE$77,$AI82,1)*(1-$AH82)+INDEX(AE$68:AE$77,$AJ82,1)*($AH82)} -> 400 | ... AG82: {=INDEX(AG$68:AG$77,$AI82,1)*(1-$AH82)+INDEX(AG$68:AG$77,$AJ82,1)*($AH82)} -> 400 | AH82: =($AL82-INDEX($AL$68:$AL$77,$AI82,1))/INDEX($L$68:$L$77,$AI82,1) -> 0 | AI82: =MOD(SUMIFS($AM$68:$AM$77,$AK$68:$AK$77,$AK82,$AL$68:$AL$77,"<="&$AL82)-1,$AJ$65)+1 -> 5 | AJ82: =IF(OR(INDEX($AK$68:$AK$77,$AI82,1)=INDEX($AK$68:$AK$77,MOD($AI82,AJ$65)+1,1),INDEX($AK$68:$AK$77,$AI82,1)="Early"),MOD($AI82,AJ$65)+1,$AI82) -> 6 | AK82: =IF($K82<$AN82,"Dry",IF($K82<$AO82,"Early",IF($K82<$AP82,"Late","Dry"))) -> Late | AL82: =IF($AK82="Early",$F82-$AN82,IF($AK82="Late",$F82-$AO82,$F82-$AP82)) -> 25 | AN82: =INDEX(i_break_date,$E82+2,1) -> 43589 | AO82: =AO81 -> 43684 | AP82: =INDEX(Periods!$F$21:$O$31,INDEX(Annual!EndGS,1,$E82+2)+2,$E82+2) -> 43758
C83: =INT($C$29)+3 -> 4 | E83: 0 | F83: =$K83+364*($K83<$AN83) -> 43738 | J83: 5 | K83: =INDEX(Periods!$F$21:$O$30,J83+1,$E83+2) -> 43738 | L83: =IF(K84-K83>0,K84-K83,OFFSET(K84,-i_p6_len,0)+365-K83) -> 20 | M83: {=INDEX(M$68:M$77,$AI83,1)*(1-$AH83)+INDEX(M$68:M$77,$AJ83,1)*($AH83)} -> 8 | N83: {=INDEX(N$68:N$77,$AI83,1)*(1-$AH83)+INDEX(N$68:N$77,$AJ83,1)*($AH83)} -> 13.3 | O83: {=INDEX(O$68:O$77,$AI83,1)*(1-$AH83)+INDEX(O$68:O$77,$AJ83,1)*($AH83)} -> 1000 | P83: {=INDEX(P$68:P$77,$AI83,1)*(1-$AH83)+INDEX(P$68:P$77,$AJ83,1)*($AH83)} -> 3000 | Q83: {=INDEX(Q$68:Q$77,$AI83,1)*(1-$AH83)+INDEX(Q$68:Q$77,$AJ83,1)*($AH83)} -> 0.76 | R83: {=INDEX(R$68:R$77,$AI83,1)*(1-$AH83)+INDEX(R$68:R$77,$AJ83,1)*($AH83)} -> 0.78 | S83: {=INDEX([0]!i_pasture_stage_p6z,$J83+1,ROUNDDOWN((ROW($J83)-ROW($J$68))/i_p6_len,0)+1)} -> 1 | T83: {=INDEX(T$68:T$77,$AI83,1)*(1-$AH83)+INDEX(T$68:T$77,$AJ83,1)*($AH83)} -> 0.3 | U83: {=INDEX(U$68:U$77,$AI83,1)*(1-$AH83)+INDEX(U$68:U$77,$AJ83,1)*($AH83)} -> 5 | V83: {=INDEX(V$68:V$77,$AI83,1)*(1-$AH83)+INDEX(V$68:V$77,$AJ83,1)*($AH83)} -> 0 | X83: {=INDEX(X$68:X$77,$AI83,1)*(1-$AH83)+INDEX(X$68:X$77,$AJ83,1)*($AH83)} -> 0.75 | Y83: {=INDEX(Y$68:Y$77,$AI83,1)*(1-$AH83)+INDEX(Y$68:Y$77,$AJ83,1)*($AH83)} -> 50 | Z83: {=INDEX(Z$68:Z$77,$AI83,1)*(1-$AH83)+INDEX(Z$68:Z$77,$AJ83,1)*($AH83)} -> 50 | AA83: {=INDEX(AA$68:AA$77,$AI83,1)*(1-$AH83)+INDEX(AA$68:AA$77,$AJ83,1)*($AH83)} -> 50 | AB83: {=INDEX(AB$68:AB$77,$AI83,1)*(1-$AH83)+INDEX(AB$68:AB$77,$AJ83,1)*($AH83)} -> 150 | AC83: {=INDEX(AC$68:AC$77,$AI83,1)*(1-$AH83)+INDEX(AC$68:AC$77,$AJ83,1)*($AH83)} -> 150 | AD83: {=INDEX(AD$68:AD$77,$AI83,1)*(1-$AH83)+INDEX(AD$68:AD$77,$AJ83,1)*($AH83)} -> 150 | AE83: {=INDEX(AE$68:AE$77,$AI83,1)*(1-$AH83)+INDEX(AE$68:AE$77,$AJ83,1)*($AH83)} -> 400 | ... AG83: {=INDEX(AG$68:AG$77,$AI83,1)*(1-$AH83)+INDEX(AG$68:AG$77,$AJ83,1)*($AH83)} -> 400 | AH83: =($AL83-INDEX($AL$68:$AL$77,$AI83,1))/INDEX($L$68:$L$77,$AI83,1) -> 0 | AI83: =MOD(SUMIFS($AM$68:$AM$77,$AK$68:$AK$77,$AK83,$AL$68:$AL$77,"<="&$AL83)-1,$AJ$65)+1 -> 6 | AJ83: =IF(OR(INDEX($AK$68:$AK$77,$AI83,1)=INDEX($AK$68:$AK$77,MOD($AI83,AJ$65)+1,1),INDEX($AK$68:$AK$77,$AI83,1)="Early"),MOD($AI83,AJ$65)+1,$AI83) -> 6 | AK83: =IF($K83<$AN83,"Dry",IF($K83<$AO83,"Early",IF($K83<$AP83,"Late","Dry"))) -> Late | AL83: =IF($AK83="Early",$F83-$AN83,IF($AK83="Late",$F83-$AO83,$F83-$AP83)) -> 54 | AN83: =INDEX(i_break_date,$E83+2,1) -> 43589 | AO83: =AO82 -> 43684 | AP83: =INDEX(Periods!$F$21:$O$31,INDEX(Annual!EndGS,1,$E83+2)+2,$E83+2) -> 43758
C84: =INT($C$29)+3 -> 4 | E84: 0 | F84: =$K84+364*($K84<$AN84) -> 43758 | J84: 6 | K84: =INDEX(Periods!$F$21:$O$30,J84+1,$E84+2) -> 43758 | L84: =IF(K85-K84>0,K85-K84,OFFSET(K85,-i_p6_len,0)+365-K84) -> 36 | M84: {=INDEX(M$68:M$77,$AI84,1)*(1-$AH84)+INDEX(M$68:M$77,$AJ84,1)*($AH84)} -> 5 | N84: {=INDEX(N$68:N$77,$AI84,1)*(1-$AH84)+INDEX(N$68:N$77,$AJ84,1)*($AH84)} -> 13.3 | O84: {=INDEX(O$68:O$77,$AI84,1)*(1-$AH84)+INDEX(O$68:O$77,$AJ84,1)*($AH84)} -> 800 | P84: {=INDEX(P$68:P$77,$AI84,1)*(1-$AH84)+INDEX(P$68:P$77,$AJ84,1)*($AH84)} -> 3000 | Q84: {=INDEX(Q$68:Q$77,$AI84,1)*(1-$AH84)+INDEX(Q$68:Q$77,$AJ84,1)*($AH84)} -> 0.6075 | R84: {=INDEX(R$68:R$77,$AI84,1)*(1-$AH84)+INDEX(R$68:R$77,$AJ84,1)*($AH84)} -> 0.7125 | S84: {=INDEX([0]!i_pasture_stage_p6z,$J84+1,ROUNDDOWN((ROW($J84)-ROW($J$68))/i_p6_len,0)+1)} -> 1 | T84: {=INDEX(T$68:T$77,$AI84,1)*(1-$AH84)+INDEX(T$68:T$77,$AJ84,1)*($AH84)} -> 0.3 | U84: {=INDEX(U$68:U$77,$AI84,1)*(1-$AH84)+INDEX(U$68:U$77,$AJ84,1)*($AH84)} -> 5 | V84: {=INDEX(V$68:V$77,$AI84,1)*(1-$AH84)+INDEX(V$68:V$77,$AJ84,1)*($AH84)} -> 0 | X84: {=INDEX(X$68:X$77,$AI84,1)*(1-$AH84)+INDEX(X$68:X$77,$AJ84,1)*($AH84)} -> 0.4 | Y84: {=INDEX(Y$68:Y$77,$AI84,1)*(1-$AH84)+INDEX(Y$68:Y$77,$AJ84,1)*($AH84)} -> 50 | Z84: {=INDEX(Z$68:Z$77,$AI84,1)*(1-$AH84)+INDEX(Z$68:Z$77,$AJ84,1)*($AH84)} -> 50 | AA84: {=INDEX(AA$68:AA$77,$AI84,1)*(1-$AH84)+INDEX(AA$68:AA$77,$AJ84,1)*($AH84)} -> 50 | AB84: {=INDEX(AB$68:AB$77,$AI84,1)*(1-$AH84)+INDEX(AB$68:AB$77,$AJ84,1)*($AH84)} -> 150 | AC84: {=INDEX(AC$68:AC$77,$AI84,1)*(1-$AH84)+INDEX(AC$68:AC$77,$AJ84,1)*($AH84)} -> 150 | AD84: {=INDEX(AD$68:AD$77,$AI84,1)*(1-$AH84)+INDEX(AD$68:AD$77,$AJ84,1)*($AH84)} -> 150 | AE84: {=INDEX(AE$68:AE$77,$AI84,1)*(1-$AH84)+INDEX(AE$68:AE$77,$AJ84,1)*($AH84)} -> 400 | ... AG84: {=INDEX(AG$68:AG$77,$AI84,1)*(1-$AH84)+INDEX(AG$68:AG$77,$AJ84,1)*($AH84)} -> 400 | AH84: =($AL84-INDEX($AL$68:$AL$77,$AI84,1))/INDEX($L$68:$L$77,$AI84,1) -> 0 | AI84: =MOD(SUMIFS($AM$68:$AM$77,$AK$68:$AK$77,$AK84,$AL$68:$AL$77,"<="&$AL84)-1,$AJ$65)+1 -> 7 | AJ84: =IF(OR(INDEX($AK$68:$AK$77,$AI84,1)=INDEX($AK$68:$AK$77,MOD($AI84,AJ$65)+1,1),INDEX($AK$68:$AK$77,$AI84,1)="Early"),MOD($AI84,AJ$65)+1,$AI84) -> 8 | AK84: =IF($K84<$AN84,"Dry",IF($K84<$AO84,"Early",IF($K84<$AP84,"Late","Dry"))) -> Dry | AL84: =IF($AK84="Early",$F84-$AN84,IF($AK84="Late",$F84-$AO84,$F84-$AP84)) -> 0 | AN84: =INDEX(i_break_date,$E84+2,1) -> 43589 | AO84: =AO83 -> 43684 | AP84: =INDEX(Periods!$F$21:$O$31,INDEX(Annual!EndGS,1,$E84+2)+2,$E84+2) -> 43758
C85: =INT($C$29)+3 -> 4 | E85: 0 | F85: =$K85+364*($K85<$AN85) -> 43794 | J85: 7 | K85: =INDEX(Periods!$F$21:$O$30,J85+1,$E85+2) -> 43794 | L85: =IF(K86-K85>0,K86-K85,OFFSET(K86,-i_p6_len,0)+365-K85) -> 37 | M85: {=INDEX(M$68:M$77,$AI85,1)*(1-$AH85)+INDEX(M$68:M$77,$AJ85,1)*($AH85)} -> 4.1219512 | N85: {=INDEX(N$68:N$77,$AI85,1)*(1-$AH85)+INDEX(N$68:N$77,$AJ85,1)*($AH85)} -> 13.3 | O85: {=INDEX(O$68:O$77,$AI85,1)*(1-$AH85)+INDEX(O$68:O$77,$AJ85,1)*($AH85)} -> 712.19512 | P85: {=INDEX(P$68:P$77,$AI85,1)*(1-$AH85)+INDEX(P$68:P$77,$AJ85,1)*($AH85)} -> 2560.9756 | Q85: {=INDEX(Q$68:Q$77,$AI85,1)*(1-$AH85)+INDEX(Q$68:Q$77,$AJ85,1)*($AH85)} -> 0.56359756 | R85: {=INDEX(R$68:R$77,$AI85,1)*(1-$AH85)+INDEX(R$68:R$77,$AJ85,1)*($AH85)} -> 0.66859756 | S85: {=INDEX([0]!i_pasture_stage_p6z,$J85+1,ROUNDDOWN((ROW($J85)-ROW($J$68))/i_p6_len,0)+1)} -> 1 | T85: {=INDEX(T$68:T$77,$AI85,1)*(1-$AH85)+INDEX(T$68:T$77,$AJ85,1)*($AH85)} -> 0.3 | U85: {=INDEX(U$68:U$77,$AI85,1)*(1-$AH85)+INDEX(U$68:U$77,$AJ85,1)*($AH85)} -> 5 | V85: {=INDEX(V$68:V$77,$AI85,1)*(1-$AH85)+INDEX(V$68:V$77,$AJ85,1)*($AH85)} -> 0 | X85: {=INDEX(X$68:X$77,$AI85,1)*(1-$AH85)+INDEX(X$68:X$77,$AJ85,1)*($AH85)} -> 0.33853659 | Y85: {=INDEX(Y$68:Y$77,$AI85,1)*(1-$AH85)+INDEX(Y$68:Y$77,$AJ85,1)*($AH85)} -> 50 | Z85: {=INDEX(Z$68:Z$77,$AI85,1)*(1-$AH85)+INDEX(Z$68:Z$77,$AJ85,1)*($AH85)} -> 50 | AA85: {=INDEX(AA$68:AA$77,$AI85,1)*(1-$AH85)+INDEX(AA$68:AA$77,$AJ85,1)*($AH85)} -> 50 | AB85: {=INDEX(AB$68:AB$77,$AI85,1)*(1-$AH85)+INDEX(AB$68:AB$77,$AJ85,1)*($AH85)} -> 369.5122 | AC85: {=INDEX(AC$68:AC$77,$AI85,1)*(1-$AH85)+INDEX(AC$68:AC$77,$AJ85,1)*($AH85)} -> 369.5122 | AD85: {=INDEX(AD$68:AD$77,$AI85,1)*(1-$AH85)+INDEX(AD$68:AD$77,$AJ85,1)*($AH85)} -> 369.5122 | AE85: {=INDEX(AE$68:AE$77,$AI85,1)*(1-$AH85)+INDEX(AE$68:AE$77,$AJ85,1)*($AH85)} -> 400 | ... AG85: {=INDEX(AG$68:AG$77,$AI85,1)*(1-$AH85)+INDEX(AG$68:AG$77,$AJ85,1)*($AH85)} -> 400 | AH85: =($AL85-INDEX($AL$68:$AL$77,$AI85,1))/INDEX($L$68:$L$77,$AI85,1) -> 0.87804878 | AI85: =MOD(SUMIFS($AM$68:$AM$77,$AK$68:$AK$77,$AK85,$AL$68:$AL$77,"<="&$AL85)-1,$AJ$65)+1 -> 7 | AJ85: =IF(OR(INDEX($AK$68:$AK$77,$AI85,1)=INDEX($AK$68:$AK$77,MOD($AI85,AJ$65)+1,1),INDEX($AK$68:$AK$77,$AI85,1)="Early"),MOD($AI85,AJ$65)+1,$AI85) -> 8 | AK85: =IF($K85<$AN85,"Dry",IF($K85<$AO85,"Early",IF($K85<$AP85,"Late","Dry"))) -> Dry | AL85: =IF($AK85="Early",$F85-$AN85,IF($AK85="Late",$F85-$AO85,$F85-$AP85)) -> 36 | AN85: =INDEX(i_break_date,$E85+2,1) -> 43589 | AO85: =AO84 -> 43684 | AP85: =INDEX(Periods!$F$21:$O$31,INDEX(Annual!EndGS,1,$E85+2)+2,$E85+2) -> 43758
C86: =INT($C$29)+3 -> 4 | E86: 0 | F86: =$K86+364*($K86<$AN86) -> 43831 | J86: 8 | K86: =INDEX(Periods!$F$21:$O$30,J86+1,$E86+2) -> 43831 | L86: =IF(K87-K86>0,K87-K86,OFFSET(K87,-i_p6_len,0)+365-K86) -> 45 | M86: {=INDEX(M$68:M$77,$AI86,1)*(1-$AH86)+INDEX(M$68:M$77,$AJ86,1)*($AH86)} -> 3.5675676 | N86: {=INDEX(N$68:N$77,$AI86,1)*(1-$AH86)+INDEX(N$68:N$77,$AJ86,1)*($AH86)} -> 13.3 | O86: {=INDEX(O$68:O$77,$AI86,1)*(1-$AH86)+INDEX(O$68:O$77,$AJ86,1)*($AH86)} -> 613.51351 | P86: {=INDEX(P$68:P$77,$AI86,1)*(1-$AH86)+INDEX(P$68:P$77,$AJ86,1)*($AH86)} -> 2067.5676 | Q86: {=INDEX(Q$68:Q$77,$AI86,1)*(1-$AH86)+INDEX(Q$68:Q$77,$AJ86,1)*($AH86)} -> 0.53155405 | R86: {=INDEX(R$68:R$77,$AI86,1)*(1-$AH86)+INDEX(R$68:R$77,$AJ86,1)*($AH86)} -> 0.61925676 | S86: {=INDEX([0]!i_pasture_stage_p6z,$J86+1,ROUNDDOWN((ROW($J86)-ROW($J$68))/i_p6_len,0)+1)} -> 1 | T86: {=INDEX(T$68:T$77,$AI86,1)*(1-$AH86)+INDEX(T$68:T$77,$AJ86,1)*($AH86)} -> 0.3 | U86: {=INDEX(U$68:U$77,$AI86,1)*(1-$AH86)+INDEX(U$68:U$77,$AJ86,1)*($AH86)} -> 5 | V86: {=INDEX(V$68:V$77,$AI86,1)*(1-$AH86)+INDEX(V$68:V$77,$AJ86,1)*($AH86)} -> 0.043243243 | X86: {=INDEX(X$68:X$77,$AI86,1)*(1-$AH86)+INDEX(X$68:X$77,$AJ86,1)*($AH86)} -> 0.33 | Y86: {=INDEX(Y$68:Y$77,$AI86,1)*(1-$AH86)+INDEX(Y$68:Y$77,$AJ86,1)*($AH86)} -> 50 | Z86: {=INDEX(Z$68:Z$77,$AI86,1)*(1-$AH86)+INDEX(Z$68:Z$77,$AJ86,1)*($AH86)} -> 50 | AA86: {=INDEX(AA$68:AA$77,$AI86,1)*(1-$AH86)+INDEX(AA$68:AA$77,$AJ86,1)*($AH86)} -> 50 | AB86: {=INDEX(AB$68:AB$77,$AI86,1)*(1-$AH86)+INDEX(AB$68:AB$77,$AJ86,1)*($AH86)} -> 400 | AC86: {=INDEX(AC$68:AC$77,$AI86,1)*(1-$AH86)+INDEX(AC$68:AC$77,$AJ86,1)*($AH86)} -> 400 | AD86: {=INDEX(AD$68:AD$77,$AI86,1)*(1-$AH86)+INDEX(AD$68:AD$77,$AJ86,1)*($AH86)} -> 400 | AE86: {=INDEX(AE$68:AE$77,$AI86,1)*(1-$AH86)+INDEX(AE$68:AE$77,$AJ86,1)*($AH86)} -> 400 | ... AG86: {=INDEX(AG$68:AG$77,$AI86,1)*(1-$AH86)+INDEX(AG$68:AG$77,$AJ86,1)*($AH86)} -> 400 | AH86: =($AL86-INDEX($AL$68:$AL$77,$AI86,1))/INDEX($L$68:$L$77,$AI86,1) -> 0.86486486 | AI86: =MOD(SUMIFS($AM$68:$AM$77,$AK$68:$AK$77,$AK86,$AL$68:$AL$77,"<="&$AL86)-1,$AJ$65)+1 -> 8 | AJ86: =IF(OR(INDEX($AK$68:$AK$77,$AI86,1)=INDEX($AK$68:$AK$77,MOD($AI86,AJ$65)+1,1),INDEX($AK$68:$AK$77,$AI86,1)="Early"),MOD($AI86,AJ$65)+1,$AI86) -> 9 | AK86: =IF($K86<$AN86,"Dry",IF($K86<$AO86,"Early",IF($K86<$AP86,"Late","Dry"))) -> Dry | AL86: =IF($AK86="Early",$F86-$AN86,IF($AK86="Late",$F86-$AO86,$F86-$AP86)) -> 73 | AN86: =INDEX(i_break_date,$E86+2,1) -> 43589 | AO86: =AO85 -> 43684 | AP86: =INDEX(Periods!$F$21:$O$31,INDEX(Annual!EndGS,1,$E86+2)+2,$E86+2) -> 43758
C87: =INT($C$29)+3 -> 4 | E87: 0 | F87: =$K87+364*($K87<$AN87) -> 43876 | J87: 9 | K87: =INDEX(Periods!$F$21:$O$30,J87+1,$E87+2) -> 43876 | L87: =IF(K88-K87>0,K88-K87,OFFSET(K88,-i_p6_len,0)+365-K87) -> 49 | M87: {=INDEX(M$68:M$77,$AI87,1)*(1-$AH87)+INDEX(M$68:M$77,$AJ87,1)*($AH87)} -> 3.5 | N87: {=INDEX(N$68:N$77,$AI87,1)*(1-$AH87)+INDEX(N$68:N$77,$AJ87,1)*($AH87)} -> 13.3 | O87: {=INDEX(O$68:O$77,$AI87,1)*(1-$AH87)+INDEX(O$68:O$77,$AJ87,1)*($AH87)} -> 555.55556 | P87: {=INDEX(P$68:P$77,$AI87,1)*(1-$AH87)+INDEX(P$68:P$77,$AJ87,1)*($AH87)} -> 1555.5556 | Q87: {=INDEX(Q$68:Q$77,$AI87,1)*(1-$AH87)+INDEX(Q$68:Q$77,$AJ87,1)*($AH87)} -> 0.51194444 | R87: {=INDEX(R$68:R$77,$AI87,1)*(1-$AH87)+INDEX(R$68:R$77,$AJ87,1)*($AH87)} -> 0.57472222 | S87: {=INDEX([0]!i_pasture_stage_p6z,$J87+1,ROUNDDOWN((ROW($J87)-ROW($J$68))/i_p6_len,0)+1)} -> 1 | T87: {=INDEX(T$68:T$77,$AI87,1)*(1-$AH87)+INDEX(T$68:T$77,$AJ87,1)*($AH87)} -> 0.3 | U87: {=INDEX(U$68:U$77,$AI87,1)*(1-$AH87)+INDEX(U$68:U$77,$AJ87,1)*($AH87)} -> 5 | V87: {=INDEX(V$68:V$77,$AI87,1)*(1-$AH87)+INDEX(V$68:V$77,$AJ87,1)*($AH87)} -> 0.094444444 | X87: {=INDEX(X$68:X$77,$AI87,1)*(1-$AH87)+INDEX(X$68:X$77,$AJ87,1)*($AH87)} -> 0.33 | Y87: {=INDEX(Y$68:Y$77,$AI87,1)*(1-$AH87)+INDEX(Y$68:Y$77,$AJ87,1)*($AH87)} -> 50 | Z87: {=INDEX(Z$68:Z$77,$AI87,1)*(1-$AH87)+INDEX(Z$68:Z$77,$AJ87,1)*($AH87)} -> 50 | AA87: {=INDEX(AA$68:AA$77,$AI87,1)*(1-$AH87)+INDEX(AA$68:AA$77,$AJ87,1)*($AH87)} -> 50 | AB87: {=INDEX(AB$68:AB$77,$AI87,1)*(1-$AH87)+INDEX(AB$68:AB$77,$AJ87,1)*($AH87)} -> 400 | AC87: {=INDEX(AC$68:AC$77,$AI87,1)*(1-$AH87)+INDEX(AC$68:AC$77,$AJ87,1)*($AH87)} -> 400 | AD87: {=INDEX(AD$68:AD$77,$AI87,1)*(1-$AH87)+INDEX(AD$68:AD$77,$AJ87,1)*($AH87)} -> 400 | AE87: {=INDEX(AE$68:AE$77,$AI87,1)*(1-$AH87)+INDEX(AE$68:AE$77,$AJ87,1)*($AH87)} -> 400 | ... AG87: {=INDEX(AG$68:AG$77,$AI87,1)*(1-$AH87)+INDEX(AG$68:AG$77,$AJ87,1)*($AH87)} -> 400 | AH87: =($AL87-INDEX($AL$68:$AL$77,$AI87,1))/INDEX($L$68:$L$77,$AI87,1) -> 0.88888889 | AI87: =MOD(SUMIFS($AM$68:$AM$77,$AK$68:$AK$77,$AK87,$AL$68:$AL$77,"<="&$AL87)-1,$AJ$65)+1 -> 9 | AJ87: =IF(OR(INDEX($AK$68:$AK$77,$AI87,1)=INDEX($AK$68:$AK$77,MOD($AI87,AJ$65)+1,1),INDEX($AK$68:$AK$77,$AI87,1)="Early"),MOD($AI87,AJ$65)+1,$AI87) -> 10 | AK87: =IF($K87<$AN87,"Dry",IF($K87<$AO87,"Early",IF($K87<$AP87,"Late","Dry"))) -> Dry | AL87: =IF($AK87="Early",$F87-$AN87,IF($AK87="Late",$F87-$AO87,$F87-$AP87)) -> 118 | AN87: =INDEX(i_break_date,$E87+2,1) -> 43589 | AO87: =AO86 -> 43684 | AP87: =INDEX(Periods!$F$21:$O$31,INDEX(Annual!EndGS,1,$E87+2)+2,$E87+2) -> 43758
C88: =INT($C$29)+2 -> 3 | E88: 1 | F88: =$K88+364*($K88<$AN88) -> 43924 | I88: season1 | J88: 0 | K88: =INDEX(Periods!$F$21:$O$30,J88+1,$E88+2) -> 43560 | L88: =IF(K89-K88>0,K89-K88,OFFSET(K89,-i_p6_len,0)+365-K88) -> 29 | M88: {=INDEX(M$68:M$77,$AI88,1)*(1-$AH88)+INDEX(M$68:M$77,$AJ88,1)*($AH88)} -> 3.5 | N88: {=INDEX(N$68:N$77,$AI88,1)*(1-$AH88)+INDEX(N$68:N$77,$AJ88,1)*($AH88)} -> 13.3 | O88: {=INDEX(O$68:O$77,$AI88,1)*(1-$AH88)+INDEX(O$68:O$77,$AJ88,1)*($AH88)} -> 418.36735 | P88: {=INDEX(P$68:P$77,$AI88,1)*(1-$AH88)+INDEX(P$68:P$77,$AJ88,1)*($AH88)} -> 885.71429 | Q88: {=INDEX(Q$68:Q$77,$AI88,1)*(1-$AH88)+INDEX(Q$68:Q$77,$AJ88,1)*($AH88)} -> 0.50122449 | R88: {=INDEX(R$68:R$77,$AI88,1)*(1-$AH88)+INDEX(R$68:R$77,$AJ88,1)*($AH88)} -> 0.54367347 | S88: {=INDEX([0]!i_pasture_stage_p6z,$J88+1,ROUNDDOWN((ROW($J88)-ROW($J$68))/i_p6_len,0)+1)} -> 1 | T88: {=INDEX(T$68:T$77,$AI88,1)*(1-$AH88)+INDEX(T$68:T$77,$AJ88,1)*($AH88)} -> 0.3 | U88: {=INDEX(U$68:U$77,$AI88,1)*(1-$AH88)+INDEX(U$68:U$77,$AJ88,1)*($AH88)} -> 5 | V88: {=INDEX(V$68:V$77,$AI88,1)*(1-$AH88)+INDEX(V$68:V$77,$AJ88,1)*($AH88)} -> 0.1 | X88: {=INDEX(X$68:X$77,$AI88,1)*(1-$AH88)+INDEX(X$68:X$77,$AJ88,1)*($AH88)} -> 0.91795918 | Y88: {=INDEX(Y$68:Y$77,$AI88,1)*(1-$AH88)+INDEX(Y$68:Y$77,$AJ88,1)*($AH88)} -> 50 | Z88: {=INDEX(Z$68:Z$77,$AI88,1)*(1-$AH88)+INDEX(Z$68:Z$77,$AJ88,1)*($AH88)} -> 50 | AA88: {=INDEX(AA$68:AA$77,$AI88,1)*(1-$AH88)+INDEX(AA$68:AA$77,$AJ88,1)*($AH88)} -> 50 | AB88: {=INDEX(AB$68:AB$77,$AI88,1)*(1-$AH88)+INDEX(AB$68:AB$77,$AJ88,1)*($AH88)} -> 136.73469 | AC88: {=INDEX(AC$68:AC$77,$AI88,1)*(1-$AH88)+INDEX(AC$68:AC$77,$AJ88,1)*($AH88)} -> 400 | AD88: {=INDEX(AD$68:AD$77,$AI88,1)*(1-$AH88)+INDEX(AD$68:AD$77,$AJ88,1)*($AH88)} -> 400 | AE88: {=INDEX(AE$68:AE$77,$AI88,1)*(1-$AH88)+INDEX(AE$68:AE$77,$AJ88,1)*($AH88)} -> 400 | ... AG88: {=INDEX(AG$68:AG$77,$AI88,1)*(1-$AH88)+INDEX(AG$68:AG$77,$AJ88,1)*($AH88)} -> 400 | AH88: =($AL88-INDEX($AL$68:$AL$77,$AI88,1))/INDEX($L$68:$L$77,$AI88,1) -> 0.87755102 | AI88: =MOD(SUMIFS($AM$68:$AM$77,$AK$68:$AK$77,$AK88,$AL$68:$AL$77,"<="&$AL88)-1,$AJ$65)+1 -> 10 | AJ88: =IF(OR(INDEX($AK$68:$AK$77,$AI88,1)=INDEX($AK$68:$AK$77,MOD($AI88,AJ$65)+1,1),INDEX($AK$68:$AK$77,$AI88,1)="Early"),MOD($AI88,AJ$65)+1,$AI88) -> 1 | AK88: =IF($K88<$AN88,"Dry",IF($K88<$AO88,"Early",IF($K88<$AP88,"Late","Dry"))) -> Dry | AL88: =IF($AK88="Early",$F88-$AN88,IF($AK88="Late",$F88-$AO88,$F88-$AP88)) -> 166 | AN88: =INDEX(i_break_date,$E88+2,1) -> 43589 | AO88: =AO87 -> 43684 | AP88: =INDEX(Periods!$F$21:$O$31,INDEX(Annual!EndGS,1,$E88+2)+2,$E88+2) -> 43758
C89: =INT($C$29)+3 -> 4 | E89: 1 | F89: =$K89+364*($K89<$AN89) -> 43589 | J89: 1 | K89: =INDEX(Periods!$F$21:$O$30,J89+1,$E89+2) -> 43589 | L89: =IF(K90-K89>0,K90-K89,OFFSET(K90,-i_p6_len,0)+365-K89) -> 42 | M89: {=INDEX(M$68:M$77,$AI89,1)*(1-$AH89)+INDEX(M$68:M$77,$AJ89,1)*($AH89)} -> 4 | N89: {=INDEX(N$68:N$77,$AI89,1)*(1-$AH89)+INDEX(N$68:N$77,$AJ89,1)*($AH89)} -> 13.3 | O89: {=INDEX(O$68:O$77,$AI89,1)*(1-$AH89)+INDEX(O$68:O$77,$AJ89,1)*($AH89)} -> 125 | P89: {=INDEX(P$68:P$77,$AI89,1)*(1-$AH89)+INDEX(P$68:P$77,$AJ89,1)*($AH89)} -> 350 | Q89: {=INDEX(Q$68:Q$77,$AI89,1)*(1-$AH89)+INDEX(Q$68:Q$77,$AJ89,1)*($AH89)} -> 0.81 | R89: {=INDEX(R$68:R$77,$AI89,1)*(1-$AH89)+INDEX(R$68:R$77,$AJ89,1)*($AH89)} -> 0.81 | S89: {=INDEX([0]!i_pasture_stage_p6z,$J89+1,ROUNDDOWN((ROW($J89)-ROW($J$68))/i_p6_len,0)+1)} -> 0.28571429 | T89: {=INDEX(T$68:T$77,$AI89,1)*(1-$AH89)+INDEX(T$68:T$77,$AJ89,1)*($AH89)} -> 0.3 | U89: {=INDEX(U$68:U$77,$AI89,1)*(1-$AH89)+INDEX(U$68:U$77,$AJ89,1)*($AH89)} -> 5 | V89: {=INDEX(V$68:V$77,$AI89,1)*(1-$AH89)+INDEX(V$68:V$77,$AJ89,1)*($AH89)} -> 0 | X89: {=INDEX(X$68:X$77,$AI89,1)*(1-$AH89)+INDEX(X$68:X$77,$AJ89,1)*($AH89)} -> 1 | Y89: {=INDEX(Y$68:Y$77,$AI89,1)*(1-$AH89)+INDEX(Y$68:Y$77,$AJ89,1)*($AH89)} -> 50 | Z89: {=INDEX(Z$68:Z$77,$AI89,1)*(1-$AH89)+INDEX(Z$68:Z$77,$AJ89,1)*($AH89)} -> 50 | AA89: {=INDEX(AA$68:AA$77,$AI89,1)*(1-$AH89)+INDEX(AA$68:AA$77,$AJ89,1)*($AH89)} -> 50 | AB89: {=INDEX(AB$68:AB$77,$AI89,1)*(1-$AH89)+INDEX(AB$68:AB$77,$AJ89,1)*($AH89)} -> 100 | AC89: {=INDEX(AC$68:AC$77,$AI89,1)*(1-$AH89)+INDEX(AC$68:AC$77,$AJ89,1)*($AH89)} -> 150 | AD89: {=INDEX(AD$68:AD$77,$AI89,1)*(1-$AH89)+INDEX(AD$68:AD$77,$AJ89,1)*($AH89)} -> 150 | AE89: {=INDEX(AE$68:AE$77,$AI89,1)*(1-$AH89)+INDEX(AE$68:AE$77,$AJ89,1)*($AH89)} -> 400 | ... AG89: {=INDEX(AG$68:AG$77,$AI89,1)*(1-$AH89)+INDEX(AG$68:AG$77,$AJ89,1)*($AH89)} -> 400 | AH89: =($AL89-INDEX($AL$68:$AL$77,$AI89,1))/INDEX($L$68:$L$77,$AI89,1) -> 0 | AI89: =MOD(SUMIFS($AM$68:$AM$77,$AK$68:$AK$77,$AK89,$AL$68:$AL$77,"<="&$AL89)-1,$AJ$65)+1 -> 2 | AJ89: =IF(OR(INDEX($AK$68:$AK$77,$AI89,1)=INDEX($AK$68:$AK$77,MOD($AI89,AJ$65)+1,1),INDEX($AK$68:$AK$77,$AI89,1)="Early"),MOD($AI89,AJ$65)+1,$AI89) -> 3 | AK89: =IF($K89<$AN89,"Dry",IF($K89<$AO89,"Early",IF($K89<$AP89,"Late","Dry"))) -> Early | AL89: =IF($AK89="Early",$F89-$AN89,IF($AK89="Late",$F89-$AO89,$F89-$AP89)) -> 0 | AN89: =INDEX(i_break_date,$E89+2,1) -> 43589 | AO89: =AO88 -> 43684 | AP89: =INDEX(Periods!$F$21:$O$31,INDEX(Annual!EndGS,1,$E89+2)+2,$E89+2) -> 43758
